Compiled from SourceFile
public class el extends java.lang.Object implements io{
public boolean a;

public java.util.List b;

public java.util.List c;

public java.util.List d;

public long e;

public int f;

protected int g;

protected int h;

public boolean i;

protected int j;

public int k;

public java.util.Random l;

public int m;

public int n;

public int o;

public boolean p;

public final ie q;

protected java.util.List r;

public java.io.File s;

public java.io.File t;

public long u;

public long v;

public final java.lang.String w;

public boolean x;

static int y;

public boolean z;

public is a();
  Code:
   0:	aload_0
   1:	getfield	#174; //Field q:Lie;
   4:	getfield	#199; //Field ie.b:Lis;
   7:	areturn

public el(java.io.File, java.lang.String, long, ie);
  Code:
   0:	aload_0
   1:	invokespecial	#324; //Method java/lang/Object."<init>":()V
   4:	aload_0
   5:	iconst_0
   6:	putfield	#159; //Field a:Z
   9:	aload_0
   10:	new	#74; //class java/util/ArrayList
   13:	dup
   14:	invokespecial	#332; //Method java/util/ArrayList."<init>":()V
   17:	putfield	#146; //Field A:Ljava/util/List;
   20:	aload_0
   21:	new	#74; //class java/util/ArrayList
   24:	dup
   25:	invokespecial	#332; //Method java/util/ArrayList."<init>":()V
   28:	putfield	#160; //Field b:Ljava/util/List;
   31:	aload_0
   32:	new	#74; //class java/util/ArrayList
   35:	dup
   36:	invokespecial	#332; //Method java/util/ArrayList."<init>":()V
   39:	putfield	#147; //Field B:Ljava/util/List;
   42:	aload_0
   43:	new	#80; //class java/util/TreeSet
   46:	dup
   47:	invokespecial	#340; //Method java/util/TreeSet."<init>":()V
   50:	putfield	#148; //Field C:Ljava/util/TreeSet;
   53:	aload_0
   54:	new	#75; //class java/util/HashSet
   57:	dup
   58:	invokespecial	#335; //Method java/util/HashSet."<init>":()V
   61:	putfield	#149; //Field D:Ljava/util/Set;
   64:	aload_0
   65:	new	#74; //class java/util/ArrayList
   68:	dup
   69:	invokespecial	#332; //Method java/util/ArrayList."<init>":()V
   72:	putfield	#161; //Field c:Ljava/util/List;
   75:	aload_0
   76:	new	#74; //class java/util/ArrayList
   79:	dup
   80:	invokespecial	#332; //Method java/util/ArrayList."<init>":()V
   83:	putfield	#162; //Field d:Ljava/util/List;
   86:	aload_0
   87:	lconst_0
   88:	putfield	#163; //Field e:J
   91:	aload_0
   92:	ldc2_w	#86; //long 16777215l
   95:	putfield	#150; //Field E:J
   98:	aload_0
   99:	iconst_0
   100:	putfield	#164; //Field f:I
   103:	aload_0
   104:	new	#78; //class java/util/Random
   107:	dup
   108:	invokespecial	#336; //Method java/util/Random."<init>":()V
   111:	invokevirtual	#338; //Method java/util/Random.nextInt:()I
   114:	putfield	#165; //Field g:I
   117:	aload_0
   118:	ldc	#4; //int 1013904223
   120:	putfield	#166; //Field h:I
   123:	aload_0
   124:	iconst_0
   125:	putfield	#167; //Field i:Z
   128:	aload_0
   129:	invokestatic	#331; //Method java/lang/System.currentTimeMillis:()J
   132:	putfield	#151; //Field F:J
   135:	aload_0
   136:	bipush	40
   138:	putfield	#168; //Field j:I
   141:	aload_0
   142:	new	#78; //class java/util/Random
   145:	dup
   146:	invokespecial	#336; //Method java/util/Random."<init>":()V
   149:	putfield	#169; //Field l:Ljava/util/Random;
   152:	aload_0
   153:	iconst_0
   154:	putfield	#173; //Field p:Z
   157:	aload_0
   158:	new	#74; //class java/util/ArrayList
   161:	dup
   162:	invokespecial	#332; //Method java/util/ArrayList."<init>":()V
   165:	putfield	#175; //Field r:Ljava/util/List;
   168:	aload_0
   169:	lconst_0
   170:	putfield	#178; //Field u:J
   173:	aload_0
   174:	lconst_0
   175:	putfield	#179; //Field v:J
   178:	aload_0
   179:	new	#74; //class java/util/ArrayList
   182:	dup
   183:	invokespecial	#332; //Method java/util/ArrayList."<init>":()V
   186:	putfield	#154; //Field I:Ljava/util/ArrayList;
   189:	aload_0
   190:	iconst_0
   191:	putfield	#155; //Field J:I
   194:	aload_0
   195:	new	#75; //class java/util/HashSet
   198:	dup
   199:	invokespecial	#335; //Method java/util/HashSet."<init>":()V
   202:	putfield	#156; //Field K:Ljava/util/Set;
   205:	aload_0
   206:	aload_0
   207:	getfield	#169; //Field l:Ljava/util/Random;
   210:	sipush	12000
   213:	invokevirtual	#339; //Method java/util/Random.nextInt:(I)I
   216:	putfield	#157; //Field L:I
   219:	aload_0
   220:	new	#74; //class java/util/ArrayList
   223:	dup
   224:	invokespecial	#332; //Method java/util/ArrayList."<init>":()V
   227:	putfield	#158; //Field M:Ljava/util/List;
   230:	aload_0
   231:	iconst_0
   232:	putfield	#183; //Field z:Z
   235:	aload_0
   236:	aload_1
   237:	putfield	#176; //Field s:Ljava/io/File;
   240:	aload_0
   241:	aload_2
   242:	putfield	#180; //Field w:Ljava/lang/String;
   245:	aload_1
   246:	invokevirtual	#313; //Method java/io/File.mkdirs:()Z
   249:	pop
   250:	aload_0
   251:	new	#61; //class java/io/File
   254:	dup
   255:	aload_1
   256:	aload_2
   257:	invokespecial	#310; //Method java/io/File."<init>":(Ljava/io/File;Ljava/lang/String;)V
   260:	putfield	#177; //Field t:Ljava/io/File;
   263:	aload_0
   264:	getfield	#177; //Field t:Ljava/io/File;
   267:	invokevirtual	#313; //Method java/io/File.mkdirs:()Z
   270:	pop
   271:	new	#61; //class java/io/File
   274:	dup
   275:	aload_0
   276:	getfield	#177; //Field t:Ljava/io/File;
   279:	ldc	#33; //String session.lock
   281:	invokespecial	#310; //Method java/io/File."<init>":(Ljava/io/File;Ljava/lang/String;)V
   284:	astore	6
   286:	new	#60; //class java/io/DataOutputStream
   289:	dup
   290:	new	#63; //class java/io/FileOutputStream
   293:	dup
   294:	aload	6
   296:	invokespecial	#316; //Method java/io/FileOutputStream."<init>":(Ljava/io/File;)V
   299:	invokespecial	#307; //Method java/io/DataOutputStream."<init>":(Ljava/io/OutputStream;)V
   302:	astore	7
   304:	aload	7
   306:	aload_0
   307:	getfield	#151; //Field F:J
   310:	invokevirtual	#309; //Method java/io/DataOutputStream.writeLong:(J)V
   313:	aload	7
   315:	invokevirtual	#308; //Method java/io/DataOutputStream.close:()V
   318:	goto	331
   321:	astore	8
   323:	aload	7
   325:	invokevirtual	#308; //Method java/io/DataOutputStream.close:()V
   328:	aload	8
   330:	athrow
   331:	goto	351
   334:	astore	6
   336:	aload	6
   338:	invokevirtual	#317; //Method java/io/IOException.printStackTrace:()V
   341:	new	#71; //class java/lang/RuntimeException
   344:	dup
   345:	ldc	#15; //String Failed to check session lock, aborting
   347:	invokespecial	#326; //Method java/lang/RuntimeException."<init>":(Ljava/lang/String;)V
   350:	athrow
   351:	new	#55; //class ie
   354:	dup
   355:	invokespecial	#297; //Method ie."<init>":()V
   358:	astore	6
   360:	new	#61; //class java/io/File
   363:	dup
   364:	aload_0
   365:	getfield	#177; //Field t:Ljava/io/File;
   368:	ldc	#30; //String level.dat
   370:	invokespecial	#310; //Method java/io/File."<init>":(Ljava/io/File;Ljava/lang/String;)V
   373:	astore	7
   375:	aload_0
   376:	aload	7
   378:	invokevirtual	#312; //Method java/io/File.exists:()Z
   381:	ifne	388
   384:	iconst_1
   385:	goto	389
   388:	iconst_0
   389:	putfield	#173; //Field p:Z
   392:	aload	7
   394:	invokevirtual	#312; //Method java/io/File.exists:()Z
   397:	ifeq	546
   400:	new	#62; //class java/io/FileInputStream
   403:	dup
   404:	aload	7
   406:	invokespecial	#315; //Method java/io/FileInputStream."<init>":(Ljava/io/File;)V
   409:	invokestatic	#208; //Method am.a:(Ljava/io/InputStream;)Lt;
   412:	astore	8
   414:	aload	8
   416:	ldc	#13; //String Data
   418:	invokevirtual	#376; //Method t.j:(Ljava/lang/String;)Lt;
   421:	astore	9
   423:	aload_0
   424:	aload	9
   426:	ldc	#19; //String RandomSeed
   428:	invokevirtual	#375; //Method t.e:(Ljava/lang/String;)J
   431:	putfield	#178; //Field u:J
   434:	aload_0
   435:	aload	9
   437:	ldc	#23; //String SpawnX
   439:	invokevirtual	#374; //Method t.d:(Ljava/lang/String;)I
   442:	putfield	#170; //Field m:I
   445:	aload_0
   446:	aload	9
   448:	ldc	#24; //String SpawnY
   450:	invokevirtual	#374; //Method t.d:(Ljava/lang/String;)I
   453:	putfield	#171; //Field n:I
   456:	aload_0
   457:	aload	9
   459:	ldc	#25; //String SpawnZ
   461:	invokevirtual	#374; //Method t.d:(Ljava/lang/String;)I
   464:	putfield	#172; //Field o:I
   467:	aload_0
   468:	aload	9
   470:	ldc	#28; //String Time
   472:	invokevirtual	#375; //Method t.e:(Ljava/lang/String;)J
   475:	putfield	#163; //Field e:J
   478:	aload_0
   479:	aload	9
   481:	ldc	#22; //String SizeOnDisk
   483:	invokevirtual	#375; //Method t.e:(Ljava/lang/String;)J
   486:	putfield	#179; //Field v:J
   489:	aload	9
   491:	ldc	#17; //String Player
   493:	invokevirtual	#369; //Method t.a:(Ljava/lang/String;)Z
   496:	ifeq	536
   499:	aload_0
   500:	aload	9
   502:	ldc	#17; //String Player
   504:	invokevirtual	#376; //Method t.j:(Ljava/lang/String;)Lt;
   507:	putfield	#153; //Field H:Lt;
   510:	aload_0
   511:	getfield	#153; //Field H:Lt;
   514:	ldc	#14; //String Dimension
   516:	invokevirtual	#374; //Method t.d:(Ljava/lang/String;)I
   519:	istore	10
   521:	iload	10
   523:	iconst_m1
   524:	if_icmpne	536
   527:	new	#54; //class hk
   530:	dup
   531:	invokespecial	#296; //Method hk."<init>":()V
   534:	astore	6
   536:	goto	546
   539:	astore	8
   541:	aload	8
   543:	invokevirtual	#322; //Method java/lang/Exception.printStackTrace:()V
   546:	aload	5
   548:	ifnull	555
   551:	aload	5
   553:	astore	6
   555:	iconst_0
   556:	istore	8
   558:	aload_0
   559:	getfield	#178; //Field u:J
   562:	lconst_0
   563:	lcmp
   564:	ifne	575
   567:	aload_0
   568:	lload_3
   569:	putfield	#178; //Field u:J
   572:	iconst_1
   573:	istore	8
   575:	aload_0
   576:	aload	6
   578:	putfield	#174; //Field q:Lie;
   581:	aload_0
   582:	getfield	#174; //Field q:Lie;
   585:	aload_0
   586:	invokevirtual	#300; //Method ie.a:(Lel;)V
   589:	aload_0
   590:	aload_0
   591:	aload_0
   592:	getfield	#177; //Field t:Ljava/io/File;
   595:	invokevirtual	#246; //Method a:(Ljava/io/File;)Lbr;
   598:	putfield	#152; //Field G:Lbr;
   601:	iload	8
   603:	ifeq	709
   606:	aload_0
   607:	iconst_1
   608:	putfield	#181; //Field x:Z
   611:	aload_0
   612:	iconst_0
   613:	putfield	#170; //Field m:I
   616:	aload_0
   617:	bipush	64
   619:	putfield	#171; //Field n:I
   622:	aload_0
   623:	iconst_0
   624:	putfield	#172; //Field o:I
   627:	aload_0
   628:	getfield	#174; //Field q:Lie;
   631:	aload_0
   632:	getfield	#170; //Field m:I
   635:	aload_0
   636:	getfield	#172; //Field o:I
   639:	invokevirtual	#298; //Method ie.a:(II)Z
   642:	ifne	704
   645:	aload_0
   646:	dup
   647:	getfield	#170; //Field m:I
   650:	aload_0
   651:	getfield	#169; //Field l:Ljava/util/Random;
   654:	bipush	64
   656:	invokevirtual	#339; //Method java/util/Random.nextInt:(I)I
   659:	aload_0
   660:	getfield	#169; //Field l:Ljava/util/Random;
   663:	bipush	64
   665:	invokevirtual	#339; //Method java/util/Random.nextInt:(I)I
   668:	isub
   669:	iadd
   670:	putfield	#170; //Field m:I
   673:	aload_0
   674:	dup
   675:	getfield	#172; //Field o:I
   678:	aload_0
   679:	getfield	#169; //Field l:Ljava/util/Random;
   682:	bipush	64
   684:	invokevirtual	#339; //Method java/util/Random.nextInt:(I)I
   687:	aload_0
   688:	getfield	#169; //Field l:Ljava/util/Random;
   691:	bipush	64
   693:	invokevirtual	#339; //Method java/util/Random.nextInt:(I)I
   696:	isub
   697:	iadd
   698:	putfield	#172; //Field o:I
   701:	goto	627
   704:	aload_0
   705:	iconst_0
   706:	putfield	#181; //Field x:Z
   709:	aload_0
   710:	invokevirtual	#260; //Method e:()V
   713:	return
  Exception table:
   from   to  target type
   304   313   321   any
   321   323   321   any
   271   331   334   Class java/io/IOException

   400   536   539   Class java/lang/Exception


protected br a(java.io.File);
  Code:
   0:	new	#57; //class iu
   3:	dup
   4:	aload_0
   5:	aload_0
   6:	getfield	#174; //Field q:Lie;
   9:	aload_1
   10:	invokevirtual	#301; //Method ie.a:(Ljava/io/File;)Lat;
   13:	aload_0
   14:	getfield	#174; //Field q:Lie;
   17:	invokevirtual	#302; //Method ie.c:()Lbr;
   20:	invokespecial	#303; //Method iu."<init>":(Lel;Lat;Lbr;)V
   23:	areturn

public int a(int, int);
  Code:
   0:	bipush	63
   2:	istore_3
   3:	aload_0
   4:	iload_1
   5:	iload_3
   6:	iconst_1
   7:	iadd
   8:	iload_2
   9:	invokevirtual	#234; //Method a:(III)I
   12:	ifeq	21
   15:	iinc	3, 1
   18:	goto	3
   21:	aload_0
   22:	iload_1
   23:	iload_3
   24:	iload_2
   25:	invokevirtual	#234; //Method a:(III)I
   28:	ireturn

public void a(boolean, iv);
  Code:
   0:	aload_0
   1:	getfield	#152; //Field G:Lbr;
   4:	invokeinterface	#389,  1; //InterfaceMethod br.b:()Z
   9:	ifne	13
   12:	return
   13:	aload_2
   14:	ifnull	25
   17:	aload_2
   18:	ldc	#21; //String Saving level
   20:	invokeinterface	#391,  2; //InterfaceMethod iv.a:(Ljava/lang/String;)V
   25:	aload_0
   26:	invokespecial	#270; //Method i:()V
   29:	aload_2
   30:	ifnull	41
   33:	aload_2
   34:	ldc	#20; //String Saving chunks
   36:	invokeinterface	#392,  2; //InterfaceMethod iv.b:(Ljava/lang/String;)V
   41:	aload_0
   42:	getfield	#152; //Field G:Lbr;
   45:	iload_1
   46:	aload_2
   47:	invokeinterface	#388,  3; //InterfaceMethod br.a:(ZLiv;)Z
   52:	pop
   53:	return

public int a(int, int, int);
  Code:
   0:	iload_1
   1:	ldc	#1; //int -32000000
   3:	if_icmplt	24
   6:	iload_3
   7:	ldc	#1; //int -32000000
   9:	if_icmplt	24
   12:	iload_1
   13:	ldc	#3; //int 32000000
   15:	if_icmpge	24
   18:	iload_3
   19:	ldc	#3; //int 32000000
   21:	if_icmple	26
   24:	iconst_0
   25:	ireturn
   26:	iload_2
   27:	ifge	32
   30:	iconst_0
   31:	ireturn
   32:	iload_2
   33:	sipush	128
   36:	if_icmplt	41
   39:	iconst_0
   40:	ireturn
   41:	aload_0
   42:	iload_1
   43:	iconst_4
   44:	ishr
   45:	iload_3
   46:	iconst_4
   47:	ishr
   48:	invokevirtual	#255; //Method c:(II)Ljn;
   51:	iload_1
   52:	bipush	15
   54:	iand
   55:	iload_2
   56:	iload_3
   57:	bipush	15
   59:	iand
   60:	invokevirtual	#345; //Method jn.a:(III)I
   63:	ireturn

public boolean e(int, int, int);
  Code:
   0:	iload_2
   1:	iflt	11
   4:	iload_2
   5:	sipush	128
   8:	if_icmplt	13
   11:	iconst_0
   12:	ireturn
   13:	aload_0
   14:	iload_1
   15:	iconst_4
   16:	ishr
   17:	iload_3
   18:	iconst_4
   19:	ishr
   20:	invokespecial	#264; //Method f:(II)Z
   23:	ireturn

public boolean a(int, int, int, int, int, int);
  Code:
   0:	iload	5
   2:	iflt	12
   5:	iload_2
   6:	sipush	128
   9:	if_icmplt	14
   12:	iconst_0
   13:	ireturn
   14:	iload_1
   15:	iconst_4
   16:	ishr
   17:	istore_1
   18:	iload_2
   19:	iconst_4
   20:	ishr
   21:	istore_2
   22:	iload_3
   23:	iconst_4
   24:	ishr
   25:	istore_3
   26:	iload	4
   28:	iconst_4
   29:	ishr
   30:	istore	4
   32:	iload	5
   34:	iconst_4
   35:	ishr
   36:	istore	5
   38:	iload	6
   40:	iconst_4
   41:	ishr
   42:	istore	6
   44:	iload_1
   45:	istore	7
   47:	iload	7
   49:	iload	4
   51:	if_icmpgt	89
   54:	iload_3
   55:	istore	8
   57:	iload	8
   59:	iload	6
   61:	if_icmpgt	83
   64:	aload_0
   65:	iload	7
   67:	iload	8
   69:	invokespecial	#264; //Method f:(II)Z
   72:	ifne	77
   75:	iconst_0
   76:	ireturn
   77:	iinc	8, 1
   80:	goto	57
   83:	iinc	7, 1
   86:	goto	47
   89:	iconst_1
   90:	ireturn

public jn b(int, int);
  Code:
   0:	aload_0
   1:	iload_1
   2:	iconst_4
   3:	ishr
   4:	iload_2
   5:	iconst_4
   6:	ishr
   7:	invokevirtual	#255; //Method c:(II)Ljn;
   10:	areturn

public jn c(int, int);
  Code:
   0:	aload_0
   1:	getfield	#152; //Field G:Lbr;
   4:	iload_1
   5:	iload_2
   6:	invokeinterface	#390,  3; //InterfaceMethod br.b:(II)Ljn;
   11:	areturn

public boolean a(int, int, int, int, int);
  Code:
   0:	iload_1
   1:	ldc	#1; //int -32000000
   3:	if_icmplt	24
   6:	iload_3
   7:	ldc	#1; //int -32000000
   9:	if_icmplt	24
   12:	iload_1
   13:	ldc	#3; //int 32000000
   15:	if_icmpge	24
   18:	iload_3
   19:	ldc	#3; //int 32000000
   21:	if_icmple	26
   24:	iconst_0
   25:	ireturn
   26:	iload_2
   27:	ifge	32
   30:	iconst_0
   31:	ireturn
   32:	iload_2
   33:	sipush	128
   36:	if_icmplt	41
   39:	iconst_0
   40:	ireturn
   41:	aload_0
   42:	iload_1
   43:	iconst_4
   44:	ishr
   45:	iload_3
   46:	iconst_4
   47:	ishr
   48:	invokevirtual	#255; //Method c:(II)Ljn;
   51:	astore	6
   53:	aload	6
   55:	iload_1
   56:	bipush	15
   58:	iand
   59:	iload_2
   60:	iload_3
   61:	bipush	15
   63:	iand
   64:	iload	4
   66:	iload	5
   68:	invokevirtual	#347; //Method jn.a:(IIIII)Z
   71:	ireturn

public boolean a(int, int, int, int);
  Code:
   0:	iload_1
   1:	ldc	#1; //int -32000000
   3:	if_icmplt	24
   6:	iload_3
   7:	ldc	#1; //int -32000000
   9:	if_icmplt	24
   12:	iload_1
   13:	ldc	#3; //int 32000000
   15:	if_icmpge	24
   18:	iload_3
   19:	ldc	#3; //int 32000000
   21:	if_icmple	26
   24:	iconst_0
   25:	ireturn
   26:	iload_2
   27:	ifge	32
   30:	iconst_0
   31:	ireturn
   32:	iload_2
   33:	sipush	128
   36:	if_icmplt	41
   39:	iconst_0
   40:	ireturn
   41:	aload_0
   42:	iload_1
   43:	iconst_4
   44:	ishr
   45:	iload_3
   46:	iconst_4
   47:	ishr
   48:	invokevirtual	#255; //Method c:(II)Ljn;
   51:	astore	5
   53:	aload	5
   55:	iload_1
   56:	bipush	15
   58:	iand
   59:	iload_2
   60:	iload_3
   61:	bipush	15
   63:	iand
   64:	iload	4
   66:	invokevirtual	#346; //Method jn.a:(IIII)Z
   69:	ireturn

public jr c(int, int, int);
  Code:
   0:	aload_0
   1:	iload_1
   2:	iload_2
   3:	iload_3
   4:	invokevirtual	#234; //Method a:(III)I
   7:	istore	4
   9:	iload	4
   11:	ifne	18
   14:	getstatic	#205; //Field jr.a:Ljr;
   17:	areturn
   18:	getstatic	#196; //Field fw.n:[Lfw;
   21:	iload	4
   23:	aaload
   24:	getfield	#195; //Field fw.bt:Ljr;
   27:	areturn

public int b(int, int, int);
  Code:
   0:	iload_1
   1:	ldc	#1; //int -32000000
   3:	if_icmplt	24
   6:	iload_3
   7:	ldc	#1; //int -32000000
   9:	if_icmplt	24
   12:	iload_1
   13:	ldc	#3; //int 32000000
   15:	if_icmpge	24
   18:	iload_3
   19:	ldc	#3; //int 32000000
   21:	if_icmple	26
   24:	iconst_0
   25:	ireturn
   26:	iload_2
   27:	ifge	32
   30:	iconst_0
   31:	ireturn
   32:	iload_2
   33:	sipush	128
   36:	if_icmplt	41
   39:	iconst_0
   40:	ireturn
   41:	aload_0
   42:	iload_1
   43:	iconst_4
   44:	ishr
   45:	iload_3
   46:	iconst_4
   47:	ishr
   48:	invokevirtual	#255; //Method c:(II)Ljn;
   51:	astore	4
   53:	iload_1
   54:	bipush	15
   56:	iand
   57:	istore_1
   58:	iload_3
   59:	bipush	15
   61:	iand
   62:	istore_3
   63:	aload	4
   65:	iload_1
   66:	iload_2
   67:	iload_3
   68:	invokevirtual	#357; //Method jn.b:(III)I
   71:	ireturn

public void b(int, int, int, int);
  Code:
   0:	aload_0
   1:	iload_1
   2:	iload_2
   3:	iload_3
   4:	iload	4
   6:	invokevirtual	#257; //Method c:(IIII)Z
   9:	ifeq	26
   12:	aload_0
   13:	iload_1
   14:	iload_2
   15:	iload_3
   16:	aload_0
   17:	iload_1
   18:	iload_2
   19:	iload_3
   20:	invokevirtual	#234; //Method a:(III)I
   23:	invokevirtual	#262; //Method e:(IIII)V
   26:	return

public boolean c(int, int, int, int);
  Code:
   0:	iload_1
   1:	ldc	#1; //int -32000000
   3:	if_icmplt	24
   6:	iload_3
   7:	ldc	#1; //int -32000000
   9:	if_icmplt	24
   12:	iload_1
   13:	ldc	#3; //int 32000000
   15:	if_icmpge	24
   18:	iload_3
   19:	ldc	#3; //int 32000000
   21:	if_icmple	26
   24:	iconst_0
   25:	ireturn
   26:	iload_2
   27:	ifge	32
   30:	iconst_0
   31:	ireturn
   32:	iload_2
   33:	sipush	128
   36:	if_icmplt	41
   39:	iconst_0
   40:	ireturn
   41:	aload_0
   42:	iload_1
   43:	iconst_4
   44:	ishr
   45:	iload_3
   46:	iconst_4
   47:	ishr
   48:	invokevirtual	#255; //Method c:(II)Ljn;
   51:	astore	5
   53:	iload_1
   54:	bipush	15
   56:	iand
   57:	istore_1
   58:	iload_3
   59:	bipush	15
   61:	iand
   62:	istore_3
   63:	aload	5
   65:	iload_1
   66:	iload_2
   67:	iload_3
   68:	iload	4
   70:	invokevirtual	#358; //Method jn.b:(IIII)V
   73:	iconst_1
   74:	ireturn

public boolean d(int, int, int, int);
  Code:
   0:	aload_0
   1:	iload_1
   2:	iload_2
   3:	iload_3
   4:	iload	4
   6:	invokevirtual	#235; //Method a:(IIII)Z
   9:	ifeq	23
   12:	aload_0
   13:	iload_1
   14:	iload_2
   15:	iload_3
   16:	iload	4
   18:	invokevirtual	#262; //Method e:(IIII)V
   21:	iconst_1
   22:	ireturn
   23:	iconst_0
   24:	ireturn

public boolean b(int, int, int, int, int);
  Code:
   0:	aload_0
   1:	iload_1
   2:	iload_2
   3:	iload_3
   4:	iload	4
   6:	iload	5
   8:	invokevirtual	#236; //Method a:(IIIII)Z
   11:	ifeq	25
   14:	aload_0
   15:	iload_1
   16:	iload_2
   17:	iload_3
   18:	iload	4
   20:	invokevirtual	#262; //Method e:(IIII)V
   23:	iconst_1
   24:	ireturn
   25:	iconst_0
   26:	ireturn

public void f(int, int, int);
  Code:
   0:	iconst_0
   1:	istore	4
   3:	iload	4
   5:	aload_0
   6:	getfield	#175; //Field r:Ljava/util/List;
   9:	invokeinterface	#402,  1; //InterfaceMethod java/util/List.size:()I
   14:	if_icmpge	45
   17:	aload_0
   18:	getfield	#175; //Field r:Ljava/util/List;
   21:	iload	4
   23:	invokeinterface	#398,  2; //InterfaceMethod java/util/List.get:(I)Ljava/lang/Object;
   28:	checkcast	#37; //class bj
   31:	iload_1
   32:	iload_2
   33:	iload_3
   34:	invokeinterface	#378,  4; //InterfaceMethod bj.a:(III)V
   39:	iinc	4, 1
   42:	goto	3
   45:	return

protected void e(int, int, int, int);
  Code:
   0:	aload_0
   1:	iload_1
   2:	iload_2
   3:	iload_3
   4:	invokevirtual	#265; //Method f:(III)V
   7:	aload_0
   8:	iload_1
   9:	iload_2
   10:	iload_3
   11:	iload	4
   13:	invokevirtual	#267; //Method g:(IIII)V
   16:	return

public void f(int, int, int, int);
  Code:
   0:	iload_3
   1:	iload	4
   3:	if_icmple	16
   6:	iload	4
   8:	istore	5
   10:	iload_3
   11:	istore	4
   13:	iload	5
   15:	istore_3
   16:	aload_0
   17:	iload_1
   18:	iload_3
   19:	iload_2
   20:	iload_1
   21:	iload	4
   23:	iload_2
   24:	invokevirtual	#252; //Method b:(IIIIII)V
   27:	return

public void b(int, int, int, int, int, int);
  Code:
   0:	iconst_0
   1:	istore	7
   3:	iload	7
   5:	aload_0
   6:	getfield	#175; //Field r:Ljava/util/List;
   9:	invokeinterface	#402,  1; //InterfaceMethod java/util/List.size:()I
   14:	if_icmpge	51
   17:	aload_0
   18:	getfield	#175; //Field r:Ljava/util/List;
   21:	iload	7
   23:	invokeinterface	#398,  2; //InterfaceMethod java/util/List.get:(I)Ljava/lang/Object;
   28:	checkcast	#37; //class bj
   31:	iload_1
   32:	iload_2
   33:	iload_3
   34:	iload	4
   36:	iload	5
   38:	iload	6
   40:	invokeinterface	#379,  7; //InterfaceMethod bj.a:(IIIIII)V
   45:	iinc	7, 1
   48:	goto	3
   51:	return

public void g(int, int, int, int);
  Code:
   0:	aload_0
   1:	iload_1
   2:	iconst_1
   3:	isub
   4:	iload_2
   5:	iload_3
   6:	iload	4
   8:	invokespecial	#274; //Method k:(IIII)V
   11:	aload_0
   12:	iload_1
   13:	iconst_1
   14:	iadd
   15:	iload_2
   16:	iload_3
   17:	iload	4
   19:	invokespecial	#274; //Method k:(IIII)V
   22:	aload_0
   23:	iload_1
   24:	iload_2
   25:	iconst_1
   26:	isub
   27:	iload_3
   28:	iload	4
   30:	invokespecial	#274; //Method k:(IIII)V
   33:	aload_0
   34:	iload_1
   35:	iload_2
   36:	iconst_1
   37:	iadd
   38:	iload_3
   39:	iload	4
   41:	invokespecial	#274; //Method k:(IIII)V
   44:	aload_0
   45:	iload_1
   46:	iload_2
   47:	iload_3
   48:	iconst_1
   49:	isub
   50:	iload	4
   52:	invokespecial	#274; //Method k:(IIII)V
   55:	aload_0
   56:	iload_1
   57:	iload_2
   58:	iload_3
   59:	iconst_1
   60:	iadd
   61:	iload	4
   63:	invokespecial	#274; //Method k:(IIII)V
   66:	return

public boolean g(int, int, int);
  Code:
   0:	aload_0
   1:	iload_1
   2:	iconst_4
   3:	ishr
   4:	iload_3
   5:	iconst_4
   6:	ishr
   7:	invokevirtual	#255; //Method c:(II)Ljn;
   10:	iload_1
   11:	bipush	15
   13:	iand
   14:	iload_2
   15:	iload_3
   16:	bipush	15
   18:	iand
   19:	invokevirtual	#360; //Method jn.c:(III)Z
   22:	ireturn

public int h(int, int, int);
  Code:
   0:	aload_0
   1:	iload_1
   2:	iload_2
   3:	iload_3
   4:	iconst_1
   5:	invokevirtual	#238; //Method a:(IIIZ)I
   8:	ireturn

public int a(int, int, int, boolean);
  Code:
   0:	iload_1
   1:	ldc	#1; //int -32000000
   3:	if_icmplt	24
   6:	iload_3
   7:	ldc	#1; //int -32000000
   9:	if_icmplt	24
   12:	iload_1
   13:	ldc	#3; //int 32000000
   15:	if_icmpge	24
   18:	iload_3
   19:	ldc	#3; //int 32000000
   21:	if_icmple	27
   24:	bipush	15
   26:	ireturn
   27:	iload	4
   29:	ifeq	170
   32:	aload_0
   33:	iload_1
   34:	iload_2
   35:	iload_3
   36:	invokevirtual	#234; //Method a:(III)I
   39:	istore	5
   41:	iload	5
   43:	getstatic	#192; //Field fw.al:Lfw;
   46:	getfield	#194; //Field fw.bi:I
   49:	if_icmpeq	63
   52:	iload	5
   54:	getstatic	#190; //Field fw.aB:Lfw;
   57:	getfield	#194; //Field fw.bi:I
   60:	if_icmpne	170
   63:	aload_0
   64:	iload_1
   65:	iload_2
   66:	iconst_1
   67:	iadd
   68:	iload_3
   69:	iconst_0
   70:	invokevirtual	#238; //Method a:(IIIZ)I
   73:	istore	6
   75:	aload_0
   76:	iload_1
   77:	iconst_1
   78:	iadd
   79:	iload_2
   80:	iload_3
   81:	iconst_0
   82:	invokevirtual	#238; //Method a:(IIIZ)I
   85:	istore	7
   87:	aload_0
   88:	iload_1
   89:	iconst_1
   90:	isub
   91:	iload_2
   92:	iload_3
   93:	iconst_0
   94:	invokevirtual	#238; //Method a:(IIIZ)I
   97:	istore	8
   99:	aload_0
   100:	iload_1
   101:	iload_2
   102:	iload_3
   103:	iconst_1
   104:	iadd
   105:	iconst_0
   106:	invokevirtual	#238; //Method a:(IIIZ)I
   109:	istore	9
   111:	aload_0
   112:	iload_1
   113:	iload_2
   114:	iload_3
   115:	iconst_1
   116:	isub
   117:	iconst_0
   118:	invokevirtual	#238; //Method a:(IIIZ)I
   121:	istore	10
   123:	iload	7
   125:	iload	6
   127:	if_icmple	134
   130:	iload	7
   132:	istore	6
   134:	iload	8
   136:	iload	6
   138:	if_icmple	145
   141:	iload	8
   143:	istore	6
   145:	iload	9
   147:	iload	6
   149:	if_icmple	156
   152:	iload	9
   154:	istore	6
   156:	iload	10
   158:	iload	6
   160:	if_icmple	167
   163:	iload	10
   165:	istore	6
   167:	iload	6
   169:	ireturn
   170:	iload_2
   171:	ifge	176
   174:	iconst_0
   175:	ireturn
   176:	iload_2
   177:	sipush	128
   180:	if_icmplt	203
   183:	bipush	15
   185:	aload_0
   186:	getfield	#164; //Field f:I
   189:	isub
   190:	istore	5
   192:	iload	5
   194:	ifge	200
   197:	iconst_0
   198:	istore	5
   200:	iload	5
   202:	ireturn
   203:	aload_0
   204:	iload_1
   205:	iconst_4
   206:	ishr
   207:	iload_3
   208:	iconst_4
   209:	ishr
   210:	invokevirtual	#255; //Method c:(II)Ljn;
   213:	astore	5
   215:	iload_1
   216:	bipush	15
   218:	iand
   219:	istore_1
   220:	iload_3
   221:	bipush	15
   223:	iand
   224:	istore_3
   225:	aload	5
   227:	iload_1
   228:	iload_2
   229:	iload_3
   230:	aload_0
   231:	getfield	#164; //Field f:I
   234:	invokevirtual	#361; //Method jn.c:(IIII)I
   237:	ireturn

public boolean i(int, int, int);
  Code:
   0:	iload_1
   1:	ldc	#1; //int -32000000
   3:	if_icmplt	24
   6:	iload_3
   7:	ldc	#1; //int -32000000
   9:	if_icmplt	24
   12:	iload_1
   13:	ldc	#3; //int 32000000
   15:	if_icmpge	24
   18:	iload_3
   19:	ldc	#3; //int 32000000
   21:	if_icmple	26
   24:	iconst_0
   25:	ireturn
   26:	iload_2
   27:	ifge	32
   30:	iconst_0
   31:	ireturn
   32:	iload_2
   33:	sipush	128
   36:	if_icmplt	41
   39:	iconst_1
   40:	ireturn
   41:	aload_0
   42:	iload_1
   43:	iconst_4
   44:	ishr
   45:	iload_3
   46:	iconst_4
   47:	ishr
   48:	invokespecial	#264; //Method f:(II)Z
   51:	ifne	56
   54:	iconst_0
   55:	ireturn
   56:	aload_0
   57:	iload_1
   58:	iconst_4
   59:	ishr
   60:	iload_3
   61:	iconst_4
   62:	ishr
   63:	invokevirtual	#255; //Method c:(II)Ljn;
   66:	astore	4
   68:	iload_1
   69:	bipush	15
   71:	iand
   72:	istore_1
   73:	iload_3
   74:	bipush	15
   76:	iand
   77:	istore_3
   78:	aload	4
   80:	iload_1
   81:	iload_2
   82:	iload_3
   83:	invokevirtual	#360; //Method jn.c:(III)Z
   86:	ireturn

public int d(int, int);
  Code:
   0:	iload_1
   1:	ldc	#1; //int -32000000
   3:	if_icmplt	24
   6:	iload_2
   7:	ldc	#1; //int -32000000
   9:	if_icmplt	24
   12:	iload_1
   13:	ldc	#3; //int 32000000
   15:	if_icmpge	24
   18:	iload_2
   19:	ldc	#3; //int 32000000
   21:	if_icmple	26
   24:	iconst_0
   25:	ireturn
   26:	aload_0
   27:	iload_1
   28:	iconst_4
   29:	ishr
   30:	iload_2
   31:	iconst_4
   32:	ishr
   33:	invokespecial	#264; //Method f:(II)Z
   36:	ifne	41
   39:	iconst_0
   40:	ireturn
   41:	aload_0
   42:	iload_1
   43:	iconst_4
   44:	ishr
   45:	iload_2
   46:	iconst_4
   47:	ishr
   48:	invokevirtual	#255; //Method c:(II)Ljn;
   51:	astore_3
   52:	aload_3
   53:	iload_1
   54:	bipush	15
   56:	iand
   57:	iload_2
   58:	bipush	15
   60:	iand
   61:	invokevirtual	#356; //Method jn.b:(II)I
   64:	ireturn

public void a(dj, int, int, int, int);
  Code:
   0:	aload_0
   1:	getfield	#174; //Field q:Lie;
   4:	getfield	#200; //Field ie.c:Z
   7:	ifeq	18
   10:	aload_1
   11:	getstatic	#114; //Field dj.a:Ldj;
   14:	if_acmpne	18
   17:	return
   18:	aload_0
   19:	iload_2
   20:	iload_3
   21:	iload	4
   23:	invokevirtual	#261; //Method e:(III)Z
   26:	ifne	30
   29:	return
   30:	aload_1
   31:	getstatic	#114; //Field dj.a:Ldj;
   34:	if_acmpne	55
   37:	aload_0
   38:	iload_2
   39:	iload_3
   40:	iload	4
   42:	invokevirtual	#271; //Method i:(III)Z
   45:	ifeq	91
   48:	bipush	15
   50:	istore	5
   52:	goto	91
   55:	aload_1
   56:	getstatic	#115; //Field dj.b:Ldj;
   59:	if_acmpne	91
   62:	aload_0
   63:	iload_2
   64:	iload_3
   65:	iload	4
   67:	invokevirtual	#234; //Method a:(III)I
   70:	istore	6
   72:	getstatic	#198; //Field fw.t:[I
   75:	iload	6
   77:	iaload
   78:	iload	5
   80:	if_icmple	91
   83:	getstatic	#198; //Field fw.t:[I
   86:	iload	6
   88:	iaload
   89:	istore	5
   91:	aload_0
   92:	aload_1
   93:	iload_2
   94:	iload_3
   95:	iload	4
   97:	invokevirtual	#241; //Method a:(Ldj;III)I
   100:	iload	5
   102:	if_icmpeq	118
   105:	aload_0
   106:	aload_1
   107:	iload_2
   108:	iload_3
   109:	iload	4
   111:	iload_2
   112:	iload_3
   113:	iload	4
   115:	invokevirtual	#242; //Method a:(Ldj;IIIIII)V
   118:	return

public int a(dj, int, int, int);
  Code:
   0:	iload_3
   1:	iflt	37
   4:	iload_3
   5:	sipush	128
   8:	if_icmpge	37
   11:	iload_2
   12:	ldc	#1; //int -32000000
   14:	if_icmplt	37
   17:	iload	4
   19:	ldc	#1; //int -32000000
   21:	if_icmplt	37
   24:	iload_2
   25:	ldc	#3; //int 32000000
   27:	if_icmpge	37
   30:	iload	4
   32:	ldc	#3; //int 32000000
   34:	if_icmple	42
   37:	aload_1
   38:	getfield	#116; //Field dj.c:I
   41:	ireturn
   42:	iload_2
   43:	iconst_4
   44:	ishr
   45:	istore	5
   47:	iload	4
   49:	iconst_4
   50:	ishr
   51:	istore	6
   53:	aload_0
   54:	iload	5
   56:	iload	6
   58:	invokespecial	#264; //Method f:(II)Z
   61:	ifne	66
   64:	iconst_0
   65:	ireturn
   66:	aload_0
   67:	iload	5
   69:	iload	6
   71:	invokevirtual	#255; //Method c:(II)Ljn;
   74:	astore	7
   76:	aload	7
   78:	aload_1
   79:	iload_2
   80:	bipush	15
   82:	iand
   83:	iload_3
   84:	iload	4
   86:	bipush	15
   88:	iand
   89:	invokevirtual	#349; //Method jn.a:(Ldj;III)I
   92:	ireturn

public void b(dj, int, int, int, int);
  Code:
   0:	iload_2
   1:	ldc	#1; //int -32000000
   3:	if_icmplt	26
   6:	iload	4
   8:	ldc	#1; //int -32000000
   10:	if_icmplt	26
   13:	iload_2
   14:	ldc	#3; //int 32000000
   16:	if_icmpge	26
   19:	iload	4
   21:	ldc	#3; //int 32000000
   23:	if_icmple	27
   26:	return
   27:	iload_3
   28:	ifge	32
   31:	return
   32:	iload_3
   33:	sipush	128
   36:	if_icmplt	40
   39:	return
   40:	aload_0
   41:	iload_2
   42:	iconst_4
   43:	ishr
   44:	iload	4
   46:	iconst_4
   47:	ishr
   48:	invokespecial	#264; //Method f:(II)Z
   51:	ifne	55
   54:	return
   55:	aload_0
   56:	iload_2
   57:	iconst_4
   58:	ishr
   59:	iload	4
   61:	iconst_4
   62:	ishr
   63:	invokevirtual	#255; //Method c:(II)Ljn;
   66:	astore	6
   68:	aload	6
   70:	aload_1
   71:	iload_2
   72:	bipush	15
   74:	iand
   75:	iload_3
   76:	iload	4
   78:	bipush	15
   80:	iand
   81:	iload	5
   83:	invokevirtual	#350; //Method jn.a:(Ldj;IIII)V
   86:	iconst_0
   87:	istore	7
   89:	iload	7
   91:	aload_0
   92:	getfield	#175; //Field r:Ljava/util/List;
   95:	invokeinterface	#402,  1; //InterfaceMethod java/util/List.size:()I
   100:	if_icmpge	132
   103:	aload_0
   104:	getfield	#175; //Field r:Ljava/util/List;
   107:	iload	7
   109:	invokeinterface	#398,  2; //InterfaceMethod java/util/List.get:(I)Ljava/lang/Object;
   114:	checkcast	#37; //class bj
   117:	iload_2
   118:	iload_3
   119:	iload	4
   121:	invokeinterface	#378,  4; //InterfaceMethod bj.a:(III)V
   126:	iinc	7, 1
   129:	goto	89
   132:	return

public float j(int, int, int);
  Code:
   0:	aload_0
   1:	getfield	#174; //Field q:Lie;
   4:	getfield	#201; //Field ie.d:[F
   7:	aload_0
   8:	iload_1
   9:	iload_2
   10:	iload_3
   11:	invokevirtual	#269; //Method h:(III)I
   14:	faload
   15:	freturn

public boolean b();
  Code:
   0:	aload_0
   1:	getfield	#164; //Field f:I
   4:	iconst_4
   5:	if_icmpge	12
   8:	iconst_1
   9:	goto	13
   12:	iconst_0
   13:	ireturn

public gk a(ba, ba);
  Code:
   0:	aload_0
   1:	aload_1
   2:	aload_2
   3:	iconst_0
   4:	invokevirtual	#240; //Method a:(Lba;Lba;Z)Lgk;
   7:	areturn

public gk a(ba, ba, boolean);
  Code:
   0:	aload_1
   1:	getfield	#106; //Field ba.a:D
   4:	invokestatic	#321; //Method java/lang/Double.isNaN:(D)Z
   7:	ifne	30
   10:	aload_1
   11:	getfield	#107; //Field ba.b:D
   14:	invokestatic	#321; //Method java/lang/Double.isNaN:(D)Z
   17:	ifne	30
   20:	aload_1
   21:	getfield	#108; //Field ba.c:D
   24:	invokestatic	#321; //Method java/lang/Double.isNaN:(D)Z
   27:	ifeq	32
   30:	aconst_null
   31:	areturn
   32:	aload_2
   33:	getfield	#106; //Field ba.a:D
   36:	invokestatic	#321; //Method java/lang/Double.isNaN:(D)Z
   39:	ifne	62
   42:	aload_2
   43:	getfield	#107; //Field ba.b:D
   46:	invokestatic	#321; //Method java/lang/Double.isNaN:(D)Z
   49:	ifne	62
   52:	aload_2
   53:	getfield	#108; //Field ba.c:D
   56:	invokestatic	#321; //Method java/lang/Double.isNaN:(D)Z
   59:	ifeq	64
   62:	aconst_null
   63:	areturn
   64:	aload_2
   65:	getfield	#106; //Field ba.a:D
   68:	invokestatic	#294; //Method hb.b:(D)I
   71:	istore	4
   73:	aload_2
   74:	getfield	#107; //Field ba.b:D
   77:	invokestatic	#294; //Method hb.b:(D)I
   80:	istore	5
   82:	aload_2
   83:	getfield	#108; //Field ba.c:D
   86:	invokestatic	#294; //Method hb.b:(D)I
   89:	istore	6
   91:	aload_1
   92:	getfield	#106; //Field ba.a:D
   95:	invokestatic	#294; //Method hb.b:(D)I
   98:	istore	7
   100:	aload_1
   101:	getfield	#107; //Field ba.b:D
   104:	invokestatic	#294; //Method hb.b:(D)I
   107:	istore	8
   109:	aload_1
   110:	getfield	#108; //Field ba.c:D
   113:	invokestatic	#294; //Method hb.b:(D)I
   116:	istore	9
   118:	sipush	200
   121:	istore	10
   123:	iload	10
   125:	iinc	10, -1
   128:	iflt	782
   131:	aload_1
   132:	getfield	#106; //Field ba.a:D
   135:	invokestatic	#321; //Method java/lang/Double.isNaN:(D)Z
   138:	ifne	161
   141:	aload_1
   142:	getfield	#107; //Field ba.b:D
   145:	invokestatic	#321; //Method java/lang/Double.isNaN:(D)Z
   148:	ifne	161
   151:	aload_1
   152:	getfield	#108; //Field ba.c:D
   155:	invokestatic	#321; //Method java/lang/Double.isNaN:(D)Z
   158:	ifeq	163
   161:	aconst_null
   162:	areturn
   163:	iload	7
   165:	iload	4
   167:	if_icmpne	186
   170:	iload	8
   172:	iload	5
   174:	if_icmpne	186
   177:	iload	9
   179:	iload	6
   181:	if_icmpne	186
   184:	aconst_null
   185:	areturn
   186:	ldc2_w	#104; //double 999.0d
   189:	dstore	11
   191:	ldc2_w	#104; //double 999.0d
   194:	dstore	13
   196:	ldc2_w	#104; //double 999.0d
   199:	dstore	15
   201:	iload	4
   203:	iload	7
   205:	if_icmple	215
   208:	iload	7
   210:	i2d
   211:	dconst_1
   212:	dadd
   213:	dstore	11
   215:	iload	4
   217:	iload	7
   219:	if_icmpge	229
   222:	iload	7
   224:	i2d
   225:	dconst_0
   226:	dadd
   227:	dstore	11
   229:	iload	5
   231:	iload	8
   233:	if_icmple	243
   236:	iload	8
   238:	i2d
   239:	dconst_1
   240:	dadd
   241:	dstore	13
   243:	iload	5
   245:	iload	8
   247:	if_icmpge	257
   250:	iload	8
   252:	i2d
   253:	dconst_0
   254:	dadd
   255:	dstore	13
   257:	iload	6
   259:	iload	9
   261:	if_icmple	271
   264:	iload	9
   266:	i2d
   267:	dconst_1
   268:	dadd
   269:	dstore	15
   271:	iload	6
   273:	iload	9
   275:	if_icmpge	285
   278:	iload	9
   280:	i2d
   281:	dconst_0
   282:	dadd
   283:	dstore	15
   285:	ldc2_w	#104; //double 999.0d
   288:	dstore	17
   290:	ldc2_w	#104; //double 999.0d
   293:	dstore	19
   295:	ldc2_w	#104; //double 999.0d
   298:	dstore	21
   300:	aload_2
   301:	getfield	#106; //Field ba.a:D
   304:	aload_1
   305:	getfield	#106; //Field ba.a:D
   308:	dsub
   309:	dstore	23
   311:	aload_2
   312:	getfield	#107; //Field ba.b:D
   315:	aload_1
   316:	getfield	#107; //Field ba.b:D
   319:	dsub
   320:	dstore	25
   322:	aload_2
   323:	getfield	#108; //Field ba.c:D
   326:	aload_1
   327:	getfield	#108; //Field ba.c:D
   330:	dsub
   331:	dstore	27
   333:	dload	11
   335:	ldc2_w	#104; //double 999.0d
   338:	dcmpl
   339:	ifeq	354
   342:	dload	11
   344:	aload_1
   345:	getfield	#106; //Field ba.a:D
   348:	dsub
   349:	dload	23
   351:	ddiv
   352:	dstore	17
   354:	dload	13
   356:	ldc2_w	#104; //double 999.0d
   359:	dcmpl
   360:	ifeq	375
   363:	dload	13
   365:	aload_1
   366:	getfield	#107; //Field ba.b:D
   369:	dsub
   370:	dload	25
   372:	ddiv
   373:	dstore	19
   375:	dload	15
   377:	ldc2_w	#104; //double 999.0d
   380:	dcmpl
   381:	ifeq	396
   384:	dload	15
   386:	aload_1
   387:	getfield	#108; //Field ba.c:D
   390:	dsub
   391:	dload	27
   393:	ddiv
   394:	dstore	21
   396:	iconst_0
   397:	istore	29
   399:	dload	17
   401:	dload	19
   403:	dcmpg
   404:	ifge	468
   407:	dload	17
   409:	dload	21
   411:	dcmpg
   412:	ifge	468
   415:	iload	4
   417:	iload	7
   419:	if_icmple	428
   422:	iconst_4
   423:	istore	29
   425:	goto	431
   428:	iconst_5
   429:	istore	29
   431:	aload_1
   432:	dload	11
   434:	putfield	#106; //Field ba.a:D
   437:	aload_1
   438:	dup
   439:	getfield	#107; //Field ba.b:D
   442:	dload	25
   444:	dload	17
   446:	dmul
   447:	dadd
   448:	putfield	#107; //Field ba.b:D
   451:	aload_1
   452:	dup
   453:	getfield	#108; //Field ba.c:D
   456:	dload	27
   458:	dload	17
   460:	dmul
   461:	dadd
   462:	putfield	#108; //Field ba.c:D
   465:	goto	579
   468:	dload	19
   470:	dload	21
   472:	dcmpg
   473:	ifge	529
   476:	iload	5
   478:	iload	8
   480:	if_icmple	489
   483:	iconst_0
   484:	istore	29
   486:	goto	492
   489:	iconst_1
   490:	istore	29
   492:	aload_1
   493:	dup
   494:	getfield	#106; //Field ba.a:D
   497:	dload	23
   499:	dload	19
   501:	dmul
   502:	dadd
   503:	putfield	#106; //Field ba.a:D
   506:	aload_1
   507:	dload	13
   509:	putfield	#107; //Field ba.b:D
   512:	aload_1
   513:	dup
   514:	getfield	#108; //Field ba.c:D
   517:	dload	27
   519:	dload	19
   521:	dmul
   522:	dadd
   523:	putfield	#108; //Field ba.c:D
   526:	goto	579
   529:	iload	6
   531:	iload	9
   533:	if_icmple	542
   536:	iconst_2
   537:	istore	29
   539:	goto	545
   542:	iconst_3
   543:	istore	29
   545:	aload_1
   546:	dup
   547:	getfield	#106; //Field ba.a:D
   550:	dload	23
   552:	dload	21
   554:	dmul
   555:	dadd
   556:	putfield	#106; //Field ba.a:D
   559:	aload_1
   560:	dup
   561:	getfield	#107; //Field ba.b:D
   564:	dload	25
   566:	dload	21
   568:	dmul
   569:	dadd
   570:	putfield	#107; //Field ba.b:D
   573:	aload_1
   574:	dload	15
   576:	putfield	#108; //Field ba.c:D
   579:	aload_1
   580:	getfield	#106; //Field ba.a:D
   583:	aload_1
   584:	getfield	#107; //Field ba.b:D
   587:	aload_1
   588:	getfield	#108; //Field ba.c:D
   591:	invokestatic	#212; //Method ba.b:(DDD)Lba;
   594:	astore	30
   596:	aload	30
   598:	aload_1
   599:	getfield	#106; //Field ba.a:D
   602:	invokestatic	#294; //Method hb.b:(D)I
   605:	i2d
   606:	dup2_x1
   607:	putfield	#106; //Field ba.a:D
   610:	d2i
   611:	istore	7
   613:	iload	29
   615:	iconst_5
   616:	if_icmpne	633
   619:	iinc	7, -1
   622:	aload	30
   624:	dup
   625:	getfield	#106; //Field ba.a:D
   628:	dconst_1
   629:	dadd
   630:	putfield	#106; //Field ba.a:D
   633:	aload	30
   635:	aload_1
   636:	getfield	#107; //Field ba.b:D
   639:	invokestatic	#294; //Method hb.b:(D)I
   642:	i2d
   643:	dup2_x1
   644:	putfield	#107; //Field ba.b:D
   647:	d2i
   648:	istore	8
   650:	iload	29
   652:	iconst_1
   653:	if_icmpne	670
   656:	iinc	8, -1
   659:	aload	30
   661:	dup
   662:	getfield	#107; //Field ba.b:D
   665:	dconst_1
   666:	dadd
   667:	putfield	#107; //Field ba.b:D
   670:	aload	30
   672:	aload_1
   673:	getfield	#108; //Field ba.c:D
   676:	invokestatic	#294; //Method hb.b:(D)I
   679:	i2d
   680:	dup2_x1
   681:	putfield	#108; //Field ba.c:D
   684:	d2i
   685:	istore	9
   687:	iload	29
   689:	iconst_3
   690:	if_icmpne	707
   693:	iinc	9, -1
   696:	aload	30
   698:	dup
   699:	getfield	#108; //Field ba.c:D
   702:	dconst_1
   703:	dadd
   704:	putfield	#108; //Field ba.c:D
   707:	aload_0
   708:	iload	7
   710:	iload	8
   712:	iload	9
   714:	invokevirtual	#234; //Method a:(III)I
   717:	istore	31
   719:	aload_0
   720:	iload	7
   722:	iload	8
   724:	iload	9
   726:	invokevirtual	#251; //Method b:(III)I
   729:	istore	32
   731:	getstatic	#196; //Field fw.n:[Lfw;
   734:	iload	31
   736:	aaload
   737:	astore	33
   739:	iload	31
   741:	ifle	779
   744:	aload	33
   746:	iload	32
   748:	iload_3
   749:	invokevirtual	#283; //Method fw.a:(IZ)Z
   752:	ifeq	779
   755:	aload	33
   757:	aload_0
   758:	iload	7
   760:	iload	8
   762:	iload	9
   764:	aload_1
   765:	aload_2
   766:	invokevirtual	#285; //Method fw.a:(Lel;IIILba;Lba;)Lgk;
   769:	astore	34
   771:	aload	34
   773:	ifnull	779
   776:	aload	34
   778:	areturn
   779:	goto	123
   782:	aconst_null
   783:	areturn

public void a(dv, java.lang.String, float, float);
  Code:
   0:	iconst_0
   1:	istore	5
   3:	iload	5
   5:	aload_0
   6:	getfield	#175; //Field r:Ljava/util/List;
   9:	invokeinterface	#402,  1; //InterfaceMethod java/util/List.size:()I
   14:	if_icmpge	64
   17:	aload_0
   18:	getfield	#175; //Field r:Ljava/util/List;
   21:	iload	5
   23:	invokeinterface	#398,  2; //InterfaceMethod java/util/List.get:(I)Ljava/lang/Object;
   28:	checkcast	#37; //class bj
   31:	aload_2
   32:	aload_1
   33:	getfield	#135; //Field dv.p:D
   36:	aload_1
   37:	getfield	#136; //Field dv.q:D
   40:	aload_1
   41:	getfield	#124; //Field dv.G:F
   44:	f2d
   45:	dsub
   46:	aload_1
   47:	getfield	#137; //Field dv.r:D
   50:	fload_3
   51:	fload	4
   53:	invokeinterface	#383,  10; //InterfaceMethod bj.a:(Ljava/lang/String;DDDFF)V
   58:	iinc	5, 1
   61:	goto	3
   64:	return

public void a(double, double, double, java.lang.String, float, float);
  Code:
   0:	iconst_0
   1:	istore	10
   3:	iload	10
   5:	aload_0
   6:	getfield	#175; //Field r:Ljava/util/List;
   9:	invokeinterface	#402,  1; //InterfaceMethod java/util/List.size:()I
   14:	if_icmpge	52
   17:	aload_0
   18:	getfield	#175; //Field r:Ljava/util/List;
   21:	iload	10
   23:	invokeinterface	#398,  2; //InterfaceMethod java/util/List.get:(I)Ljava/lang/Object;
   28:	checkcast	#37; //class bj
   31:	aload	7
   33:	dload_1
   34:	dload_3
   35:	dload	5
   37:	fload	8
   39:	fload	9
   41:	invokeinterface	#383,  10; //InterfaceMethod bj.a:(Ljava/lang/String;DDDFF)V
   46:	iinc	10, 1
   49:	goto	3
   52:	return

public void a(java.lang.String, int, int, int);
  Code:
   0:	iconst_0
   1:	istore	5
   3:	iload	5
   5:	aload_0
   6:	getfield	#175; //Field r:Ljava/util/List;
   9:	invokeinterface	#402,  1; //InterfaceMethod java/util/List.size:()I
   14:	if_icmpge	47
   17:	aload_0
   18:	getfield	#175; //Field r:Ljava/util/List;
   21:	iload	5
   23:	invokeinterface	#398,  2; //InterfaceMethod java/util/List.get:(I)Ljava/lang/Object;
   28:	checkcast	#37; //class bj
   31:	aload_1
   32:	iload_2
   33:	iload_3
   34:	iload	4
   36:	invokeinterface	#384,  5; //InterfaceMethod bj.a:(Ljava/lang/String;III)V
   41:	iinc	5, 1
   44:	goto	3
   47:	return

public void a(java.lang.String, double, double, double, double, double, double);
  Code:
   0:	iconst_0
   1:	istore	14
   3:	iload	14
   5:	aload_0
   6:	getfield	#175; //Field r:Ljava/util/List;
   9:	invokeinterface	#402,  1; //InterfaceMethod java/util/List.size:()I
   14:	if_icmpge	54
   17:	aload_0
   18:	getfield	#175; //Field r:Ljava/util/List;
   21:	iload	14
   23:	invokeinterface	#398,  2; //InterfaceMethod java/util/List.get:(I)Ljava/lang/Object;
   28:	checkcast	#37; //class bj
   31:	aload_1
   32:	dload_2
   33:	dload	4
   35:	dload	6
   37:	dload	8
   39:	dload	10
   41:	dload	12
   43:	invokeinterface	#382,  14; //InterfaceMethod bj.a:(Ljava/lang/String;DDDDDD)V
   48:	iinc	14, 1
   51:	goto	3
   54:	return

public boolean a(dv);
  Code:
   0:	aload_1
   1:	getfield	#135; //Field dv.p:D
   4:	ldc2_w	#102; //double 16.0d
   7:	ddiv
   8:	invokestatic	#294; //Method hb.b:(D)I
   11:	istore_2
   12:	aload_1
   13:	getfield	#137; //Field dv.r:D
   16:	ldc2_w	#102; //double 16.0d
   19:	ddiv
   20:	invokestatic	#294; //Method hb.b:(D)I
   23:	istore_3
   24:	iconst_0
   25:	istore	4
   27:	aload_1
   28:	instanceof	#50; //class ft
   31:	ifeq	37
   34:	iconst_1
   35:	istore	4
   37:	iload	4
   39:	ifne	51
   42:	aload_0
   43:	iload_2
   44:	iload_3
   45:	invokespecial	#264; //Method f:(II)Z
   48:	ifeq	133
   51:	aload_1
   52:	instanceof	#50; //class ft
   55:	ifeq	105
   58:	aload_0
   59:	getfield	#162; //Field d:Ljava/util/List;
   62:	aload_1
   63:	checkcast	#50; //class ft
   66:	invokeinterface	#395,  2; //InterfaceMethod java/util/List.add:(Ljava/lang/Object;)Z
   71:	pop
   72:	getstatic	#202; //Field java/lang/System.out:Ljava/io/PrintStream;
   75:	new	#72; //class java/lang/StringBuilder
   78:	dup
   79:	invokespecial	#327; //Method java/lang/StringBuilder."<init>":()V
   82:	ldc	#18; //String Player count: 
   84:	invokevirtual	#329; //Method java/lang/StringBuilder.append:(Ljava/lang/String;)Ljava/lang/StringBuilder;
   87:	aload_0
   88:	getfield	#162; //Field d:Ljava/util/List;
   91:	invokeinterface	#402,  1; //InterfaceMethod java/util/List.size:()I
   96:	invokevirtual	#328; //Method java/lang/StringBuilder.append:(I)Ljava/lang/StringBuilder;
   99:	invokevirtual	#330; //Method java/lang/StringBuilder.toString:()Ljava/lang/String;
   102:	invokevirtual	#318; //Method java/io/PrintStream.println:(Ljava/lang/String;)V
   105:	aload_0
   106:	iload_2
   107:	iload_3
   108:	invokevirtual	#255; //Method c:(II)Ljn;
   111:	aload_1
   112:	invokevirtual	#351; //Method jn.a:(Ldv;)V
   115:	aload_0
   116:	getfield	#160; //Field b:Ljava/util/List;
   119:	aload_1
   120:	invokeinterface	#395,  2; //InterfaceMethod java/util/List.add:(Ljava/lang/Object;)Z
   125:	pop
   126:	aload_0
   127:	aload_1
   128:	invokevirtual	#253; //Method b:(Ldv;)V
   131:	iconst_1
   132:	ireturn
   133:	iconst_0
   134:	ireturn

protected void b(dv);
  Code:
   0:	iconst_0
   1:	istore_2
   2:	iload_2
   3:	aload_0
   4:	getfield	#175; //Field r:Ljava/util/List;
   7:	invokeinterface	#402,  1; //InterfaceMethod java/util/List.size:()I
   12:	if_icmpge	40
   15:	aload_0
   16:	getfield	#175; //Field r:Ljava/util/List;
   19:	iload_2
   20:	invokeinterface	#398,  2; //InterfaceMethod java/util/List.get:(I)Ljava/lang/Object;
   25:	checkcast	#37; //class bj
   28:	aload_1
   29:	invokeinterface	#381,  2; //InterfaceMethod bj.a:(Ldv;)V
   34:	iinc	2, 1
   37:	goto	2
   40:	return

protected void c(dv);
  Code:
   0:	iconst_0
   1:	istore_2
   2:	iload_2
   3:	aload_0
   4:	getfield	#175; //Field r:Ljava/util/List;
   7:	invokeinterface	#402,  1; //InterfaceMethod java/util/List.size:()I
   12:	if_icmpge	40
   15:	aload_0
   16:	getfield	#175; //Field r:Ljava/util/List;
   19:	iload_2
   20:	invokeinterface	#398,  2; //InterfaceMethod java/util/List.get:(I)Ljava/lang/Object;
   25:	checkcast	#37; //class bj
   28:	aload_1
   29:	invokeinterface	#385,  2; //InterfaceMethod bj.b:(Ldv;)V
   34:	iinc	2, 1
   37:	goto	2
   40:	return

public void d(dv);
  Code:
   0:	aload_1
   1:	invokevirtual	#224; //Method dv.l:()V
   4:	aload_1
   5:	instanceof	#50; //class ft
   8:	ifeq	58
   11:	aload_0
   12:	getfield	#162; //Field d:Ljava/util/List;
   15:	aload_1
   16:	checkcast	#50; //class ft
   19:	invokeinterface	#400,  2; //InterfaceMethod java/util/List.remove:(Ljava/lang/Object;)Z
   24:	pop
   25:	getstatic	#202; //Field java/lang/System.out:Ljava/io/PrintStream;
   28:	new	#72; //class java/lang/StringBuilder
   31:	dup
   32:	invokespecial	#327; //Method java/lang/StringBuilder."<init>":()V
   35:	ldc	#18; //String Player count: 
   37:	invokevirtual	#329; //Method java/lang/StringBuilder.append:(Ljava/lang/String;)Ljava/lang/StringBuilder;
   40:	aload_0
   41:	getfield	#162; //Field d:Ljava/util/List;
   44:	invokeinterface	#402,  1; //InterfaceMethod java/util/List.size:()I
   49:	invokevirtual	#328; //Method java/lang/StringBuilder.append:(I)Ljava/lang/StringBuilder;
   52:	invokevirtual	#330; //Method java/lang/StringBuilder.toString:()Ljava/lang/String;
   55:	invokevirtual	#318; //Method java/io/PrintStream.println:(Ljava/lang/String;)V
   58:	return

public void a(bj);
  Code:
   0:	aload_0
   1:	getfield	#175; //Field r:Ljava/util/List;
   4:	aload_1
   5:	invokeinterface	#395,  2; //InterfaceMethod java/util/List.add:(Ljava/lang/Object;)Z
   10:	pop
   11:	return

public java.util.List a(dv, ds);
  Code:
   0:	aload_0
   1:	getfield	#154; //Field I:Ljava/util/ArrayList;
   4:	invokevirtual	#334; //Method java/util/ArrayList.clear:()V
   7:	aload_2
   8:	getfield	#117; //Field ds.a:D
   11:	invokestatic	#294; //Method hb.b:(D)I
   14:	istore_3
   15:	aload_2
   16:	getfield	#120; //Field ds.d:D
   19:	dconst_1
   20:	dadd
   21:	invokestatic	#294; //Method hb.b:(D)I
   24:	istore	4
   26:	aload_2
   27:	getfield	#118; //Field ds.b:D
   30:	invokestatic	#294; //Method hb.b:(D)I
   33:	istore	5
   35:	aload_2
   36:	getfield	#121; //Field ds.e:D
   39:	dconst_1
   40:	dadd
   41:	invokestatic	#294; //Method hb.b:(D)I
   44:	istore	6
   46:	aload_2
   47:	getfield	#119; //Field ds.c:D
   50:	invokestatic	#294; //Method hb.b:(D)I
   53:	istore	7
   55:	aload_2
   56:	getfield	#122; //Field ds.f:D
   59:	dconst_1
   60:	dadd
   61:	invokestatic	#294; //Method hb.b:(D)I
   64:	istore	8
   66:	iload_3
   67:	istore	9
   69:	iload	9
   71:	iload	4
   73:	if_icmpge	169
   76:	iload	7
   78:	istore	10
   80:	iload	10
   82:	iload	8
   84:	if_icmpge	163
   87:	aload_0
   88:	iload	9
   90:	bipush	64
   92:	iload	10
   94:	invokevirtual	#261; //Method e:(III)Z
   97:	ifeq	157
   100:	iload	5
   102:	iconst_1
   103:	isub
   104:	istore	11
   106:	iload	11
   108:	iload	6
   110:	if_icmpge	157
   113:	getstatic	#196; //Field fw.n:[Lfw;
   116:	aload_0
   117:	iload	9
   119:	iload	11
   121:	iload	10
   123:	invokevirtual	#234; //Method a:(III)I
   126:	aaload
   127:	astore	12
   129:	aload	12
   131:	ifnull	151
   134:	aload	12
   136:	aload_0
   137:	iload	9
   139:	iload	11
   141:	iload	10
   143:	aload_2
   144:	aload_0
   145:	getfield	#154; //Field I:Ljava/util/ArrayList;
   148:	invokevirtual	#286; //Method fw.a:(Lel;IIILds;Ljava/util/ArrayList;)V
   151:	iinc	11, 1
   154:	goto	106
   157:	iinc	10, 1
   160:	goto	80
   163:	iinc	9, 1
   166:	goto	69
   169:	ldc2_w	#92; //double 0.25d
   172:	dstore	9
   174:	aload_0
   175:	aload_1
   176:	aload_2
   177:	dload	9
   179:	dload	9
   181:	dload	9
   183:	invokevirtual	#221; //Method ds.b:(DDD)Lds;
   186:	invokevirtual	#254; //Method b:(Ldv;Lds;)Ljava/util/List;
   189:	astore	11
   191:	iconst_0
   192:	istore	12
   194:	iload	12
   196:	aload	11
   198:	invokeinterface	#402,  1; //InterfaceMethod java/util/List.size:()I
   203:	if_icmpge	295
   206:	aload	11
   208:	iload	12
   210:	invokeinterface	#398,  2; //InterfaceMethod java/util/List.get:(I)Ljava/lang/Object;
   215:	checkcast	#45; //class dv
   218:	invokevirtual	#225; //Method dv.q:()Lds;
   221:	astore	13
   223:	aload	13
   225:	ifnull	247
   228:	aload	13
   230:	aload_2
   231:	invokevirtual	#220; //Method ds.a:(Lds;)Z
   234:	ifeq	247
   237:	aload_0
   238:	getfield	#154; //Field I:Ljava/util/ArrayList;
   241:	aload	13
   243:	invokevirtual	#333; //Method java/util/ArrayList.add:(Ljava/lang/Object;)Z
   246:	pop
   247:	aload_1
   248:	aload	11
   250:	iload	12
   252:	invokeinterface	#398,  2; //InterfaceMethod java/util/List.get:(I)Ljava/lang/Object;
   257:	checkcast	#45; //class dv
   260:	invokevirtual	#223; //Method dv.d:(Ldv;)Lds;
   263:	astore	13
   265:	aload	13
   267:	ifnull	289
   270:	aload	13
   272:	aload_2
   273:	invokevirtual	#220; //Method ds.a:(Lds;)Z
   276:	ifeq	289
   279:	aload_0
   280:	getfield	#154; //Field I:Ljava/util/ArrayList;
   283:	aload	13
   285:	invokevirtual	#333; //Method java/util/ArrayList.add:(Ljava/lang/Object;)Z
   288:	pop
   289:	iinc	12, 1
   292:	goto	194
   295:	aload_0
   296:	getfield	#154; //Field I:Ljava/util/ArrayList;
   299:	areturn

public int a(float);
  Code:
   0:	aload_0
   1:	fload_1
   2:	invokevirtual	#249; //Method b:(F)F
   5:	fstore_2
   6:	fconst_1
   7:	fload_2
   8:	ldc	#9; //float 3.1415927f
   10:	fmul
   11:	fconst_2
   12:	fmul
   13:	invokestatic	#295; //Method hb.b:(F)F
   16:	fconst_2
   17:	fmul
   18:	ldc	#6; //float 0.5f
   20:	fadd
   21:	fsub
   22:	fstore_3
   23:	fload_3
   24:	fconst_0
   25:	fcmpg
   26:	ifge	31
   29:	fconst_0
   30:	fstore_3
   31:	fload_3
   32:	fconst_1
   33:	fcmpl
   34:	ifle	39
   37:	fconst_1
   38:	fstore_3
   39:	fload_3
   40:	ldc	#11; //float 11.0f
   42:	fmul
   43:	f2i
   44:	ireturn

public float b(float);
  Code:
   0:	aload_0
   1:	getfield	#174; //Field q:Lie;
   4:	aload_0
   5:	getfield	#163; //Field e:J
   8:	fload_1
   9:	invokevirtual	#299; //Method ie.a:(JF)F
   12:	freturn

public int e(int, int);
  Code:
   0:	aload_0
   1:	iload_1
   2:	iload_2
   3:	invokevirtual	#250; //Method b:(II)Ljn;
   6:	astore_3
   7:	bipush	127
   9:	istore	4
   11:	aload_0
   12:	iload_1
   13:	iload	4
   15:	iload_2
   16:	invokevirtual	#256; //Method c:(III)Ljr;
   19:	invokevirtual	#365; //Method jr.c:()Z
   22:	ifeq	36
   25:	iload	4
   27:	ifle	36
   30:	iinc	4, -1
   33:	goto	11
   36:	iload_1
   37:	bipush	15
   39:	iand
   40:	istore_1
   41:	iload_2
   42:	bipush	15
   44:	iand
   45:	istore_2
   46:	iload	4
   48:	ifle	110
   51:	aload_3
   52:	iload_1
   53:	iload	4
   55:	iload_2
   56:	invokevirtual	#345; //Method jn.a:(III)I
   59:	istore	5
   61:	iload	5
   63:	ifeq	96
   66:	getstatic	#196; //Field fw.n:[Lfw;
   69:	iload	5
   71:	aaload
   72:	getfield	#195; //Field fw.bt:Ljr;
   75:	invokevirtual	#365; //Method jr.c:()Z
   78:	ifne	102
   81:	getstatic	#196; //Field fw.n:[Lfw;
   84:	iload	5
   86:	aaload
   87:	getfield	#195; //Field fw.bt:Ljr;
   90:	invokevirtual	#366; //Method jr.d:()Z
   93:	ifne	102
   96:	iinc	4, -1
   99:	goto	107
   102:	iload	4
   104:	iconst_1
   105:	iadd
   106:	ireturn
   107:	goto	46
   110:	iconst_m1
   111:	ireturn

public void h(int, int, int, int);
  Code:
   0:	new	#41; //class ci
   3:	dup
   4:	iload_1
   5:	iload_2
   6:	iload_3
   7:	iload	4
   9:	invokespecial	#217; //Method ci."<init>":(IIII)V
   12:	astore	5
   14:	bipush	8
   16:	istore	6
   18:	aload_0
   19:	getfield	#159; //Field a:Z
   22:	ifeq	146
   25:	aload_0
   26:	aload	5
   28:	getfield	#109; //Field ci.a:I
   31:	iload	6
   33:	isub
   34:	aload	5
   36:	getfield	#110; //Field ci.b:I
   39:	iload	6
   41:	isub
   42:	aload	5
   44:	getfield	#111; //Field ci.c:I
   47:	iload	6
   49:	isub
   50:	aload	5
   52:	getfield	#109; //Field ci.a:I
   55:	iload	6
   57:	iadd
   58:	aload	5
   60:	getfield	#110; //Field ci.b:I
   63:	iload	6
   65:	iadd
   66:	aload	5
   68:	getfield	#111; //Field ci.c:I
   71:	iload	6
   73:	iadd
   74:	invokevirtual	#237; //Method a:(IIIIII)Z
   77:	ifeq	145
   80:	aload_0
   81:	aload	5
   83:	getfield	#109; //Field ci.a:I
   86:	aload	5
   88:	getfield	#110; //Field ci.b:I
   91:	aload	5
   93:	getfield	#111; //Field ci.c:I
   96:	invokevirtual	#234; //Method a:(III)I
   99:	istore	7
   101:	iload	7
   103:	aload	5
   105:	getfield	#112; //Field ci.d:I
   108:	if_icmpne	145
   111:	iload	7
   113:	ifle	145
   116:	getstatic	#196; //Field fw.n:[Lfw;
   119:	iload	7
   121:	aaload
   122:	aload_0
   123:	aload	5
   125:	getfield	#109; //Field ci.a:I
   128:	aload	5
   130:	getfield	#110; //Field ci.b:I
   133:	aload	5
   135:	getfield	#111; //Field ci.c:I
   138:	aload_0
   139:	getfield	#169; //Field l:Ljava/util/Random;
   142:	invokevirtual	#288; //Method fw.a:(Lel;IIILjava/util/Random;)V
   145:	return
   146:	aload_0
   147:	iload_1
   148:	iload	6
   150:	isub
   151:	iload_2
   152:	iload	6
   154:	isub
   155:	iload_3
   156:	iload	6
   158:	isub
   159:	iload_1
   160:	iload	6
   162:	iadd
   163:	iload_2
   164:	iload	6
   166:	iadd
   167:	iload_3
   168:	iload	6
   170:	iadd
   171:	invokevirtual	#237; //Method a:(IIIIII)Z
   174:	ifeq	239
   177:	iload	4
   179:	ifle	203
   182:	aload	5
   184:	getstatic	#196; //Field fw.n:[Lfw;
   187:	iload	4
   189:	aaload
   190:	invokevirtual	#289; //Method fw.b:()I
   193:	i2l
   194:	aload_0
   195:	getfield	#163; //Field e:J
   198:	ladd
   199:	invokevirtual	#218; //Method ci.a:(J)Lci;
   202:	pop
   203:	aload_0
   204:	getfield	#149; //Field D:Ljava/util/Set;
   207:	aload	5
   209:	invokeinterface	#405,  2; //InterfaceMethod java/util/Set.contains:(Ljava/lang/Object;)Z
   214:	ifne	239
   217:	aload_0
   218:	getfield	#149; //Field D:Ljava/util/Set;
   221:	aload	5
   223:	invokeinterface	#403,  2; //InterfaceMethod java/util/Set.add:(Ljava/lang/Object;)Z
   228:	pop
   229:	aload_0
   230:	getfield	#148; //Field C:Ljava/util/TreeSet;
   233:	aload	5
   235:	invokevirtual	#341; //Method java/util/TreeSet.add:(Ljava/lang/Object;)Z
   238:	pop
   239:	return

public void c();
  Code:
   0:	aload_0
   1:	getfield	#160; //Field b:Ljava/util/List;
   4:	aload_0
   5:	getfield	#147; //Field B:Ljava/util/List;
   8:	invokeinterface	#401,  2; //InterfaceMethod java/util/List.removeAll:(Ljava/util/Collection;)Z
   13:	pop
   14:	iconst_0
   15:	istore_1
   16:	iload_1
   17:	aload_0
   18:	getfield	#147; //Field B:Ljava/util/List;
   21:	invokeinterface	#402,  1; //InterfaceMethod java/util/List.size:()I
   26:	if_icmpge	88
   29:	aload_0
   30:	getfield	#147; //Field B:Ljava/util/List;
   33:	iload_1
   34:	invokeinterface	#398,  2; //InterfaceMethod java/util/List.get:(I)Ljava/lang/Object;
   39:	checkcast	#45; //class dv
   42:	astore_2
   43:	aload_2
   44:	getfield	#129; //Field dv.af:I
   47:	istore_3
   48:	aload_2
   49:	getfield	#131; //Field dv.ah:I
   52:	istore	4
   54:	aload_2
   55:	getfield	#128; //Field dv.ae:Z
   58:	ifeq	82
   61:	aload_0
   62:	iload_3
   63:	iload	4
   65:	invokespecial	#264; //Method f:(II)Z
   68:	ifeq	82
   71:	aload_0
   72:	iload_3
   73:	iload	4
   75:	invokevirtual	#255; //Method c:(II)Ljn;
   78:	aload_2
   79:	invokevirtual	#359; //Method jn.b:(Ldv;)V
   82:	iinc	1, 1
   85:	goto	16
   88:	iconst_0
   89:	istore_1
   90:	iload_1
   91:	aload_0
   92:	getfield	#147; //Field B:Ljava/util/List;
   95:	invokeinterface	#402,  1; //InterfaceMethod java/util/List.size:()I
   100:	if_icmpge	126
   103:	aload_0
   104:	aload_0
   105:	getfield	#147; //Field B:Ljava/util/List;
   108:	iload_1
   109:	invokeinterface	#398,  2; //InterfaceMethod java/util/List.get:(I)Ljava/lang/Object;
   114:	checkcast	#45; //class dv
   117:	invokevirtual	#258; //Method c:(Ldv;)V
   120:	iinc	1, 1
   123:	goto	90
   126:	aload_0
   127:	getfield	#147; //Field B:Ljava/util/List;
   130:	invokeinterface	#397,  1; //InterfaceMethod java/util/List.clear:()V
   135:	iconst_0
   136:	istore_1
   137:	iload_1
   138:	aload_0
   139:	getfield	#160; //Field b:Ljava/util/List;
   142:	invokeinterface	#402,  1; //InterfaceMethod java/util/List.size:()I
   147:	if_icmpge	288
   150:	aload_0
   151:	getfield	#160; //Field b:Ljava/util/List;
   154:	iload_1
   155:	invokeinterface	#398,  2; //InterfaceMethod java/util/List.get:(I)Ljava/lang/Object;
   160:	checkcast	#45; //class dv
   163:	astore_2
   164:	aload_2
   165:	getfield	#134; //Field dv.k:Ldv;
   168:	ifnull	205
   171:	aload_2
   172:	getfield	#134; //Field dv.k:Ldv;
   175:	getfield	#123; //Field dv.F:Z
   178:	ifne	192
   181:	aload_2
   182:	getfield	#134; //Field dv.k:Ldv;
   185:	getfield	#133; //Field dv.j:Ldv;
   188:	aload_2
   189:	if_acmpeq	282
   192:	aload_2
   193:	getfield	#134; //Field dv.k:Ldv;
   196:	aconst_null
   197:	putfield	#133; //Field dv.j:Ldv;
   200:	aload_2
   201:	aconst_null
   202:	putfield	#134; //Field dv.k:Ldv;
   205:	aload_2
   206:	getfield	#123; //Field dv.F:Z
   209:	ifne	217
   212:	aload_0
   213:	aload_2
   214:	invokevirtual	#263; //Method e:(Ldv;)V
   217:	aload_2
   218:	getfield	#123; //Field dv.F:Z
   221:	ifeq	282
   224:	aload_2
   225:	getfield	#129; //Field dv.af:I
   228:	istore_3
   229:	aload_2
   230:	getfield	#131; //Field dv.ah:I
   233:	istore	4
   235:	aload_2
   236:	getfield	#128; //Field dv.ae:Z
   239:	ifeq	263
   242:	aload_0
   243:	iload_3
   244:	iload	4
   246:	invokespecial	#264; //Method f:(II)Z
   249:	ifeq	263
   252:	aload_0
   253:	iload_3
   254:	iload	4
   256:	invokevirtual	#255; //Method c:(II)Ljn;
   259:	aload_2
   260:	invokevirtual	#359; //Method jn.b:(Ldv;)V
   263:	aload_0
   264:	getfield	#160; //Field b:Ljava/util/List;
   267:	iload_1
   268:	iinc	1, -1
   271:	invokeinterface	#399,  2; //InterfaceMethod java/util/List.remove:(I)Ljava/lang/Object;
   276:	pop
   277:	aload_0
   278:	aload_2
   279:	invokevirtual	#258; //Method c:(Ldv;)V
   282:	iinc	1, 1
   285:	goto	137
   288:	iconst_0
   289:	istore_1
   290:	iload_1
   291:	aload_0
   292:	getfield	#161; //Field c:Ljava/util/List;
   295:	invokeinterface	#402,  1; //InterfaceMethod java/util/List.size:()I
   300:	if_icmpge	327
   303:	aload_0
   304:	getfield	#161; //Field c:Ljava/util/List;
   307:	iload_1
   308:	invokeinterface	#398,  2; //InterfaceMethod java/util/List.get:(I)Ljava/lang/Object;
   313:	checkcast	#35; //class av
   316:	astore_2
   317:	aload_2
   318:	invokevirtual	#210; //Method av.b:()V
   321:	iinc	1, 1
   324:	goto	290
   327:	return

public void e(dv);
  Code:
   0:	aload_0
   1:	aload_1
   2:	iconst_1
   3:	invokevirtual	#245; //Method a:(Ldv;Z)V
   6:	return

public void a(dv, boolean);
  Code:
   0:	aload_1
   1:	getfield	#135; //Field dv.p:D
   4:	invokestatic	#294; //Method hb.b:(D)I
   7:	istore_3
   8:	aload_1
   9:	getfield	#137; //Field dv.r:D
   12:	invokestatic	#294; //Method hb.b:(D)I
   15:	istore	4
   17:	bipush	16
   19:	istore	5
   21:	iload_2
   22:	ifne	55
   25:	aload_0
   26:	iload_3
   27:	iload	5
   29:	isub
   30:	iconst_0
   31:	iload	4
   33:	iload	5
   35:	isub
   36:	iload_3
   37:	iload	5
   39:	iadd
   40:	sipush	128
   43:	iload	4
   45:	iload	5
   47:	iadd
   48:	invokevirtual	#237; //Method a:(IIIIII)Z
   51:	ifne	55
   54:	return
   55:	aload_1
   56:	aload_1
   57:	getfield	#135; //Field dv.p:D
   60:	putfield	#125; //Field dv.N:D
   63:	aload_1
   64:	aload_1
   65:	getfield	#136; //Field dv.q:D
   68:	putfield	#126; //Field dv.O:D
   71:	aload_1
   72:	aload_1
   73:	getfield	#137; //Field dv.r:D
   76:	putfield	#127; //Field dv.P:D
   79:	aload_1
   80:	aload_1
   81:	getfield	#141; //Field dv.v:F
   84:	putfield	#143; //Field dv.x:F
   87:	aload_1
   88:	aload_1
   89:	getfield	#142; //Field dv.w:F
   92:	putfield	#144; //Field dv.y:F
   95:	iload_2
   96:	ifeq	124
   99:	aload_1
   100:	getfield	#128; //Field dv.ae:Z
   103:	ifeq	124
   106:	aload_1
   107:	getfield	#134; //Field dv.k:Ldv;
   110:	ifnull	120
   113:	aload_1
   114:	invokevirtual	#226; //Method dv.y:()V
   117:	goto	124
   120:	aload_1
   121:	invokevirtual	#222; //Method dv.b_:()V
   124:	aload_1
   125:	getfield	#135; //Field dv.p:D
   128:	ldc2_w	#102; //double 16.0d
   131:	ddiv
   132:	invokestatic	#294; //Method hb.b:(D)I
   135:	istore	6
   137:	aload_1
   138:	getfield	#136; //Field dv.q:D
   141:	ldc2_w	#102; //double 16.0d
   144:	ddiv
   145:	invokestatic	#294; //Method hb.b:(D)I
   148:	istore	7
   150:	aload_1
   151:	getfield	#137; //Field dv.r:D
   154:	ldc2_w	#102; //double 16.0d
   157:	ddiv
   158:	invokestatic	#294; //Method hb.b:(D)I
   161:	istore	8
   163:	aload_1
   164:	getfield	#128; //Field dv.ae:Z
   167:	ifeq	197
   170:	aload_1
   171:	getfield	#129; //Field dv.af:I
   174:	iload	6
   176:	if_icmpne	197
   179:	aload_1
   180:	getfield	#130; //Field dv.ag:I
   183:	iload	7
   185:	if_icmpne	197
   188:	aload_1
   189:	getfield	#131; //Field dv.ah:I
   192:	iload	8
   194:	if_icmpeq	275
   197:	aload_1
   198:	getfield	#128; //Field dv.ae:Z
   201:	ifeq	239
   204:	aload_0
   205:	aload_1
   206:	getfield	#129; //Field dv.af:I
   209:	aload_1
   210:	getfield	#131; //Field dv.ah:I
   213:	invokespecial	#264; //Method f:(II)Z
   216:	ifeq	239
   219:	aload_0
   220:	aload_1
   221:	getfield	#129; //Field dv.af:I
   224:	aload_1
   225:	getfield	#131; //Field dv.ah:I
   228:	invokevirtual	#255; //Method c:(II)Ljn;
   231:	aload_1
   232:	aload_1
   233:	getfield	#130; //Field dv.ag:I
   236:	invokevirtual	#352; //Method jn.a:(Ldv;I)V
   239:	aload_0
   240:	iload	6
   242:	iload	8
   244:	invokespecial	#264; //Method f:(II)Z
   247:	ifeq	270
   250:	aload_1
   251:	iconst_1
   252:	putfield	#128; //Field dv.ae:Z
   255:	aload_0
   256:	iload	6
   258:	iload	8
   260:	invokevirtual	#255; //Method c:(II)Ljn;
   263:	aload_1
   264:	invokevirtual	#351; //Method jn.a:(Ldv;)V
   267:	goto	275
   270:	aload_1
   271:	iconst_0
   272:	putfield	#128; //Field dv.ae:Z
   275:	iload_2
   276:	ifeq	338
   279:	aload_1
   280:	getfield	#128; //Field dv.ae:Z
   283:	ifeq	338
   286:	aload_1
   287:	getfield	#133; //Field dv.j:Ldv;
   290:	ifnull	338
   293:	aload_1
   294:	getfield	#133; //Field dv.j:Ldv;
   297:	getfield	#123; //Field dv.F:Z
   300:	ifne	314
   303:	aload_1
   304:	getfield	#133; //Field dv.j:Ldv;
   307:	getfield	#134; //Field dv.k:Ldv;
   310:	aload_1
   311:	if_acmpeq	330
   314:	aload_1
   315:	getfield	#133; //Field dv.j:Ldv;
   318:	aconst_null
   319:	putfield	#134; //Field dv.k:Ldv;
   322:	aload_1
   323:	aconst_null
   324:	putfield	#133; //Field dv.j:Ldv;
   327:	goto	338
   330:	aload_0
   331:	aload_1
   332:	getfield	#133; //Field dv.j:Ldv;
   335:	invokevirtual	#263; //Method e:(Ldv;)V
   338:	aload_1
   339:	getfield	#135; //Field dv.p:D
   342:	invokestatic	#321; //Method java/lang/Double.isNaN:(D)Z
   345:	ifne	358
   348:	aload_1
   349:	getfield	#135; //Field dv.p:D
   352:	invokestatic	#320; //Method java/lang/Double.isInfinite:(D)Z
   355:	ifeq	366
   358:	aload_1
   359:	aload_1
   360:	getfield	#125; //Field dv.N:D
   363:	putfield	#135; //Field dv.p:D
   366:	aload_1
   367:	getfield	#136; //Field dv.q:D
   370:	invokestatic	#321; //Method java/lang/Double.isNaN:(D)Z
   373:	ifne	386
   376:	aload_1
   377:	getfield	#136; //Field dv.q:D
   380:	invokestatic	#320; //Method java/lang/Double.isInfinite:(D)Z
   383:	ifeq	394
   386:	aload_1
   387:	aload_1
   388:	getfield	#126; //Field dv.O:D
   391:	putfield	#136; //Field dv.q:D
   394:	aload_1
   395:	getfield	#137; //Field dv.r:D
   398:	invokestatic	#321; //Method java/lang/Double.isNaN:(D)Z
   401:	ifne	414
   404:	aload_1
   405:	getfield	#137; //Field dv.r:D
   408:	invokestatic	#320; //Method java/lang/Double.isInfinite:(D)Z
   411:	ifeq	422
   414:	aload_1
   415:	aload_1
   416:	getfield	#127; //Field dv.P:D
   419:	putfield	#137; //Field dv.r:D
   422:	aload_1
   423:	getfield	#142; //Field dv.w:F
   426:	f2d
   427:	invokestatic	#321; //Method java/lang/Double.isNaN:(D)Z
   430:	ifne	444
   433:	aload_1
   434:	getfield	#142; //Field dv.w:F
   437:	f2d
   438:	invokestatic	#320; //Method java/lang/Double.isInfinite:(D)Z
   441:	ifeq	452
   444:	aload_1
   445:	aload_1
   446:	getfield	#144; //Field dv.y:F
   449:	putfield	#142; //Field dv.w:F
   452:	aload_1
   453:	getfield	#141; //Field dv.v:F
   456:	f2d
   457:	invokestatic	#321; //Method java/lang/Double.isNaN:(D)Z
   460:	ifne	474
   463:	aload_1
   464:	getfield	#141; //Field dv.v:F
   467:	f2d
   468:	invokestatic	#320; //Method java/lang/Double.isInfinite:(D)Z
   471:	ifeq	482
   474:	aload_1
   475:	aload_1
   476:	getfield	#143; //Field dv.x:F
   479:	putfield	#141; //Field dv.v:F
   482:	return

public boolean a(ds);
  Code:
   0:	aload_0
   1:	aconst_null
   2:	aload_1
   3:	invokevirtual	#254; //Method b:(Ldv;Lds;)Ljava/util/List;
   6:	astore_2
   7:	iconst_0
   8:	istore_3
   9:	iload_3
   10:	aload_2
   11:	invokeinterface	#402,  1; //InterfaceMethod java/util/List.size:()I
   16:	if_icmpge	55
   19:	aload_2
   20:	iload_3
   21:	invokeinterface	#398,  2; //InterfaceMethod java/util/List.get:(I)Ljava/lang/Object;
   26:	checkcast	#45; //class dv
   29:	astore	4
   31:	aload	4
   33:	getfield	#123; //Field dv.F:Z
   36:	ifne	49
   39:	aload	4
   41:	getfield	#132; //Field dv.i:Z
   44:	ifeq	49
   47:	iconst_0
   48:	ireturn
   49:	iinc	3, 1
   52:	goto	9
   55:	iconst_1
   56:	ireturn

public boolean b(ds);
  Code:
   0:	aload_1
   1:	getfield	#117; //Field ds.a:D
   4:	invokestatic	#294; //Method hb.b:(D)I
   7:	istore_2
   8:	aload_1
   9:	getfield	#120; //Field ds.d:D
   12:	dconst_1
   13:	dadd
   14:	invokestatic	#294; //Method hb.b:(D)I
   17:	istore_3
   18:	aload_1
   19:	getfield	#118; //Field ds.b:D
   22:	invokestatic	#294; //Method hb.b:(D)I
   25:	istore	4
   27:	aload_1
   28:	getfield	#121; //Field ds.e:D
   31:	dconst_1
   32:	dadd
   33:	invokestatic	#294; //Method hb.b:(D)I
   36:	istore	5
   38:	aload_1
   39:	getfield	#119; //Field ds.c:D
   42:	invokestatic	#294; //Method hb.b:(D)I
   45:	istore	6
   47:	aload_1
   48:	getfield	#122; //Field ds.f:D
   51:	dconst_1
   52:	dadd
   53:	invokestatic	#294; //Method hb.b:(D)I
   56:	istore	7
   58:	aload_1
   59:	getfield	#117; //Field ds.a:D
   62:	dconst_0
   63:	dcmpg
   64:	ifge	70
   67:	iinc	2, -1
   70:	aload_1
   71:	getfield	#118; //Field ds.b:D
   74:	dconst_0
   75:	dcmpg
   76:	ifge	82
   79:	iinc	4, -1
   82:	aload_1
   83:	getfield	#119; //Field ds.c:D
   86:	dconst_0
   87:	dcmpg
   88:	ifge	94
   91:	iinc	6, -1
   94:	iload_2
   95:	istore	8
   97:	iload	8
   99:	iload_3
   100:	if_icmpge	177
   103:	iload	4
   105:	istore	9
   107:	iload	9
   109:	iload	5
   111:	if_icmpge	171
   114:	iload	6
   116:	istore	10
   118:	iload	10
   120:	iload	7
   122:	if_icmpge	165
   125:	getstatic	#196; //Field fw.n:[Lfw;
   128:	aload_0
   129:	iload	8
   131:	iload	9
   133:	iload	10
   135:	invokevirtual	#234; //Method a:(III)I
   138:	aaload
   139:	astore	11
   141:	aload	11
   143:	ifnull	159
   146:	aload	11
   148:	getfield	#195; //Field fw.bt:Ljr;
   151:	invokevirtual	#366; //Method jr.d:()Z
   154:	ifeq	159
   157:	iconst_1
   158:	ireturn
   159:	iinc	10, 1
   162:	goto	118
   165:	iinc	9, 1
   168:	goto	107
   171:	iinc	8, 1
   174:	goto	97
   177:	iconst_0
   178:	ireturn

public boolean c(ds);
  Code:
   0:	aload_1
   1:	getfield	#117; //Field ds.a:D
   4:	invokestatic	#294; //Method hb.b:(D)I
   7:	istore_2
   8:	aload_1
   9:	getfield	#120; //Field ds.d:D
   12:	dconst_1
   13:	dadd
   14:	invokestatic	#294; //Method hb.b:(D)I
   17:	istore_3
   18:	aload_1
   19:	getfield	#118; //Field ds.b:D
   22:	invokestatic	#294; //Method hb.b:(D)I
   25:	istore	4
   27:	aload_1
   28:	getfield	#121; //Field ds.e:D
   31:	dconst_1
   32:	dadd
   33:	invokestatic	#294; //Method hb.b:(D)I
   36:	istore	5
   38:	aload_1
   39:	getfield	#119; //Field ds.c:D
   42:	invokestatic	#294; //Method hb.b:(D)I
   45:	istore	6
   47:	aload_1
   48:	getfield	#122; //Field ds.f:D
   51:	dconst_1
   52:	dadd
   53:	invokestatic	#294; //Method hb.b:(D)I
   56:	istore	7
   58:	iload_2
   59:	istore	8
   61:	iload	8
   63:	iload_3
   64:	if_icmpge	154
   67:	iload	4
   69:	istore	9
   71:	iload	9
   73:	iload	5
   75:	if_icmpge	148
   78:	iload	6
   80:	istore	10
   82:	iload	10
   84:	iload	7
   86:	if_icmpge	142
   89:	aload_0
   90:	iload	8
   92:	iload	9
   94:	iload	10
   96:	invokevirtual	#234; //Method a:(III)I
   99:	istore	11
   101:	iload	11
   103:	getstatic	#193; //Field fw.as:Ljm;
   106:	getfield	#203; //Field jm.bi:I
   109:	if_icmpeq	134
   112:	iload	11
   114:	getstatic	#188; //Field fw.D:Lfw;
   117:	getfield	#194; //Field fw.bi:I
   120:	if_icmpeq	134
   123:	iload	11
   125:	getstatic	#189; //Field fw.E:Lfw;
   128:	getfield	#194; //Field fw.bi:I
   131:	if_icmpne	136
   134:	iconst_1
   135:	ireturn
   136:	iinc	10, 1
   139:	goto	82
   142:	iinc	9, 1
   145:	goto	71
   148:	iinc	8, 1
   151:	goto	61
   154:	iconst_0
   155:	ireturn

public boolean a(ds, jr, dv);
  Code:
   0:	aload_1
   1:	getfield	#117; //Field ds.a:D
   4:	invokestatic	#294; //Method hb.b:(D)I
   7:	istore	4
   9:	aload_1
   10:	getfield	#120; //Field ds.d:D
   13:	dconst_1
   14:	dadd
   15:	invokestatic	#294; //Method hb.b:(D)I
   18:	istore	5
   20:	aload_1
   21:	getfield	#118; //Field ds.b:D
   24:	invokestatic	#294; //Method hb.b:(D)I
   27:	istore	6
   29:	aload_1
   30:	getfield	#121; //Field ds.e:D
   33:	dconst_1
   34:	dadd
   35:	invokestatic	#294; //Method hb.b:(D)I
   38:	istore	7
   40:	aload_1
   41:	getfield	#119; //Field ds.c:D
   44:	invokestatic	#294; //Method hb.b:(D)I
   47:	istore	8
   49:	aload_1
   50:	getfield	#122; //Field ds.f:D
   53:	dconst_1
   54:	dadd
   55:	invokestatic	#294; //Method hb.b:(D)I
   58:	istore	9
   60:	iconst_0
   61:	istore	10
   63:	dconst_0
   64:	dconst_0
   65:	dconst_0
   66:	invokestatic	#212; //Method ba.b:(DDD)Lba;
   69:	astore	11
   71:	iload	4
   73:	istore	12
   75:	iload	12
   77:	iload	5
   79:	if_icmpge	201
   82:	iload	6
   84:	istore	13
   86:	iload	13
   88:	iload	7
   90:	if_icmpge	195
   93:	iload	8
   95:	istore	14
   97:	iload	14
   99:	iload	9
   101:	if_icmpge	189
   104:	getstatic	#196; //Field fw.n:[Lfw;
   107:	aload_0
   108:	iload	12
   110:	iload	13
   112:	iload	14
   114:	invokevirtual	#234; //Method a:(III)I
   117:	aaload
   118:	astore	15
   120:	aload	15
   122:	ifnull	183
   125:	aload	15
   127:	getfield	#195; //Field fw.bt:Ljr;
   130:	aload_2
   131:	if_acmpne	183
   134:	iload	13
   136:	iconst_1
   137:	iadd
   138:	i2f
   139:	aload_0
   140:	iload	12
   142:	iload	13
   144:	iload	14
   146:	invokevirtual	#251; //Method b:(III)I
   149:	invokestatic	#219; //Method cx.b:(I)F
   152:	fsub
   153:	f2d
   154:	dstore	16
   156:	iload	7
   158:	i2d
   159:	dload	16
   161:	dcmpl
   162:	iflt	183
   165:	iconst_1
   166:	istore	10
   168:	aload	15
   170:	aload_0
   171:	iload	12
   173:	iload	13
   175:	iload	14
   177:	aload_3
   178:	aload	11
   180:	invokevirtual	#287; //Method fw.a:(Lel;IIILdv;Lba;)V
   183:	iinc	14, 1
   186:	goto	97
   189:	iinc	13, 1
   192:	goto	86
   195:	iinc	12, 1
   198:	goto	75
   201:	aload	11
   203:	invokevirtual	#213; //Method ba.c:()D
   206:	dconst_0
   207:	dcmpl
   208:	ifle	274
   211:	aload	11
   213:	invokevirtual	#211; //Method ba.b:()Lba;
   216:	astore	11
   218:	ldc2_w	#90; //double 0.0040d
   221:	dstore	12
   223:	aload_3
   224:	dup
   225:	getfield	#138; //Field dv.s:D
   228:	aload	11
   230:	getfield	#106; //Field ba.a:D
   233:	dload	12
   235:	dmul
   236:	dadd
   237:	putfield	#138; //Field dv.s:D
   240:	aload_3
   241:	dup
   242:	getfield	#139; //Field dv.t:D
   245:	aload	11
   247:	getfield	#107; //Field ba.b:D
   250:	dload	12
   252:	dmul
   253:	dadd
   254:	putfield	#139; //Field dv.t:D
   257:	aload_3
   258:	dup
   259:	getfield	#140; //Field dv.u:D
   262:	aload	11
   264:	getfield	#108; //Field ba.c:D
   267:	dload	12
   269:	dmul
   270:	dadd
   271:	putfield	#140; //Field dv.u:D
   274:	iload	10
   276:	ireturn

public boolean a(ds, jr);
  Code:
   0:	aload_1
   1:	getfield	#117; //Field ds.a:D
   4:	invokestatic	#294; //Method hb.b:(D)I
   7:	istore_3
   8:	aload_1
   9:	getfield	#120; //Field ds.d:D
   12:	dconst_1
   13:	dadd
   14:	invokestatic	#294; //Method hb.b:(D)I
   17:	istore	4
   19:	aload_1
   20:	getfield	#118; //Field ds.b:D
   23:	invokestatic	#294; //Method hb.b:(D)I
   26:	istore	5
   28:	aload_1
   29:	getfield	#121; //Field ds.e:D
   32:	dconst_1
   33:	dadd
   34:	invokestatic	#294; //Method hb.b:(D)I
   37:	istore	6
   39:	aload_1
   40:	getfield	#119; //Field ds.c:D
   43:	invokestatic	#294; //Method hb.b:(D)I
   46:	istore	7
   48:	aload_1
   49:	getfield	#122; //Field ds.f:D
   52:	dconst_1
   53:	dadd
   54:	invokestatic	#294; //Method hb.b:(D)I
   57:	istore	8
   59:	iload_3
   60:	istore	9
   62:	iload	9
   64:	iload	4
   66:	if_icmpge	141
   69:	iload	5
   71:	istore	10
   73:	iload	10
   75:	iload	6
   77:	if_icmpge	135
   80:	iload	7
   82:	istore	11
   84:	iload	11
   86:	iload	8
   88:	if_icmpge	129
   91:	getstatic	#196; //Field fw.n:[Lfw;
   94:	aload_0
   95:	iload	9
   97:	iload	10
   99:	iload	11
   101:	invokevirtual	#234; //Method a:(III)I
   104:	aaload
   105:	astore	12
   107:	aload	12
   109:	ifnull	123
   112:	aload	12
   114:	getfield	#195; //Field fw.bt:Ljr;
   117:	aload_2
   118:	if_acmpne	123
   121:	iconst_1
   122:	ireturn
   123:	iinc	11, 1
   126:	goto	84
   129:	iinc	10, 1
   132:	goto	73
   135:	iinc	9, 1
   138:	goto	62
   141:	iconst_0
   142:	ireturn

public boolean b(ds, jr);
  Code:
   0:	aload_1
   1:	getfield	#117; //Field ds.a:D
   4:	invokestatic	#294; //Method hb.b:(D)I
   7:	istore_3
   8:	aload_1
   9:	getfield	#120; //Field ds.d:D
   12:	dconst_1
   13:	dadd
   14:	invokestatic	#294; //Method hb.b:(D)I
   17:	istore	4
   19:	aload_1
   20:	getfield	#118; //Field ds.b:D
   23:	invokestatic	#294; //Method hb.b:(D)I
   26:	istore	5
   28:	aload_1
   29:	getfield	#121; //Field ds.e:D
   32:	dconst_1
   33:	dadd
   34:	invokestatic	#294; //Method hb.b:(D)I
   37:	istore	6
   39:	aload_1
   40:	getfield	#119; //Field ds.c:D
   43:	invokestatic	#294; //Method hb.b:(D)I
   46:	istore	7
   48:	aload_1
   49:	getfield	#122; //Field ds.f:D
   52:	dconst_1
   53:	dadd
   54:	invokestatic	#294; //Method hb.b:(D)I
   57:	istore	8
   59:	iload_3
   60:	istore	9
   62:	iload	9
   64:	iload	4
   66:	if_icmpge	192
   69:	iload	5
   71:	istore	10
   73:	iload	10
   75:	iload	6
   77:	if_icmpge	186
   80:	iload	7
   82:	istore	11
   84:	iload	11
   86:	iload	8
   88:	if_icmpge	180
   91:	getstatic	#196; //Field fw.n:[Lfw;
   94:	aload_0
   95:	iload	9
   97:	iload	10
   99:	iload	11
   101:	invokevirtual	#234; //Method a:(III)I
   104:	aaload
   105:	astore	12
   107:	aload	12
   109:	ifnull	174
   112:	aload	12
   114:	getfield	#195; //Field fw.bt:Ljr;
   117:	aload_2
   118:	if_acmpne	174
   121:	aload_0
   122:	iload	9
   124:	iload	10
   126:	iload	11
   128:	invokevirtual	#251; //Method b:(III)I
   131:	istore	13
   133:	iload	10
   135:	iconst_1
   136:	iadd
   137:	i2d
   138:	dstore	14
   140:	iload	13
   142:	bipush	8
   144:	if_icmpge	162
   147:	iload	10
   149:	iconst_1
   150:	iadd
   151:	i2d
   152:	iload	13
   154:	i2d
   155:	ldc2_w	#100; //double 8.0d
   158:	ddiv
   159:	dsub
   160:	dstore	14
   162:	dload	14
   164:	aload_1
   165:	getfield	#118; //Field ds.b:D
   168:	dcmpl
   169:	iflt	174
   172:	iconst_1
   173:	ireturn
   174:	iinc	11, 1
   177:	goto	84
   180:	iinc	10, 1
   183:	goto	73
   186:	iinc	9, 1
   189:	goto	62
   192:	iconst_0
   193:	ireturn

public void a(dv, double, double, double, float);
  Code:
   0:	new	#40; //class cg
   3:	dup
   4:	invokespecial	#215; //Method cg."<init>":()V
   7:	aload_0
   8:	aload_1
   9:	dload_2
   10:	dload	4
   12:	dload	6
   14:	fload	8
   16:	invokevirtual	#216; //Method cg.a:(Lel;Ldv;DDDF)V
   19:	return

public float a(ba, ds);
  Code:
   0:	dconst_1
   1:	aload_2
   2:	getfield	#120; //Field ds.d:D
   5:	aload_2
   6:	getfield	#117; //Field ds.a:D
   9:	dsub
   10:	ldc2_w	#96; //double 2.0d
   13:	dmul
   14:	dconst_1
   15:	dadd
   16:	ddiv
   17:	dstore_3
   18:	dconst_1
   19:	aload_2
   20:	getfield	#121; //Field ds.e:D
   23:	aload_2
   24:	getfield	#118; //Field ds.b:D
   27:	dsub
   28:	ldc2_w	#96; //double 2.0d
   31:	dmul
   32:	dconst_1
   33:	dadd
   34:	ddiv
   35:	dstore	5
   37:	dconst_1
   38:	aload_2
   39:	getfield	#122; //Field ds.f:D
   42:	aload_2
   43:	getfield	#119; //Field ds.c:D
   46:	dsub
   47:	ldc2_w	#96; //double 2.0d
   50:	dmul
   51:	dconst_1
   52:	dadd
   53:	ddiv
   54:	dstore	7
   56:	iconst_0
   57:	istore	9
   59:	iconst_0
   60:	istore	10
   62:	fconst_0
   63:	fstore	11
   65:	fload	11
   67:	fconst_1
   68:	fcmpg
   69:	ifgt	210
   72:	fconst_0
   73:	fstore	12
   75:	fload	12
   77:	fconst_1
   78:	fcmpg
   79:	ifgt	199
   82:	fconst_0
   83:	fstore	13
   85:	fload	13
   87:	fconst_1
   88:	fcmpg
   89:	ifgt	187
   92:	aload_2
   93:	getfield	#117; //Field ds.a:D
   96:	aload_2
   97:	getfield	#120; //Field ds.d:D
   100:	aload_2
   101:	getfield	#117; //Field ds.a:D
   104:	dsub
   105:	fload	11
   107:	f2d
   108:	dmul
   109:	dadd
   110:	dstore	14
   112:	aload_2
   113:	getfield	#118; //Field ds.b:D
   116:	aload_2
   117:	getfield	#121; //Field ds.e:D
   120:	aload_2
   121:	getfield	#118; //Field ds.b:D
   124:	dsub
   125:	fload	12
   127:	f2d
   128:	dmul
   129:	dadd
   130:	dstore	16
   132:	aload_2
   133:	getfield	#119; //Field ds.c:D
   136:	aload_2
   137:	getfield	#122; //Field ds.f:D
   140:	aload_2
   141:	getfield	#119; //Field ds.c:D
   144:	dsub
   145:	fload	13
   147:	f2d
   148:	dmul
   149:	dadd
   150:	dstore	18
   152:	aload_0
   153:	dload	14
   155:	dload	16
   157:	dload	18
   159:	invokestatic	#212; //Method ba.b:(DDD)Lba;
   162:	aload_1
   163:	invokevirtual	#239; //Method a:(Lba;Lba;)Lgk;
   166:	ifnonnull	172
   169:	iinc	9, 1
   172:	iinc	10, 1
   175:	fload	13
   177:	f2d
   178:	dload	7
   180:	dadd
   181:	d2f
   182:	fstore	13
   184:	goto	85
   187:	fload	12
   189:	f2d
   190:	dload	5
   192:	dadd
   193:	d2f
   194:	fstore	12
   196:	goto	75
   199:	fload	11
   201:	f2d
   202:	dload_3
   203:	dadd
   204:	d2f
   205:	fstore	11
   207:	goto	65
   210:	iload	9
   212:	i2f
   213:	iload	10
   215:	i2f
   216:	fdiv
   217:	freturn

public av k(int, int, int);
  Code:
   0:	aload_0
   1:	iload_1
   2:	iconst_4
   3:	ishr
   4:	iload_3
   5:	iconst_4
   6:	ishr
   7:	invokevirtual	#255; //Method c:(II)Ljn;
   10:	astore	4
   12:	aload	4
   14:	ifnull	32
   17:	aload	4
   19:	iload_1
   20:	bipush	15
   22:	iand
   23:	iload_2
   24:	iload_3
   25:	bipush	15
   27:	iand
   28:	invokevirtual	#362; //Method jn.d:(III)Lav;
   31:	areturn
   32:	aconst_null
   33:	areturn

public void a(int, int, int, av);
  Code:
   0:	aload_0
   1:	iload_1
   2:	iconst_4
   3:	ishr
   4:	iload_3
   5:	iconst_4
   6:	ishr
   7:	invokevirtual	#255; //Method c:(II)Ljn;
   10:	astore	5
   12:	aload	5
   14:	ifnull	33
   17:	aload	5
   19:	iload_1
   20:	bipush	15
   22:	iand
   23:	iload_2
   24:	iload_3
   25:	bipush	15
   27:	iand
   28:	aload	4
   30:	invokevirtual	#348; //Method jn.a:(IIILav;)V
   33:	return

public void l(int, int, int);
  Code:
   0:	aload_0
   1:	iload_1
   2:	iconst_4
   3:	ishr
   4:	iload_3
   5:	iconst_4
   6:	ishr
   7:	invokevirtual	#255; //Method c:(II)Ljn;
   10:	astore	4
   12:	aload	4
   14:	ifnull	31
   17:	aload	4
   19:	iload_1
   20:	bipush	15
   22:	iand
   23:	iload_2
   24:	iload_3
   25:	bipush	15
   27:	iand
   28:	invokevirtual	#363; //Method jn.e:(III)V
   31:	return

public boolean d(int, int, int);
  Code:
   0:	getstatic	#196; //Field fw.n:[Lfw;
   3:	aload_0
   4:	iload_1
   5:	iload_2
   6:	iload_3
   7:	invokevirtual	#234; //Method a:(III)I
   10:	aaload
   11:	astore	4
   13:	aload	4
   15:	ifnonnull	20
   18:	iconst_0
   19:	ireturn
   20:	aload	4
   22:	invokevirtual	#282; //Method fw.a:()Z
   25:	ireturn

public boolean d();
  Code:
   0:	aload_0
   1:	getfield	#155; //Field J:I
   4:	bipush	10
   6:	if_icmplt	11
   9:	iconst_0
   10:	ireturn
   11:	aload_0
   12:	dup
   13:	getfield	#155; //Field J:I
   16:	iconst_1
   17:	iadd
   18:	putfield	#155; //Field J:I
   21:	bipush	100
   23:	istore_1
   24:	aload_0
   25:	getfield	#146; //Field A:Ljava/util/List;
   28:	invokeinterface	#402,  1; //InterfaceMethod java/util/List.size:()I
   33:	ifle	87
   36:	iinc	1, -1
   39:	iload_1
   40:	ifgt	57
   43:	iconst_1
   44:	istore_2
   45:	aload_0
   46:	dup
   47:	getfield	#155; //Field J:I
   50:	iconst_1
   51:	isub
   52:	putfield	#155; //Field J:I
   55:	iload_2
   56:	ireturn
   57:	aload_0
   58:	getfield	#146; //Field A:Ljava/util/List;
   61:	aload_0
   62:	getfield	#146; //Field A:Ljava/util/List;
   65:	invokeinterface	#402,  1; //InterfaceMethod java/util/List.size:()I
   70:	iconst_1
   71:	isub
   72:	invokeinterface	#399,  2; //InterfaceMethod java/util/List.remove:(I)Ljava/lang/Object;
   77:	checkcast	#46; //class eb
   80:	aload_0
   81:	invokevirtual	#229; //Method eb.a:(Lel;)V
   84:	goto	24
   87:	iconst_0
   88:	istore_2
   89:	aload_0
   90:	dup
   91:	getfield	#155; //Field J:I
   94:	iconst_1
   95:	isub
   96:	putfield	#155; //Field J:I
   99:	iload_2
   100:	ireturn
   101:	astore_3
   102:	aload_0
   103:	dup
   104:	getfield	#155; //Field J:I
   107:	iconst_1
   108:	isub
   109:	putfield	#155; //Field J:I
   112:	aload_3
   113:	athrow
  Exception table:
   from   to  target type
    21    45   101   any
    57    89   101   any
   101   102   101   any

public void a(dj, int, int, int, int, int, int);
  Code:
   0:	aload_0
   1:	aload_1
   2:	iload_2
   3:	iload_3
   4:	iload	4
   6:	iload	5
   8:	iload	6
   10:	iload	7
   12:	iconst_1
   13:	invokevirtual	#243; //Method a:(Ldj;IIIIIIZ)V
   16:	return

public void a(dj, int, int, int, int, int, int, boolean);
  Code:
   0:	aload_0
   1:	getfield	#174; //Field q:Lie;
   4:	getfield	#200; //Field ie.c:Z
   7:	ifeq	18
   10:	aload_1
   11:	getstatic	#114; //Field dj.a:Ldj;
   14:	if_acmpne	18
   17:	return
   18:	getstatic	#182; //Field y:I
   21:	iconst_1
   22:	iadd
   23:	putstatic	#182; //Field y:I
   26:	getstatic	#182; //Field y:I
   29:	bipush	50
   31:	if_icmpne	43
   34:	getstatic	#182; //Field y:I
   37:	iconst_1
   38:	isub
   39:	putstatic	#182; //Field y:I
   42:	return
   43:	iload	5
   45:	iload_2
   46:	iadd
   47:	iconst_2
   48:	idiv
   49:	istore	9
   51:	iload	7
   53:	iload	4
   55:	iadd
   56:	iconst_2
   57:	idiv
   58:	istore	10
   60:	aload_0
   61:	iload	9
   63:	bipush	64
   65:	iload	10
   67:	invokevirtual	#261; //Method e:(III)Z
   70:	ifne	82
   73:	getstatic	#182; //Field y:I
   76:	iconst_1
   77:	isub
   78:	putstatic	#182; //Field y:I
   81:	return
   82:	aload_0
   83:	getfield	#146; //Field A:Ljava/util/List;
   86:	invokeinterface	#402,  1; //InterfaceMethod java/util/List.size:()I
   91:	istore	11
   93:	iload	8
   95:	ifeq	192
   98:	iconst_4
   99:	istore	12
   101:	iload	12
   103:	iload	11
   105:	if_icmple	112
   108:	iload	11
   110:	istore	12
   112:	iconst_0
   113:	istore	13
   115:	iload	13
   117:	iload	12
   119:	if_icmpge	192
   122:	aload_0
   123:	getfield	#146; //Field A:Ljava/util/List;
   126:	aload_0
   127:	getfield	#146; //Field A:Ljava/util/List;
   130:	invokeinterface	#402,  1; //InterfaceMethod java/util/List.size:()I
   135:	iload	13
   137:	isub
   138:	iconst_1
   139:	isub
   140:	invokeinterface	#398,  2; //InterfaceMethod java/util/List.get:(I)Ljava/lang/Object;
   145:	checkcast	#46; //class eb
   148:	astore	14
   150:	aload	14
   152:	getfield	#145; //Field eb.a:Ldj;
   155:	aload_1
   156:	if_acmpne	186
   159:	aload	14
   161:	iload_2
   162:	iload_3
   163:	iload	4
   165:	iload	5
   167:	iload	6
   169:	iload	7
   171:	invokevirtual	#228; //Method eb.a:(IIIIII)Z
   174:	ifeq	186
   177:	getstatic	#182; //Field y:I
   180:	iconst_1
   181:	isub
   182:	putstatic	#182; //Field y:I
   185:	return
   186:	iinc	13, 1
   189:	goto	115
   192:	aload_0
   193:	getfield	#146; //Field A:Ljava/util/List;
   196:	new	#46; //class eb
   199:	dup
   200:	aload_1
   201:	iload_2
   202:	iload_3
   203:	iload	4
   205:	iload	5
   207:	iload	6
   209:	iload	7
   211:	invokespecial	#227; //Method eb."<init>":(Ldj;IIIIII)V
   214:	invokeinterface	#395,  2; //InterfaceMethod java/util/List.add:(Ljava/lang/Object;)Z
   219:	pop
   220:	aload_0
   221:	getfield	#146; //Field A:Ljava/util/List;
   224:	invokeinterface	#402,  1; //InterfaceMethod java/util/List.size:()I
   229:	ldc	#2; //int 100000
   231:	if_icmple	243
   234:	aload_0
   235:	getfield	#146; //Field A:Ljava/util/List;
   238:	invokeinterface	#397,  1; //InterfaceMethod java/util/List.clear:()V
   243:	getstatic	#182; //Field y:I
   246:	iconst_1
   247:	isub
   248:	putstatic	#182; //Field y:I
   251:	return

public void e();
  Code:
   0:	aload_0
   1:	fconst_1
   2:	invokevirtual	#233; //Method a:(F)I
   5:	istore_1
   6:	iload_1
   7:	aload_0
   8:	getfield	#164; //Field f:I
   11:	if_icmpeq	19
   14:	aload_0
   15:	iload_1
   16:	putfield	#164; //Field f:I
   19:	return

public void f();
  Code:
   0:	aload_0
   1:	invokestatic	#214; //Method bt.a:(Lel;)I
   4:	pop
   5:	aload_0
   6:	getfield	#152; //Field G:Lbr;
   9:	invokeinterface	#386,  1; //InterfaceMethod br.a:()Z
   14:	pop
   15:	aload_0
   16:	fconst_1
   17:	invokevirtual	#233; //Method a:(F)I
   20:	istore_1
   21:	iload_1
   22:	aload_0
   23:	getfield	#164; //Field f:I
   26:	if_icmpeq	73
   29:	aload_0
   30:	iload_1
   31:	putfield	#164; //Field f:I
   34:	iconst_0
   35:	istore_2
   36:	iload_2
   37:	aload_0
   38:	getfield	#175; //Field r:Ljava/util/List;
   41:	invokeinterface	#402,  1; //InterfaceMethod java/util/List.size:()I
   46:	if_icmpge	73
   49:	aload_0
   50:	getfield	#175; //Field r:Ljava/util/List;
   53:	iload_2
   54:	invokeinterface	#398,  2; //InterfaceMethod java/util/List.get:(I)Ljava/lang/Object;
   59:	checkcast	#37; //class bj
   62:	invokeinterface	#377,  1; //InterfaceMethod bj.a:()V
   67:	iinc	2, 1
   70:	goto	36
   73:	aload_0
   74:	dup
   75:	getfield	#163; //Field e:J
   78:	lconst_1
   79:	ladd
   80:	putfield	#163; //Field e:J
   83:	aload_0
   84:	getfield	#163; //Field e:J
   87:	aload_0
   88:	getfield	#168; //Field j:I
   91:	i2l
   92:	lrem
   93:	lconst_0
   94:	lcmp
   95:	ifne	104
   98:	aload_0
   99:	iconst_0
   100:	aconst_null
   101:	invokevirtual	#248; //Method a:(ZLiv;)V
   104:	aload_0
   105:	iconst_0
   106:	invokevirtual	#247; //Method a:(Z)Z
   109:	pop
   110:	aload_0
   111:	invokevirtual	#266; //Method g:()V
   114:	return

protected void g();
  Code:
   0:	aload_0
   1:	getfield	#156; //Field K:Ljava/util/Set;
   4:	invokeinterface	#404,  1; //InterfaceMethod java/util/Set.clear:()V
   9:	iconst_0
   10:	istore_1
   11:	iload_1
   12:	aload_0
   13:	getfield	#162; //Field d:Ljava/util/List;
   16:	invokeinterface	#402,  1; //InterfaceMethod java/util/List.size:()I
   21:	if_icmpge	135
   24:	aload_0
   25:	getfield	#162; //Field d:Ljava/util/List;
   28:	iload_1
   29:	invokeinterface	#398,  2; //InterfaceMethod java/util/List.get:(I)Ljava/lang/Object;
   34:	checkcast	#50; //class ft
   37:	astore_2
   38:	aload_2
   39:	getfield	#184; //Field ft.p:D
   42:	ldc2_w	#102; //double 16.0d
   45:	ddiv
   46:	invokestatic	#294; //Method hb.b:(D)I
   49:	istore_3
   50:	aload_2
   51:	getfield	#185; //Field ft.r:D
   54:	ldc2_w	#102; //double 16.0d
   57:	ddiv
   58:	invokestatic	#294; //Method hb.b:(D)I
   61:	istore	4
   63:	bipush	9
   65:	istore	5
   67:	iload	5
   69:	ineg
   70:	istore	6
   72:	iload	6
   74:	iload	5
   76:	if_icmpgt	129
   79:	iload	5
   81:	ineg
   82:	istore	7
   84:	iload	7
   86:	iload	5
   88:	if_icmpgt	123
   91:	aload_0
   92:	getfield	#156; //Field K:Ljava/util/Set;
   95:	new	#84; //class ka
   98:	dup
   99:	iload	6
   101:	iload_3
   102:	iadd
   103:	iload	7
   105:	iload	4
   107:	iadd
   108:	invokespecial	#367; //Method ka."<init>":(II)V
   111:	invokeinterface	#403,  2; //InterfaceMethod java/util/Set.add:(Ljava/lang/Object;)Z
   116:	pop
   117:	iinc	7, 1
   120:	goto	84
   123:	iinc	6, 1
   126:	goto	72
   129:	iinc	1, 1
   132:	goto	11
   135:	aload_0
   136:	getfield	#157; //Field L:I
   139:	ifle	152
   142:	aload_0
   143:	dup
   144:	getfield	#157; //Field L:I
   147:	iconst_1
   148:	isub
   149:	putfield	#157; //Field L:I
   152:	aload_0
   153:	getfield	#156; //Field K:Ljava/util/Set;
   156:	invokeinterface	#406,  1; //InterfaceMethod java/util/Set.iterator:()Ljava/util/Iterator;
   161:	astore_1
   162:	aload_1
   163:	invokeinterface	#393,  1; //InterfaceMethod java/util/Iterator.hasNext:()Z
   168:	ifeq	591
   171:	aload_1
   172:	invokeinterface	#394,  1; //InterfaceMethod java/util/Iterator.next:()Ljava/lang/Object;
   177:	checkcast	#84; //class ka
   180:	astore_2
   181:	aload_2
   182:	getfield	#206; //Field ka.a:I
   185:	bipush	16
   187:	imul
   188:	istore_3
   189:	aload_2
   190:	getfield	#207; //Field ka.b:I
   193:	bipush	16
   195:	imul
   196:	istore	4
   198:	aload_0
   199:	aload_2
   200:	getfield	#206; //Field ka.a:I
   203:	aload_2
   204:	getfield	#207; //Field ka.b:I
   207:	invokevirtual	#255; //Method c:(II)Ljn;
   210:	astore	5
   212:	aload_0
   213:	getfield	#157; //Field L:I
   216:	ifne	466
   219:	aload_0
   220:	aload_0
   221:	getfield	#165; //Field g:I
   224:	iconst_3
   225:	imul
   226:	aload_0
   227:	getfield	#166; //Field h:I
   230:	iadd
   231:	putfield	#165; //Field g:I
   234:	aload_0
   235:	getfield	#165; //Field g:I
   238:	iconst_2
   239:	ishr
   240:	istore	6
   242:	iload	6
   244:	bipush	15
   246:	iand
   247:	istore	7
   249:	iload	6
   251:	bipush	8
   253:	ishr
   254:	bipush	15
   256:	iand
   257:	istore	8
   259:	iload	6
   261:	bipush	16
   263:	ishr
   264:	bipush	127
   266:	iand
   267:	istore	9
   269:	aload	5
   271:	iload	7
   273:	iload	9
   275:	iload	8
   277:	invokevirtual	#345; //Method jn.a:(III)I
   280:	istore	10
   282:	iload	7
   284:	iload_3
   285:	iadd
   286:	istore	7
   288:	iload	8
   290:	iload	4
   292:	iadd
   293:	istore	8
   295:	iload	10
   297:	ifne	466
   300:	aload_0
   301:	iload	7
   303:	iload	9
   305:	iload	8
   307:	invokevirtual	#269; //Method h:(III)I
   310:	aload_0
   311:	getfield	#169; //Field l:Ljava/util/Random;
   314:	bipush	8
   316:	invokevirtual	#339; //Method java/util/Random.nextInt:(I)I
   319:	if_icmpgt	466
   322:	aload_0
   323:	getstatic	#114; //Field dj.a:Ldj;
   326:	iload	7
   328:	iload	9
   330:	iload	8
   332:	invokevirtual	#241; //Method a:(Ldj;III)I
   335:	ifgt	466
   338:	aload_0
   339:	iload	7
   341:	i2d
   342:	ldc2_w	#94; //double 0.5d
   345:	dadd
   346:	iload	9
   348:	i2d
   349:	ldc2_w	#94; //double 0.5d
   352:	dadd
   353:	iload	8
   355:	i2d
   356:	ldc2_w	#94; //double 0.5d
   359:	dadd
   360:	ldc2_w	#100; //double 8.0d
   363:	invokevirtual	#231; //Method a:(DDDD)Lft;
   366:	astore	11
   368:	aload	11
   370:	ifnull	466
   373:	aload	11
   375:	iload	7
   377:	i2d
   378:	ldc2_w	#94; //double 0.5d
   381:	dadd
   382:	iload	9
   384:	i2d
   385:	ldc2_w	#94; //double 0.5d
   388:	dadd
   389:	iload	8
   391:	i2d
   392:	ldc2_w	#94; //double 0.5d
   395:	dadd
   396:	invokevirtual	#279; //Method ft.d:(DDD)D
   399:	ldc2_w	#98; //double 4.0d
   402:	dcmpl
   403:	ifle	466
   406:	aload_0
   407:	iload	7
   409:	i2d
   410:	ldc2_w	#94; //double 0.5d
   413:	dadd
   414:	iload	9
   416:	i2d
   417:	ldc2_w	#94; //double 0.5d
   420:	dadd
   421:	iload	8
   423:	i2d
   424:	ldc2_w	#94; //double 0.5d
   427:	dadd
   428:	ldc	#29; //String ambient.cave.cave
   430:	ldc	#7; //float 0.7f
   432:	ldc	#8; //float 0.8f
   434:	aload_0
   435:	getfield	#169; //Field l:Ljava/util/Random;
   438:	invokevirtual	#337; //Method java/util/Random.nextFloat:()F
   441:	ldc	#5; //float 0.2f
   443:	fmul
   444:	fadd
   445:	invokevirtual	#232; //Method a:(DDDLjava/lang/String;FF)V
   448:	aload_0
   449:	aload_0
   450:	getfield	#169; //Field l:Ljava/util/Random;
   453:	sipush	12000
   456:	invokevirtual	#339; //Method java/util/Random.nextInt:(I)I
   459:	sipush	6000
   462:	iadd
   463:	putfield	#157; //Field L:I
   466:	iconst_0
   467:	istore	6
   469:	iload	6
   471:	bipush	80
   473:	if_icmpge	588
   476:	aload_0
   477:	aload_0
   478:	getfield	#165; //Field g:I
   481:	iconst_3
   482:	imul
   483:	aload_0
   484:	getfield	#166; //Field h:I
   487:	iadd
   488:	putfield	#165; //Field g:I
   491:	aload_0
   492:	getfield	#165; //Field g:I
   495:	iconst_2
   496:	ishr
   497:	istore	7
   499:	iload	7
   501:	bipush	15
   503:	iand
   504:	istore	8
   506:	iload	7
   508:	bipush	8
   510:	ishr
   511:	bipush	15
   513:	iand
   514:	istore	9
   516:	iload	7
   518:	bipush	16
   520:	ishr
   521:	bipush	127
   523:	iand
   524:	istore	10
   526:	aload	5
   528:	getfield	#204; //Field jn.b:[B
   531:	iload	8
   533:	bipush	11
   535:	ishl
   536:	iload	9
   538:	bipush	7
   540:	ishl
   541:	ior
   542:	iload	10
   544:	ior
   545:	baload
   546:	istore	11
   548:	getstatic	#197; //Field fw.o:[Z
   551:	iload	11
   553:	baload
   554:	ifeq	582
   557:	getstatic	#196; //Field fw.n:[Lfw;
   560:	iload	11
   562:	aaload
   563:	aload_0
   564:	iload	8
   566:	iload_3
   567:	iadd
   568:	iload	10
   570:	iload	9
   572:	iload	4
   574:	iadd
   575:	aload_0
   576:	getfield	#169; //Field l:Ljava/util/Random;
   579:	invokevirtual	#288; //Method fw.a:(Lel;IIILjava/util/Random;)V
   582:	iinc	6, 1
   585:	goto	469
   588:	goto	162
   591:	return

public boolean a(boolean);
  Code:
   0:	aload_0
   1:	getfield	#148; //Field C:Ljava/util/TreeSet;
   4:	invokevirtual	#344; //Method java/util/TreeSet.size:()I
   7:	istore_2
   8:	iload_2
   9:	aload_0
   10:	getfield	#149; //Field D:Ljava/util/Set;
   13:	invokeinterface	#408,  1; //InterfaceMethod java/util/Set.size:()I
   18:	if_icmpeq	31
   21:	new	#69; //class java/lang/IllegalStateException
   24:	dup
   25:	ldc	#27; //String TickNextTick list out of synch
   27:	invokespecial	#323; //Method java/lang/IllegalStateException."<init>":(Ljava/lang/String;)V
   30:	athrow
   31:	iload_2
   32:	sipush	1000
   35:	if_icmple	42
   38:	sipush	1000
   41:	istore_2
   42:	iconst_0
   43:	istore_3
   44:	iload_3
   45:	iload_2
   46:	if_icmpge	233
   49:	aload_0
   50:	getfield	#148; //Field C:Ljava/util/TreeSet;
   53:	invokevirtual	#342; //Method java/util/TreeSet.first:()Ljava/lang/Object;
   56:	checkcast	#41; //class ci
   59:	astore	4
   61:	iload_1
   62:	ifne	81
   65:	aload	4
   67:	getfield	#113; //Field ci.e:J
   70:	aload_0
   71:	getfield	#163; //Field e:J
   74:	lcmp
   75:	ifle	81
   78:	goto	233
   81:	aload_0
   82:	getfield	#148; //Field C:Ljava/util/TreeSet;
   85:	aload	4
   87:	invokevirtual	#343; //Method java/util/TreeSet.remove:(Ljava/lang/Object;)Z
   90:	pop
   91:	aload_0
   92:	getfield	#149; //Field D:Ljava/util/Set;
   95:	aload	4
   97:	invokeinterface	#407,  2; //InterfaceMethod java/util/Set.remove:(Ljava/lang/Object;)Z
   102:	pop
   103:	bipush	8
   105:	istore	5
   107:	aload_0
   108:	aload	4
   110:	getfield	#109; //Field ci.a:I
   113:	iload	5
   115:	isub
   116:	aload	4
   118:	getfield	#110; //Field ci.b:I
   121:	iload	5
   123:	isub
   124:	aload	4
   126:	getfield	#111; //Field ci.c:I
   129:	iload	5
   131:	isub
   132:	aload	4
   134:	getfield	#109; //Field ci.a:I
   137:	iload	5
   139:	iadd
   140:	aload	4
   142:	getfield	#110; //Field ci.b:I
   145:	iload	5
   147:	iadd
   148:	aload	4
   150:	getfield	#111; //Field ci.c:I
   153:	iload	5
   155:	iadd
   156:	invokevirtual	#237; //Method a:(IIIIII)Z
   159:	ifeq	227
   162:	aload_0
   163:	aload	4
   165:	getfield	#109; //Field ci.a:I
   168:	aload	4
   170:	getfield	#110; //Field ci.b:I
   173:	aload	4
   175:	getfield	#111; //Field ci.c:I
   178:	invokevirtual	#234; //Method a:(III)I
   181:	istore	6
   183:	iload	6
   185:	aload	4
   187:	getfield	#112; //Field ci.d:I
   190:	if_icmpne	227
   193:	iload	6
   195:	ifle	227
   198:	getstatic	#196; //Field fw.n:[Lfw;
   201:	iload	6
   203:	aaload
   204:	aload_0
   205:	aload	4
   207:	getfield	#109; //Field ci.a:I
   210:	aload	4
   212:	getfield	#110; //Field ci.b:I
   215:	aload	4
   217:	getfield	#111; //Field ci.c:I
   220:	aload_0
   221:	getfield	#169; //Field l:Ljava/util/Random;
   224:	invokevirtual	#288; //Method fw.a:(Lel;IIILjava/util/Random;)V
   227:	iinc	3, 1
   230:	goto	44
   233:	aload_0
   234:	getfield	#148; //Field C:Ljava/util/TreeSet;
   237:	invokevirtual	#344; //Method java/util/TreeSet.size:()I
   240:	ifeq	247
   243:	iconst_1
   244:	goto	248
   247:	iconst_0
   248:	ireturn

public java.util.List b(dv, ds);
  Code:
   0:	aload_0
   1:	getfield	#158; //Field M:Ljava/util/List;
   4:	invokeinterface	#397,  1; //InterfaceMethod java/util/List.clear:()V
   9:	aload_2
   10:	getfield	#117; //Field ds.a:D
   13:	ldc2_w	#96; //double 2.0d
   16:	dsub
   17:	ldc2_w	#102; //double 16.0d
   20:	ddiv
   21:	invokestatic	#294; //Method hb.b:(D)I
   24:	istore_3
   25:	aload_2
   26:	getfield	#120; //Field ds.d:D
   29:	ldc2_w	#96; //double 2.0d
   32:	dadd
   33:	ldc2_w	#102; //double 16.0d
   36:	ddiv
   37:	invokestatic	#294; //Method hb.b:(D)I
   40:	istore	4
   42:	aload_2
   43:	getfield	#119; //Field ds.c:D
   46:	ldc2_w	#96; //double 2.0d
   49:	dsub
   50:	ldc2_w	#102; //double 16.0d
   53:	ddiv
   54:	invokestatic	#294; //Method hb.b:(D)I
   57:	istore	5
   59:	aload_2
   60:	getfield	#122; //Field ds.f:D
   63:	ldc2_w	#96; //double 2.0d
   66:	dadd
   67:	ldc2_w	#102; //double 16.0d
   70:	ddiv
   71:	invokestatic	#294; //Method hb.b:(D)I
   74:	istore	6
   76:	iload_3
   77:	istore	7
   79:	iload	7
   81:	iload	4
   83:	if_icmpgt	137
   86:	iload	5
   88:	istore	8
   90:	iload	8
   92:	iload	6
   94:	if_icmpgt	131
   97:	aload_0
   98:	iload	7
   100:	iload	8
   102:	invokespecial	#264; //Method f:(II)Z
   105:	ifeq	125
   108:	aload_0
   109:	iload	7
   111:	iload	8
   113:	invokevirtual	#255; //Method c:(II)Ljn;
   116:	aload_1
   117:	aload_2
   118:	aload_0
   119:	getfield	#158; //Field M:Ljava/util/List;
   122:	invokevirtual	#353; //Method jn.a:(Ldv;Lds;Ljava/util/List;)V
   125:	iinc	8, 1
   128:	goto	90
   131:	iinc	7, 1
   134:	goto	79
   137:	aload_0
   138:	getfield	#158; //Field M:Ljava/util/List;
   141:	areturn

public java.util.List a(java.lang.Class, ds);
  Code:
   0:	aload_2
   1:	getfield	#117; //Field ds.a:D
   4:	ldc2_w	#96; //double 2.0d
   7:	dsub
   8:	ldc2_w	#102; //double 16.0d
   11:	ddiv
   12:	invokestatic	#294; //Method hb.b:(D)I
   15:	istore_3
   16:	aload_2
   17:	getfield	#120; //Field ds.d:D
   20:	ldc2_w	#96; //double 2.0d
   23:	dadd
   24:	ldc2_w	#102; //double 16.0d
   27:	ddiv
   28:	invokestatic	#294; //Method hb.b:(D)I
   31:	istore	4
   33:	aload_2
   34:	getfield	#119; //Field ds.c:D
   37:	ldc2_w	#96; //double 2.0d
   40:	dsub
   41:	ldc2_w	#102; //double 16.0d
   44:	ddiv
   45:	invokestatic	#294; //Method hb.b:(D)I
   48:	istore	5
   50:	aload_2
   51:	getfield	#122; //Field ds.f:D
   54:	ldc2_w	#96; //double 2.0d
   57:	dadd
   58:	ldc2_w	#102; //double 16.0d
   61:	ddiv
   62:	invokestatic	#294; //Method hb.b:(D)I
   65:	istore	6
   67:	new	#74; //class java/util/ArrayList
   70:	dup
   71:	invokespecial	#332; //Method java/util/ArrayList."<init>":()V
   74:	astore	7
   76:	iload_3
   77:	istore	8
   79:	iload	8
   81:	iload	4
   83:	if_icmpgt	135
   86:	iload	5
   88:	istore	9
   90:	iload	9
   92:	iload	6
   94:	if_icmpgt	129
   97:	aload_0
   98:	iload	8
   100:	iload	9
   102:	invokespecial	#264; //Method f:(II)Z
   105:	ifeq	123
   108:	aload_0
   109:	iload	8
   111:	iload	9
   113:	invokevirtual	#255; //Method c:(II)Ljn;
   116:	aload_1
   117:	aload_2
   118:	aload	7
   120:	invokevirtual	#354; //Method jn.a:(Ljava/lang/Class;Lds;Ljava/util/List;)V
   123:	iinc	9, 1
   126:	goto	90
   129:	iinc	8, 1
   132:	goto	79
   135:	aload	7
   137:	areturn

public void b(int, int, int, av);
  Code:
   0:	aload_0
   1:	iload_1
   2:	iload_2
   3:	iload_3
   4:	invokevirtual	#261; //Method e:(III)Z
   7:	ifeq	19
   10:	aload_0
   11:	iload_1
   12:	iload_3
   13:	invokevirtual	#250; //Method b:(II)Ljn;
   16:	invokevirtual	#364; //Method jn.f:()V
   19:	iconst_0
   20:	istore	5
   22:	iload	5
   24:	aload_0
   25:	getfield	#175; //Field r:Ljava/util/List;
   28:	invokeinterface	#402,  1; //InterfaceMethod java/util/List.size:()I
   33:	if_icmpge	66
   36:	aload_0
   37:	getfield	#175; //Field r:Ljava/util/List;
   40:	iload	5
   42:	invokeinterface	#398,  2; //InterfaceMethod java/util/List.get:(I)Ljava/lang/Object;
   47:	checkcast	#37; //class bj
   50:	iload_1
   51:	iload_2
   52:	iload_3
   53:	aload	4
   55:	invokeinterface	#380,  5; //InterfaceMethod bj.a:(IIILav;)V
   60:	iinc	5, 1
   63:	goto	22
   66:	return

public int a(java.lang.Class);
  Code:
   0:	iconst_0
   1:	istore_2
   2:	iconst_0
   3:	istore_3
   4:	iload_3
   5:	aload_0
   6:	getfield	#160; //Field b:Ljava/util/List;
   9:	invokeinterface	#402,  1; //InterfaceMethod java/util/List.size:()I
   14:	if_icmpge	53
   17:	aload_0
   18:	getfield	#160; //Field b:Ljava/util/List;
   21:	iload_3
   22:	invokeinterface	#398,  2; //InterfaceMethod java/util/List.get:(I)Ljava/lang/Object;
   27:	checkcast	#45; //class dv
   30:	astore	4
   32:	aload_1
   33:	aload	4
   35:	invokevirtual	#325; //Method java/lang/Object.getClass:()Ljava/lang/Class;
   38:	invokevirtual	#319; //Method java/lang/Class.isAssignableFrom:(Ljava/lang/Class;)Z
   41:	ifeq	47
   44:	iinc	2, 1
   47:	iinc	3, 1
   50:	goto	4
   53:	iload_2
   54:	ireturn

public void a(java.util.List);
  Code:
   0:	aload_0
   1:	getfield	#160; //Field b:Ljava/util/List;
   4:	aload_1
   5:	invokeinterface	#396,  2; //InterfaceMethod java/util/List.addAll:(Ljava/util/Collection;)Z
   10:	pop
   11:	iconst_0
   12:	istore_2
   13:	iload_2
   14:	aload_1
   15:	invokeinterface	#402,  1; //InterfaceMethod java/util/List.size:()I
   20:	if_icmpge	43
   23:	aload_0
   24:	aload_1
   25:	iload_2
   26:	invokeinterface	#398,  2; //InterfaceMethod java/util/List.get:(I)Ljava/lang/Object;
   31:	checkcast	#45; //class dv
   34:	invokevirtual	#253; //Method b:(Ldv;)V
   37:	iinc	2, 1
   40:	goto	13
   43:	return

public void b(java.util.List);
  Code:
   0:	aload_0
   1:	getfield	#147; //Field B:Ljava/util/List;
   4:	aload_1
   5:	invokeinterface	#396,  2; //InterfaceMethod java/util/List.addAll:(Ljava/util/Collection;)Z
   10:	pop
   11:	return

public boolean a(int, int, int, int, boolean);
  Code:
   0:	aload_0
   1:	iload_2
   2:	iload_3
   3:	iload	4
   5:	invokevirtual	#234; //Method a:(III)I
   8:	istore	6
   10:	getstatic	#196; //Field fw.n:[Lfw;
   13:	iload	6
   15:	aaload
   16:	astore	7
   18:	getstatic	#196; //Field fw.n:[Lfw;
   21:	iload_1
   22:	aaload
   23:	astore	8
   25:	aload	8
   27:	aload_0
   28:	iload_2
   29:	iload_3
   30:	iload	4
   32:	invokevirtual	#292; //Method fw.d:(Lel;III)Lds;
   35:	astore	9
   37:	iload	5
   39:	ifeq	45
   42:	aconst_null
   43:	astore	9
   45:	aload	9
   47:	ifnull	61
   50:	aload_0
   51:	aload	9
   53:	invokevirtual	#244; //Method a:(Lds;)Z
   56:	ifne	61
   59:	iconst_0
   60:	ireturn
   61:	aload	7
   63:	getstatic	#186; //Field fw.B:Lfw;
   66:	if_acmpeq	109
   69:	aload	7
   71:	getstatic	#187; //Field fw.C:Lfw;
   74:	if_acmpeq	109
   77:	aload	7
   79:	getstatic	#188; //Field fw.D:Lfw;
   82:	if_acmpeq	109
   85:	aload	7
   87:	getstatic	#189; //Field fw.E:Lfw;
   90:	if_acmpeq	109
   93:	aload	7
   95:	getstatic	#193; //Field fw.as:Ljm;
   98:	if_acmpeq	109
   101:	aload	7
   103:	getstatic	#191; //Field fw.aT:Lfw;
   106:	if_acmpne	111
   109:	iconst_1
   110:	ireturn
   111:	iload_1
   112:	ifle	135
   115:	aload	7
   117:	ifnonnull	135
   120:	aload	8
   122:	aload_0
   123:	iload_2
   124:	iload_3
   125:	iload	4
   127:	invokevirtual	#284; //Method fw.a:(Lel;III)Z
   130:	ifeq	135
   133:	iconst_1
   134:	ireturn
   135:	iconst_0
   136:	ireturn

public co a(dv, dv, float);
  Code:
   0:	aload_1
   1:	getfield	#135; //Field dv.p:D
   4:	invokestatic	#294; //Method hb.b:(D)I
   7:	istore	4
   9:	aload_1
   10:	getfield	#136; //Field dv.q:D
   13:	invokestatic	#294; //Method hb.b:(D)I
   16:	istore	5
   18:	aload_1
   19:	getfield	#137; //Field dv.r:D
   22:	invokestatic	#294; //Method hb.b:(D)I
   25:	istore	6
   27:	fload_3
   28:	ldc	#12; //float 16.0f
   30:	fadd
   31:	f2i
   32:	istore	7
   34:	iload	4
   36:	iload	7
   38:	isub
   39:	istore	8
   41:	iload	5
   43:	iload	7
   45:	isub
   46:	istore	9
   48:	iload	6
   50:	iload	7
   52:	isub
   53:	istore	10
   55:	iload	4
   57:	iload	7
   59:	iadd
   60:	istore	11
   62:	iload	5
   64:	iload	7
   66:	iadd
   67:	istore	12
   69:	iload	6
   71:	iload	7
   73:	iadd
   74:	istore	13
   76:	new	#47; //class ed
   79:	dup
   80:	aload_0
   81:	iload	8
   83:	iload	9
   85:	iload	10
   87:	iload	11
   89:	iload	12
   91:	iload	13
   93:	invokespecial	#230; //Method ed."<init>":(Lel;IIIIII)V
   96:	astore	14
   98:	new	#49; //class fd
   101:	dup
   102:	aload	14
   104:	invokespecial	#276; //Method fd."<init>":(Lio;)V
   107:	aload_1
   108:	aload_2
   109:	fload_3
   110:	invokevirtual	#278; //Method fd.a:(Ldv;Ldv;F)Lco;
   113:	areturn

public co a(dv, int, int, int, float);
  Code:
   0:	aload_1
   1:	getfield	#135; //Field dv.p:D
   4:	invokestatic	#294; //Method hb.b:(D)I
   7:	istore	6
   9:	aload_1
   10:	getfield	#136; //Field dv.q:D
   13:	invokestatic	#294; //Method hb.b:(D)I
   16:	istore	7
   18:	aload_1
   19:	getfield	#137; //Field dv.r:D
   22:	invokestatic	#294; //Method hb.b:(D)I
   25:	istore	8
   27:	fload	5
   29:	ldc	#10; //float 8.0f
   31:	fadd
   32:	f2i
   33:	istore	9
   35:	iload	6
   37:	iload	9
   39:	isub
   40:	istore	10
   42:	iload	7
   44:	iload	9
   46:	isub
   47:	istore	11
   49:	iload	8
   51:	iload	9
   53:	isub
   54:	istore	12
   56:	iload	6
   58:	iload	9
   60:	iadd
   61:	istore	13
   63:	iload	7
   65:	iload	9
   67:	iadd
   68:	istore	14
   70:	iload	8
   72:	iload	9
   74:	iadd
   75:	istore	15
   77:	new	#47; //class ed
   80:	dup
   81:	aload_0
   82:	iload	10
   84:	iload	11
   86:	iload	12
   88:	iload	13
   90:	iload	14
   92:	iload	15
   94:	invokespecial	#230; //Method ed."<init>":(Lel;IIIIII)V
   97:	astore	16
   99:	new	#49; //class fd
   102:	dup
   103:	aload	16
   105:	invokespecial	#276; //Method fd."<init>":(Lio;)V
   108:	aload_1
   109:	iload_2
   110:	iload_3
   111:	iload	4
   113:	fload	5
   115:	invokevirtual	#277; //Method fd.a:(Ldv;IIIF)Lco;
   118:	areturn

public boolean i(int, int, int, int);
  Code:
   0:	aload_0
   1:	iload_1
   2:	iload_2
   3:	iload_3
   4:	invokevirtual	#234; //Method a:(III)I
   7:	istore	5
   9:	iload	5
   11:	ifne	16
   14:	iconst_0
   15:	ireturn
   16:	getstatic	#196; //Field fw.n:[Lfw;
   19:	iload	5
   21:	aaload
   22:	aload_0
   23:	iload_1
   24:	iload_2
   25:	iload_3
   26:	iload	4
   28:	invokevirtual	#293; //Method fw.d:(Lel;IIII)Z
   31:	ireturn

public boolean m(int, int, int);
  Code:
   0:	aload_0
   1:	iload_1
   2:	iload_2
   3:	iconst_1
   4:	isub
   5:	iload_3
   6:	iconst_0
   7:	invokevirtual	#272; //Method i:(IIII)Z
   10:	ifeq	15
   13:	iconst_1
   14:	ireturn
   15:	aload_0
   16:	iload_1
   17:	iload_2
   18:	iconst_1
   19:	iadd
   20:	iload_3
   21:	iconst_1
   22:	invokevirtual	#272; //Method i:(IIII)Z
   25:	ifeq	30
   28:	iconst_1
   29:	ireturn
   30:	aload_0
   31:	iload_1
   32:	iload_2
   33:	iload_3
   34:	iconst_1
   35:	isub
   36:	iconst_2
   37:	invokevirtual	#272; //Method i:(IIII)Z
   40:	ifeq	45
   43:	iconst_1
   44:	ireturn
   45:	aload_0
   46:	iload_1
   47:	iload_2
   48:	iload_3
   49:	iconst_1
   50:	iadd
   51:	iconst_3
   52:	invokevirtual	#272; //Method i:(IIII)Z
   55:	ifeq	60
   58:	iconst_1
   59:	ireturn
   60:	aload_0
   61:	iload_1
   62:	iconst_1
   63:	isub
   64:	iload_2
   65:	iload_3
   66:	iconst_4
   67:	invokevirtual	#272; //Method i:(IIII)Z
   70:	ifeq	75
   73:	iconst_1
   74:	ireturn
   75:	aload_0
   76:	iload_1
   77:	iconst_1
   78:	iadd
   79:	iload_2
   80:	iload_3
   81:	iconst_5
   82:	invokevirtual	#272; //Method i:(IIII)Z
   85:	ifeq	90
   88:	iconst_1
   89:	ireturn
   90:	iconst_0
   91:	ireturn

public boolean j(int, int, int, int);
  Code:
   0:	aload_0
   1:	iload_1
   2:	iload_2
   3:	iload_3
   4:	invokevirtual	#259; //Method d:(III)Z
   7:	ifeq	18
   10:	aload_0
   11:	iload_1
   12:	iload_2
   13:	iload_3
   14:	invokevirtual	#275; //Method m:(III)Z
   17:	ireturn
   18:	aload_0
   19:	iload_1
   20:	iload_2
   21:	iload_3
   22:	invokevirtual	#234; //Method a:(III)I
   25:	istore	5
   27:	iload	5
   29:	ifne	34
   32:	iconst_0
   33:	ireturn
   34:	getstatic	#196; //Field fw.n:[Lfw;
   37:	iload	5
   39:	aaload
   40:	aload_0
   41:	iload_1
   42:	iload_2
   43:	iload_3
   44:	iload	4
   46:	invokevirtual	#291; //Method fw.b:(Lio;IIII)Z
   49:	ireturn

public boolean n(int, int, int);
  Code:
   0:	aload_0
   1:	iload_1
   2:	iload_2
   3:	iconst_1
   4:	isub
   5:	iload_3
   6:	iconst_0
   7:	invokevirtual	#273; //Method j:(IIII)Z
   10:	ifeq	15
   13:	iconst_1
   14:	ireturn
   15:	aload_0
   16:	iload_1
   17:	iload_2
   18:	iconst_1
   19:	iadd
   20:	iload_3
   21:	iconst_1
   22:	invokevirtual	#273; //Method j:(IIII)Z
   25:	ifeq	30
   28:	iconst_1
   29:	ireturn
   30:	aload_0
   31:	iload_1
   32:	iload_2
   33:	iload_3
   34:	iconst_1
   35:	isub
   36:	iconst_2
   37:	invokevirtual	#273; //Method j:(IIII)Z
   40:	ifeq	45
   43:	iconst_1
   44:	ireturn
   45:	aload_0
   46:	iload_1
   47:	iload_2
   48:	iload_3
   49:	iconst_1
   50:	iadd
   51:	iconst_3
   52:	invokevirtual	#273; //Method j:(IIII)Z
   55:	ifeq	60
   58:	iconst_1
   59:	ireturn
   60:	aload_0
   61:	iload_1
   62:	iconst_1
   63:	isub
   64:	iload_2
   65:	iload_3
   66:	iconst_4
   67:	invokevirtual	#273; //Method j:(IIII)Z
   70:	ifeq	75
   73:	iconst_1
   74:	ireturn
   75:	aload_0
   76:	iload_1
   77:	iconst_1
   78:	iadd
   79:	iload_2
   80:	iload_3
   81:	iconst_5
   82:	invokevirtual	#273; //Method j:(IIII)Z
   85:	ifeq	90
   88:	iconst_1
   89:	ireturn
   90:	iconst_0
   91:	ireturn

public ft a(dv, double);
  Code:
   0:	aload_0
   1:	aload_1
   2:	getfield	#135; //Field dv.p:D
   5:	aload_1
   6:	getfield	#136; //Field dv.q:D
   9:	aload_1
   10:	getfield	#137; //Field dv.r:D
   13:	dload_2
   14:	invokevirtual	#231; //Method a:(DDDD)Lft;
   17:	areturn

public ft a(double, double, double, double);
  Code:
   0:	ldc2_w	#88; //double -1.0d
   3:	dstore	9
   5:	aconst_null
   6:	astore	11
   8:	iconst_0
   9:	istore	12
   11:	iload	12
   13:	aload_0
   14:	getfield	#162; //Field d:Ljava/util/List;
   17:	invokeinterface	#402,  1; //InterfaceMethod java/util/List.size:()I
   22:	if_icmpge	101
   25:	aload_0
   26:	getfield	#162; //Field d:Ljava/util/List;
   29:	iload	12
   31:	invokeinterface	#398,  2; //InterfaceMethod java/util/List.get:(I)Ljava/lang/Object;
   36:	checkcast	#50; //class ft
   39:	astore	13
   41:	aload	13
   43:	dload_1
   44:	dload_3
   45:	dload	5
   47:	invokevirtual	#279; //Method ft.d:(DDD)D
   50:	dstore	14
   52:	dload	7
   54:	dconst_0
   55:	dcmpg
   56:	iflt	70
   59:	dload	14
   61:	dload	7
   63:	dload	7
   65:	dmul
   66:	dcmpg
   67:	ifge	95
   70:	dload	9
   72:	ldc2_w	#88; //double -1.0d
   75:	dcmpl
   76:	ifeq	87
   79:	dload	14
   81:	dload	9
   83:	dcmpg
   84:	ifge	95
   87:	dload	14
   89:	dstore	9
   91:	aload	13
   93:	astore	11
   95:	iinc	12, 1
   98:	goto	11
   101:	aload	11
   103:	areturn

public byte[] c(int, int, int, int, int, int);
  Code:
   0:	iload	4
   2:	iload	5
   4:	imul
   5:	iload	6
   7:	imul
   8:	iconst_5
   9:	imul
   10:	iconst_2
   11:	idiv
   12:	newarray byte
   14:	astore	7
   16:	iload_1
   17:	iconst_4
   18:	ishr
   19:	istore	8
   21:	iload_3
   22:	iconst_4
   23:	ishr
   24:	istore	9
   26:	iload_1
   27:	iload	4
   29:	iadd
   30:	iconst_1
   31:	isub
   32:	iconst_4
   33:	ishr
   34:	istore	10
   36:	iload_3
   37:	iload	6
   39:	iadd
   40:	iconst_1
   41:	isub
   42:	iconst_4
   43:	ishr
   44:	istore	11
   46:	iconst_0
   47:	istore	12
   49:	iload_2
   50:	istore	13
   52:	iload_2
   53:	iload	5
   55:	iadd
   56:	istore	14
   58:	iload	13
   60:	ifge	66
   63:	iconst_0
   64:	istore	13
   66:	iload	14
   68:	sipush	128
   71:	if_icmple	79
   74:	sipush	128
   77:	istore	14
   79:	iload	8
   81:	istore	15
   83:	iload	15
   85:	iload	10
   87:	if_icmpgt	222
   90:	iload_1
   91:	iload	15
   93:	bipush	16
   95:	imul
   96:	isub
   97:	istore	16
   99:	iload_1
   100:	iload	4
   102:	iadd
   103:	iload	15
   105:	bipush	16
   107:	imul
   108:	isub
   109:	istore	17
   111:	iload	16
   113:	ifge	119
   116:	iconst_0
   117:	istore	16
   119:	iload	17
   121:	bipush	16
   123:	if_icmple	130
   126:	bipush	16
   128:	istore	17
   130:	iload	9
   132:	istore	18
   134:	iload	18
   136:	iload	11
   138:	if_icmpgt	216
   141:	iload_3
   142:	iload	18
   144:	bipush	16
   146:	imul
   147:	isub
   148:	istore	19
   150:	iload_3
   151:	iload	6
   153:	iadd
   154:	iload	18
   156:	bipush	16
   158:	imul
   159:	isub
   160:	istore	20
   162:	iload	19
   164:	ifge	170
   167:	iconst_0
   168:	istore	19
   170:	iload	20
   172:	bipush	16
   174:	if_icmple	181
   177:	bipush	16
   179:	istore	20
   181:	aload_0
   182:	iload	15
   184:	iload	18
   186:	invokevirtual	#255; //Method c:(II)Ljn;
   189:	aload	7
   191:	iload	16
   193:	iload	13
   195:	iload	19
   197:	iload	17
   199:	iload	14
   201:	iload	20
   203:	iload	12
   205:	invokevirtual	#355; //Method jn.a:([BIIIIIII)I
   208:	istore	12
   210:	iinc	18, 1
   213:	goto	134
   216:	iinc	15, 1
   219:	goto	83
   222:	aload	7
   224:	areturn

public void h();
  Code:
   0:	new	#61; //class java/io/File
   3:	dup
   4:	aload_0
   5:	getfield	#177; //Field t:Ljava/io/File;
   8:	ldc	#33; //String session.lock
   10:	invokespecial	#310; //Method java/io/File."<init>":(Ljava/io/File;Ljava/lang/String;)V
   13:	astore_1
   14:	new	#59; //class java/io/DataInputStream
   17:	dup
   18:	new	#62; //class java/io/FileInputStream
   21:	dup
   22:	aload_1
   23:	invokespecial	#315; //Method java/io/FileInputStream."<init>":(Ljava/io/File;)V
   26:	invokespecial	#304; //Method java/io/DataInputStream."<init>":(Ljava/io/InputStream;)V
   29:	astore_2
   30:	aload_2
   31:	invokevirtual	#306; //Method java/io/DataInputStream.readLong:()J
   34:	aload_0
   35:	getfield	#151; //Field F:J
   38:	lcmp
   39:	ifeq	52
   42:	new	#51; //class fu
   45:	dup
   46:	ldc	#26; //String The save is being accessed from another location, aborting
   48:	invokespecial	#281; //Method fu."<init>":(Ljava/lang/String;)V
   51:	athrow
   52:	aload_2
   53:	invokevirtual	#305; //Method java/io/DataInputStream.close:()V
   56:	goto	66
   59:	astore_3
   60:	aload_2
   61:	invokevirtual	#305; //Method java/io/DataInputStream.close:()V
   64:	aload_3
   65:	athrow
   66:	goto	80
   69:	astore_1
   70:	new	#51; //class fu
   73:	dup
   74:	ldc	#15; //String Failed to check session lock, aborting
   76:	invokespecial	#281; //Method fu."<init>":(Ljava/lang/String;)V
   79:	athrow
   80:	return
  Exception table:
   from   to  target type
    30    52    59   any
    59    60    59   any
     0    66    69   Class java/io/IOException


static {};
  Code:
   0:	iconst_0
   1:	putstatic	#182; //Field y:I
   4:	return

}

