Compiled from SourceFile
public class jc extends ex implements et{
public static java.util.logging.Logger a;

public bf b;

public boolean c;

public jc(net.minecraft.server.MinecraftServer, bf, eo);
  Code:
   0:	aload_0
   1:	invokespecial	#192; //Method ex."<init>":()V
   4:	aload_0
   5:	iconst_0
   6:	putfield	#148; //Field c:Z
   9:	aload_0
   10:	iconst_0
   11:	putfield	#151; //Field f:I
   14:	aload_0
   15:	iconst_1
   16:	putfield	#155; //Field j:Z
   19:	aload_0
   20:	aconst_null
   21:	putfield	#156; //Field k:Lhh;
   24:	aload_0
   25:	aload_1
   26:	putfield	#149; //Field d:Lnet/minecraft/server/MinecraftServer;
   29:	aload_0
   30:	aload_2
   31:	putfield	#147; //Field b:Lbf;
   34:	aload_2
   35:	aload_0
   36:	invokevirtual	#175; //Method bf.a:(Lex;)V
   39:	aload_0
   40:	aload_3
   41:	putfield	#150; //Field e:Leo;
   44:	aload_3
   45:	aload_0
   46:	putfield	#95; //Field eo.a:Ljc;
   49:	return

public void a();
  Code:
   0:	aload_0
   1:	getfield	#147; //Field b:Lbf;
   4:	invokevirtual	#174; //Method bf.a:()V
   7:	aload_0
   8:	dup
   9:	getfield	#151; //Field f:I
   12:	dup_x1
   13:	iconst_1
   14:	iadd
   15:	putfield	#151; //Field f:I
   18:	bipush	20
   20:	irem
   21:	ifne	38
   24:	aload_0
   25:	getfield	#147; //Field b:Lbf;
   28:	new	#63; //class kc
   31:	dup
   32:	invokespecial	#233; //Method kc."<init>":()V
   35:	invokevirtual	#176; //Method bf.a:(Lim;)V
   38:	return

public void c(java.lang.String);
  Code:
   0:	aload_0
   1:	getfield	#147; //Field b:Lbf;
   4:	new	#61; //class jp
   7:	dup
   8:	aload_1
   9:	invokespecial	#232; //Method jp."<init>":(Ljava/lang/String;)V
   12:	invokevirtual	#176; //Method bf.a:(Lim;)V
   15:	aload_0
   16:	getfield	#147; //Field b:Lbf;
   19:	invokevirtual	#178; //Method bf.c:()V
   22:	aload_0
   23:	getfield	#149; //Field d:Lnet/minecraft/server/MinecraftServer;
   26:	getfield	#166; //Field net/minecraft/server/MinecraftServer.f:Lgl;
   29:	aload_0
   30:	getfield	#150; //Field e:Leo;
   33:	invokevirtual	#198; //Method gl.c:(Leo;)V
   36:	aload_0
   37:	iconst_1
   38:	putfield	#148; //Field c:Z
   41:	return

public void a(gx);
  Code:
   0:	aload_0
   1:	getfield	#155; //Field j:Z
   4:	ifne	56
   7:	aload_1
   8:	getfield	#125; //Field gx.b:D
   11:	aload_0
   12:	getfield	#153; //Field h:D
   15:	dsub
   16:	dstore_2
   17:	aload_1
   18:	getfield	#124; //Field gx.a:D
   21:	aload_0
   22:	getfield	#152; //Field g:D
   25:	dcmpl
   26:	ifne	56
   29:	dload_2
   30:	dload_2
   31:	dmul
   32:	ldc2_w	#70; //double 0.01d
   35:	dcmpg
   36:	ifge	56
   39:	aload_1
   40:	getfield	#126; //Field gx.c:D
   43:	aload_0
   44:	getfield	#154; //Field i:D
   47:	dcmpl
   48:	ifne	56
   51:	aload_0
   52:	iconst_1
   53:	putfield	#155; //Field j:Z
   56:	aload_0
   57:	getfield	#155; //Field j:Z
   60:	ifeq	655
   63:	aload_0
   64:	aload_0
   65:	getfield	#150; //Field e:Leo;
   68:	getfield	#101; //Field eo.p:D
   71:	putfield	#152; //Field g:D
   74:	aload_0
   75:	aload_0
   76:	getfield	#150; //Field e:Leo;
   79:	getfield	#102; //Field eo.q:D
   82:	putfield	#153; //Field h:D
   85:	aload_0
   86:	aload_0
   87:	getfield	#150; //Field e:Leo;
   90:	getfield	#103; //Field eo.r:D
   93:	putfield	#154; //Field i:D
   96:	aload_0
   97:	getfield	#150; //Field e:Leo;
   100:	getfield	#101; //Field eo.p:D
   103:	dstore_2
   104:	aload_0
   105:	getfield	#150; //Field e:Leo;
   108:	getfield	#102; //Field eo.q:D
   111:	dstore	4
   113:	aload_0
   114:	getfield	#150; //Field e:Leo;
   117:	getfield	#103; //Field eo.r:D
   120:	dstore	6
   122:	aload_0
   123:	getfield	#150; //Field e:Leo;
   126:	getfield	#104; //Field eo.v:F
   129:	fstore	8
   131:	aload_0
   132:	getfield	#150; //Field e:Leo;
   135:	getfield	#105; //Field eo.w:F
   138:	fstore	9
   140:	aload_1
   141:	getfield	#131; //Field gx.h:Z
   144:	ifeq	246
   147:	aload_1
   148:	getfield	#124; //Field gx.a:D
   151:	dstore_2
   152:	aload_1
   153:	getfield	#125; //Field gx.b:D
   156:	dstore	4
   158:	aload_1
   159:	getfield	#126; //Field gx.c:D
   162:	dstore	6
   164:	aload_1
   165:	getfield	#127; //Field gx.d:D
   168:	aload_1
   169:	getfield	#125; //Field gx.b:D
   172:	dsub
   173:	dstore	10
   175:	dload	10
   177:	ldc2_w	#82; //double 1.65d
   180:	dcmpl
   181:	ifgt	193
   184:	dload	10
   186:	ldc2_w	#74; //double 0.1d
   189:	dcmpg
   190:	ifge	235
   193:	aload_0
   194:	ldc	#22; //String Illegal stance
   196:	invokevirtual	#226; //Method c:(Ljava/lang/String;)V
   199:	getstatic	#146; //Field a:Ljava/util/logging/Logger;
   202:	new	#56; //class java/lang/StringBuilder
   205:	dup
   206:	invokespecial	#216; //Method java/lang/StringBuilder."<init>":()V
   209:	aload_0
   210:	getfield	#150; //Field e:Leo;
   213:	getfield	#98; //Field eo.ar:Ljava/lang/String;
   216:	invokevirtual	#219; //Method java/lang/StringBuilder.append:(Ljava/lang/String;)Ljava/lang/StringBuilder;
   219:	ldc	#4; //String  had an illegal stance: 
   221:	invokevirtual	#219; //Method java/lang/StringBuilder.append:(Ljava/lang/String;)Ljava/lang/StringBuilder;
   224:	dload	10
   226:	invokevirtual	#217; //Method java/lang/StringBuilder.append:(D)Ljava/lang/StringBuilder;
   229:	invokevirtual	#220; //Method java/lang/StringBuilder.toString:()Ljava/lang/String;
   232:	invokevirtual	#223; //Method java/util/logging/Logger.warning:(Ljava/lang/String;)V
   235:	aload_0
   236:	getfield	#150; //Field e:Leo;
   239:	aload_1
   240:	getfield	#127; //Field gx.d:D
   243:	putfield	#96; //Field eo.aj:D
   246:	aload_1
   247:	getfield	#132; //Field gx.i:Z
   250:	ifeq	265
   253:	aload_1
   254:	getfield	#128; //Field gx.e:F
   257:	fstore	8
   259:	aload_1
   260:	getfield	#129; //Field gx.f:F
   263:	fstore	9
   265:	aload_0
   266:	getfield	#150; //Field e:Leo;
   269:	invokevirtual	#187; //Method eo.k:()V
   272:	aload_0
   273:	getfield	#150; //Field e:Leo;
   276:	fconst_0
   277:	putfield	#94; //Field eo.Q:F
   280:	aload_0
   281:	getfield	#150; //Field e:Leo;
   284:	aload_0
   285:	getfield	#152; //Field g:D
   288:	aload_0
   289:	getfield	#153; //Field h:D
   292:	aload_0
   293:	getfield	#154; //Field i:D
   296:	fload	8
   298:	fload	9
   300:	invokevirtual	#185; //Method eo.b:(DDDFF)V
   303:	dload_2
   304:	aload_0
   305:	getfield	#150; //Field e:Leo;
   308:	getfield	#101; //Field eo.p:D
   311:	dsub
   312:	dstore	10
   314:	dload	4
   316:	aload_0
   317:	getfield	#150; //Field e:Leo;
   320:	getfield	#102; //Field eo.q:D
   323:	dsub
   324:	dstore	12
   326:	dload	6
   328:	aload_0
   329:	getfield	#150; //Field e:Leo;
   332:	getfield	#103; //Field eo.r:D
   335:	dsub
   336:	dstore	14
   338:	ldc	#1; //float 0.0625f
   340:	fstore	16
   342:	aload_0
   343:	getfield	#149; //Field d:Lnet/minecraft/server/MinecraftServer;
   346:	getfield	#165; //Field net/minecraft/server/MinecraftServer.e:Les;
   349:	aload_0
   350:	getfield	#150; //Field e:Leo;
   353:	aload_0
   354:	getfield	#150; //Field e:Leo;
   357:	getfield	#106; //Field eo.z:Lds;
   360:	invokevirtual	#180; //Method ds.b:()Lds;
   363:	fload	16
   365:	f2d
   366:	fload	16
   368:	f2d
   369:	fload	16
   371:	f2d
   372:	invokevirtual	#181; //Method ds.e:(DDD)Lds;
   375:	invokevirtual	#189; //Method es.a:(Ldv;Lds;)Ljava/util/List;
   378:	invokeinterface	#237,  1; //InterfaceMethod java/util/List.size:()I
   383:	ifne	390
   386:	iconst_1
   387:	goto	391
   390:	iconst_0
   391:	istore	17
   393:	aload_0
   394:	getfield	#150; //Field e:Leo;
   397:	dload	10
   399:	dload	12
   401:	dload	14
   403:	invokevirtual	#186; //Method eo.c:(DDD)V
   406:	dload_2
   407:	aload_0
   408:	getfield	#150; //Field e:Leo;
   411:	getfield	#101; //Field eo.p:D
   414:	dsub
   415:	dstore	10
   417:	dload	4
   419:	aload_0
   420:	getfield	#150; //Field e:Leo;
   423:	getfield	#102; //Field eo.q:D
   426:	dsub
   427:	dstore	12
   429:	dload	12
   431:	ldc2_w	#68; //double -0.5d
   434:	dcmpl
   435:	ifgt	447
   438:	dload	12
   440:	ldc2_w	#76; //double 0.5d
   443:	dcmpg
   444:	ifge	450
   447:	dconst_0
   448:	dstore	12
   450:	dload	6
   452:	aload_0
   453:	getfield	#150; //Field e:Leo;
   456:	getfield	#103; //Field eo.r:D
   459:	dsub
   460:	dstore	14
   462:	dload	10
   464:	dload	10
   466:	dmul
   467:	dload	12
   469:	dload	12
   471:	dmul
   472:	dadd
   473:	dload	14
   475:	dload	14
   477:	dmul
   478:	dadd
   479:	dstore	18
   481:	iconst_0
   482:	istore	20
   484:	dload	18
   486:	ldc2_w	#72; //double 0.0625d
   489:	dcmpl
   490:	ifle	527
   493:	iconst_1
   494:	istore	20
   496:	getstatic	#146; //Field a:Ljava/util/logging/Logger;
   499:	new	#56; //class java/lang/StringBuilder
   502:	dup
   503:	invokespecial	#216; //Method java/lang/StringBuilder."<init>":()V
   506:	aload_0
   507:	getfield	#150; //Field e:Leo;
   510:	getfield	#98; //Field eo.ar:Ljava/lang/String;
   513:	invokevirtual	#219; //Method java/lang/StringBuilder.append:(Ljava/lang/String;)Ljava/lang/StringBuilder;
   516:	ldc	#7; //String  moved wrongly!
   518:	invokevirtual	#219; //Method java/lang/StringBuilder.append:(Ljava/lang/String;)Ljava/lang/StringBuilder;
   521:	invokevirtual	#220; //Method java/lang/StringBuilder.toString:()Ljava/lang/String;
   524:	invokevirtual	#223; //Method java/util/logging/Logger.warning:(Ljava/lang/String;)V
   527:	aload_0
   528:	getfield	#150; //Field e:Leo;
   531:	dload_2
   532:	dload	4
   534:	dload	6
   536:	fload	8
   538:	fload	9
   540:	invokevirtual	#185; //Method eo.b:(DDDFF)V
   543:	aload_0
   544:	getfield	#149; //Field d:Lnet/minecraft/server/MinecraftServer;
   547:	getfield	#165; //Field net/minecraft/server/MinecraftServer.e:Les;
   550:	aload_0
   551:	getfield	#150; //Field e:Leo;
   554:	aload_0
   555:	getfield	#150; //Field e:Leo;
   558:	getfield	#106; //Field eo.z:Lds;
   561:	invokevirtual	#180; //Method ds.b:()Lds;
   564:	fload	16
   566:	f2d
   567:	fload	16
   569:	f2d
   570:	fload	16
   572:	f2d
   573:	invokevirtual	#181; //Method ds.e:(DDD)Lds;
   576:	invokevirtual	#189; //Method es.a:(Ldv;Lds;)Ljava/util/List;
   579:	invokeinterface	#237,  1; //InterfaceMethod java/util/List.size:()I
   584:	ifne	591
   587:	iconst_1
   588:	goto	592
   591:	iconst_0
   592:	istore	21
   594:	iload	17
   596:	ifeq	630
   599:	iload	20
   601:	ifne	609
   604:	iload	21
   606:	ifne	630
   609:	aload_0
   610:	aload_0
   611:	getfield	#152; //Field g:D
   614:	aload_0
   615:	getfield	#153; //Field h:D
   618:	aload_0
   619:	getfield	#154; //Field i:D
   622:	fload	8
   624:	fload	9
   626:	invokevirtual	#224; //Method a:(DDDFF)V
   629:	return
   630:	aload_0
   631:	getfield	#150; //Field e:Leo;
   634:	aload_1
   635:	getfield	#130; //Field gx.g:Z
   638:	putfield	#93; //Field eo.A:Z
   641:	aload_0
   642:	getfield	#149; //Field d:Lnet/minecraft/server/MinecraftServer;
   645:	getfield	#166; //Field net/minecraft/server/MinecraftServer.f:Lgl;
   648:	aload_0
   649:	getfield	#150; //Field e:Leo;
   652:	invokevirtual	#197; //Method gl.b:(Leo;)V
   655:	return

public void a(double, double, double, float, float);
  Code:
   0:	aload_0
   1:	iconst_0
   2:	putfield	#155; //Field j:Z
   5:	aload_0
   6:	dload_1
   7:	putfield	#152; //Field g:D
   10:	aload_0
   11:	dload_3
   12:	putfield	#153; //Field h:D
   15:	aload_0
   16:	dload	5
   18:	putfield	#154; //Field i:D
   21:	aload_0
   22:	getfield	#150; //Field e:Leo;
   25:	dload_1
   26:	dload_3
   27:	dload	5
   29:	fload	7
   31:	fload	8
   33:	invokevirtual	#185; //Method eo.b:(DDDFF)V
   36:	aload_0
   37:	getfield	#150; //Field e:Leo;
   40:	getfield	#95; //Field eo.a:Ljc;
   43:	new	#35; //class ec
   46:	dup
   47:	dload_1
   48:	dload_3
   49:	ldc2_w	#80; //double 1.6200000047683716d
   52:	dadd
   53:	dload_3
   54:	dload	5
   56:	fload	7
   58:	fload	8
   60:	iconst_0
   61:	invokespecial	#182; //Method ec."<init>":(DDDDFFZ)V
   64:	invokevirtual	#225; //Method b:(Lim;)V
   67:	return

public void a(hx);
  Code:
   0:	aload_0
   1:	getfield	#150; //Field e:Leo;
   4:	getfield	#97; //Field eo.ak:Lhe;
   7:	getfield	#133; //Field he.a:[Lhh;
   10:	aload_0
   11:	getfield	#150; //Field e:Leo;
   14:	getfield	#97; //Field eo.ak:Lhe;
   17:	getfield	#136; //Field he.d:I
   20:	aload_0
   21:	getfield	#156; //Field k:Lhh;
   24:	aastore
   25:	aload_0
   26:	getfield	#149; //Field d:Lnet/minecraft/server/MinecraftServer;
   29:	getfield	#165; //Field net/minecraft/server/MinecraftServer.e:Les;
   32:	aload_0
   33:	getfield	#149; //Field d:Lnet/minecraft/server/MinecraftServer;
   36:	getfield	#166; //Field net/minecraft/server/MinecraftServer.f:Lgl;
   39:	aload_0
   40:	getfield	#150; //Field e:Leo;
   43:	getfield	#98; //Field eo.ar:Ljava/lang/String;
   46:	invokevirtual	#199; //Method gl.g:(Ljava/lang/String;)Z
   49:	dup_x1
   50:	putfield	#107; //Field es.B:Z
   53:	istore_2
   54:	iconst_0
   55:	istore_3
   56:	aload_1
   57:	getfield	#141; //Field hx.e:I
   60:	ifne	65
   63:	iconst_1
   64:	istore_3
   65:	aload_1
   66:	getfield	#141; //Field hx.e:I
   69:	iconst_1
   70:	if_icmpne	75
   73:	iconst_1
   74:	istore_3
   75:	iload_3
   76:	ifeq	179
   79:	aload_0
   80:	getfield	#150; //Field e:Leo;
   83:	getfield	#102; //Field eo.q:D
   86:	dstore	4
   88:	aload_0
   89:	getfield	#150; //Field e:Leo;
   92:	aload_0
   93:	getfield	#150; //Field e:Leo;
   96:	getfield	#96; //Field eo.aj:D
   99:	putfield	#102; //Field eo.q:D
   102:	aload_0
   103:	getfield	#150; //Field e:Leo;
   106:	ldc2_w	#84; //double 4.0d
   109:	fconst_1
   110:	invokevirtual	#184; //Method eo.a:(DF)Lgk;
   113:	astore	6
   115:	aload_0
   116:	getfield	#150; //Field e:Leo;
   119:	dload	4
   121:	putfield	#102; //Field eo.q:D
   124:	aload	6
   126:	ifnonnull	130
   129:	return
   130:	aload	6
   132:	getfield	#119; //Field gk.b:I
   135:	aload_1
   136:	getfield	#137; //Field hx.a:I
   139:	if_icmpne	178
   142:	aload	6
   144:	getfield	#120; //Field gk.c:I
   147:	aload_1
   148:	getfield	#138; //Field hx.b:I
   151:	if_icmpne	178
   154:	aload	6
   156:	getfield	#121; //Field gk.d:I
   159:	aload_1
   160:	getfield	#139; //Field hx.c:I
   163:	if_icmpne	178
   166:	aload	6
   168:	getfield	#122; //Field gk.e:I
   171:	aload_1
   172:	getfield	#140; //Field hx.d:I
   175:	if_icmpeq	179
   178:	return
   179:	aload_1
   180:	getfield	#137; //Field hx.a:I
   183:	istore	4
   185:	aload_1
   186:	getfield	#138; //Field hx.b:I
   189:	istore	5
   191:	aload_1
   192:	getfield	#139; //Field hx.c:I
   195:	istore	6
   197:	aload_1
   198:	getfield	#140; //Field hx.d:I
   201:	istore	7
   203:	iload	4
   205:	aload_0
   206:	getfield	#149; //Field d:Lnet/minecraft/server/MinecraftServer;
   209:	getfield	#165; //Field net/minecraft/server/MinecraftServer.e:Les;
   212:	getfield	#108; //Field es.m:I
   215:	isub
   216:	i2f
   217:	invokestatic	#202; //Method hb.e:(F)F
   220:	f2i
   221:	istore	8
   223:	iload	6
   225:	aload_0
   226:	getfield	#149; //Field d:Lnet/minecraft/server/MinecraftServer;
   229:	getfield	#165; //Field net/minecraft/server/MinecraftServer.e:Les;
   232:	getfield	#109; //Field es.o:I
   235:	isub
   236:	i2f
   237:	invokestatic	#202; //Method hb.e:(F)F
   240:	f2i
   241:	istore	9
   243:	iload	8
   245:	iload	9
   247:	if_icmple	254
   250:	iload	8
   252:	istore	9
   254:	aload_1
   255:	getfield	#141; //Field hx.e:I
   258:	ifne	291
   261:	iload	9
   263:	bipush	16
   265:	if_icmpgt	272
   268:	iload_2
   269:	ifeq	469
   272:	aload_0
   273:	getfield	#150; //Field e:Leo;
   276:	getfield	#99; //Field eo.c:Ljo;
   279:	iload	4
   281:	iload	5
   283:	iload	6
   285:	invokevirtual	#229; //Method jo.a:(III)V
   288:	goto	469
   291:	aload_1
   292:	getfield	#141; //Field hx.e:I
   295:	iconst_2
   296:	if_icmpne	312
   299:	aload_0
   300:	getfield	#150; //Field e:Leo;
   303:	getfield	#99; //Field eo.c:Ljo;
   306:	invokevirtual	#228; //Method jo.a:()V
   309:	goto	469
   312:	aload_1
   313:	getfield	#141; //Field hx.e:I
   316:	iconst_1
   317:	if_icmpne	352
   320:	iload	9
   322:	bipush	16
   324:	if_icmpgt	331
   327:	iload_2
   328:	ifeq	469
   331:	aload_0
   332:	getfield	#150; //Field e:Leo;
   335:	getfield	#99; //Field eo.c:Ljo;
   338:	iload	4
   340:	iload	5
   342:	iload	6
   344:	iload	7
   346:	invokevirtual	#230; //Method jo.a:(IIII)V
   349:	goto	469
   352:	aload_1
   353:	getfield	#141; //Field hx.e:I
   356:	iconst_3
   357:	if_icmpne	469
   360:	aload_0
   361:	getfield	#150; //Field e:Leo;
   364:	getfield	#101; //Field eo.p:D
   367:	iload	4
   369:	i2d
   370:	ldc2_w	#76; //double 0.5d
   373:	dadd
   374:	dsub
   375:	dstore	10
   377:	aload_0
   378:	getfield	#150; //Field e:Leo;
   381:	getfield	#102; //Field eo.q:D
   384:	iload	5
   386:	i2d
   387:	ldc2_w	#76; //double 0.5d
   390:	dadd
   391:	dsub
   392:	dstore	12
   394:	aload_0
   395:	getfield	#150; //Field e:Leo;
   398:	getfield	#103; //Field eo.r:D
   401:	iload	6
   403:	i2d
   404:	ldc2_w	#76; //double 0.5d
   407:	dadd
   408:	dsub
   409:	dstore	14
   411:	dload	10
   413:	dload	10
   415:	dmul
   416:	dload	12
   418:	dload	12
   420:	dmul
   421:	dadd
   422:	dload	14
   424:	dload	14
   426:	dmul
   427:	dadd
   428:	dstore	16
   430:	dload	16
   432:	ldc2_w	#90; //double 256.0d
   435:	dcmpg
   436:	ifge	469
   439:	aload_0
   440:	getfield	#150; //Field e:Leo;
   443:	getfield	#95; //Field eo.a:Ljc;
   446:	new	#40; //class fi
   449:	dup
   450:	iload	4
   452:	iload	5
   454:	iload	6
   456:	aload_0
   457:	getfield	#149; //Field d:Lnet/minecraft/server/MinecraftServer;
   460:	getfield	#165; //Field net/minecraft/server/MinecraftServer.e:Les;
   463:	invokespecial	#193; //Method fi."<init>":(IIILel;)V
   466:	invokevirtual	#225; //Method b:(Lim;)V
   469:	aload_0
   470:	getfield	#149; //Field d:Lnet/minecraft/server/MinecraftServer;
   473:	getfield	#165; //Field net/minecraft/server/MinecraftServer.e:Les;
   476:	iconst_0
   477:	putfield	#107; //Field es.B:Z
   480:	return

public void a(fv);
  Code:
   0:	aload_0
   1:	getfield	#149; //Field d:Lnet/minecraft/server/MinecraftServer;
   4:	getfield	#165; //Field net/minecraft/server/MinecraftServer.e:Les;
   7:	aload_0
   8:	getfield	#149; //Field d:Lnet/minecraft/server/MinecraftServer;
   11:	getfield	#166; //Field net/minecraft/server/MinecraftServer.f:Lgl;
   14:	aload_0
   15:	getfield	#150; //Field e:Leo;
   18:	getfield	#98; //Field eo.ar:Ljava/lang/String;
   21:	invokevirtual	#199; //Method gl.g:(Ljava/lang/String;)Z
   24:	dup_x1
   25:	putfield	#107; //Field es.B:Z
   28:	istore_2
   29:	aload_1
   30:	getfield	#111; //Field fv.b:I
   33:	istore_3
   34:	aload_1
   35:	getfield	#112; //Field fv.c:I
   38:	istore	4
   40:	aload_1
   41:	getfield	#113; //Field fv.d:I
   44:	istore	5
   46:	aload_1
   47:	getfield	#114; //Field fv.e:I
   50:	istore	6
   52:	iload_3
   53:	aload_0
   54:	getfield	#149; //Field d:Lnet/minecraft/server/MinecraftServer;
   57:	getfield	#165; //Field net/minecraft/server/MinecraftServer.e:Les;
   60:	getfield	#108; //Field es.m:I
   63:	isub
   64:	i2f
   65:	invokestatic	#202; //Method hb.e:(F)F
   68:	f2i
   69:	istore	7
   71:	iload	5
   73:	aload_0
   74:	getfield	#149; //Field d:Lnet/minecraft/server/MinecraftServer;
   77:	getfield	#165; //Field net/minecraft/server/MinecraftServer.e:Les;
   80:	getfield	#109; //Field es.o:I
   83:	isub
   84:	i2f
   85:	invokestatic	#202; //Method hb.e:(F)F
   88:	f2i
   89:	istore	8
   91:	iload	7
   93:	iload	8
   95:	if_icmple	102
   98:	iload	7
   100:	istore	8
   102:	iload	8
   104:	bipush	16
   106:	if_icmpgt	113
   109:	iload_2
   110:	ifeq	168
   113:	aload_1
   114:	getfield	#110; //Field fv.a:I
   117:	iflt	134
   120:	new	#50; //class hh
   123:	dup
   124:	aload_1
   125:	getfield	#110; //Field fv.a:I
   128:	invokespecial	#203; //Method hh."<init>":(I)V
   131:	goto	135
   134:	aconst_null
   135:	astore	9
   137:	aload_0
   138:	getfield	#150; //Field e:Leo;
   141:	getfield	#99; //Field eo.c:Ljo;
   144:	aload_0
   145:	getfield	#150; //Field e:Leo;
   148:	aload_0
   149:	getfield	#149; //Field d:Lnet/minecraft/server/MinecraftServer;
   152:	getfield	#165; //Field net/minecraft/server/MinecraftServer.e:Les;
   155:	aload	9
   157:	iload_3
   158:	iload	4
   160:	iload	5
   162:	iload	6
   164:	invokevirtual	#231; //Method jo.a:(Lft;Lel;Lhh;IIII)Z
   167:	pop
   168:	aload_0
   169:	getfield	#150; //Field e:Leo;
   172:	getfield	#95; //Field eo.a:Ljc;
   175:	new	#40; //class fi
   178:	dup
   179:	iload_3
   180:	iload	4
   182:	iload	5
   184:	aload_0
   185:	getfield	#149; //Field d:Lnet/minecraft/server/MinecraftServer;
   188:	getfield	#165; //Field net/minecraft/server/MinecraftServer.e:Les;
   191:	invokespecial	#193; //Method fi."<init>":(IIILel;)V
   194:	invokevirtual	#225; //Method b:(Lim;)V
   197:	aload_0
   198:	getfield	#149; //Field d:Lnet/minecraft/server/MinecraftServer;
   201:	getfield	#165; //Field net/minecraft/server/MinecraftServer.e:Les;
   204:	iconst_0
   205:	putfield	#107; //Field es.B:Z
   208:	return

public void a(java.lang.String);
  Code:
   0:	getstatic	#146; //Field a:Ljava/util/logging/Logger;
   3:	new	#56; //class java/lang/StringBuilder
   6:	dup
   7:	invokespecial	#216; //Method java/lang/StringBuilder."<init>":()V
   10:	aload_0
   11:	getfield	#150; //Field e:Leo;
   14:	getfield	#98; //Field eo.ar:Ljava/lang/String;
   17:	invokevirtual	#219; //Method java/lang/StringBuilder.append:(Ljava/lang/String;)Ljava/lang/StringBuilder;
   20:	ldc	#6; //String  lost connection: 
   22:	invokevirtual	#219; //Method java/lang/StringBuilder.append:(Ljava/lang/String;)Ljava/lang/StringBuilder;
   25:	aload_1
   26:	invokevirtual	#219; //Method java/lang/StringBuilder.append:(Ljava/lang/String;)Ljava/lang/StringBuilder;
   29:	invokevirtual	#220; //Method java/lang/StringBuilder.toString:()Ljava/lang/String;
   32:	invokevirtual	#222; //Method java/util/logging/Logger.info:(Ljava/lang/String;)V
   35:	aload_0
   36:	getfield	#149; //Field d:Lnet/minecraft/server/MinecraftServer;
   39:	getfield	#166; //Field net/minecraft/server/MinecraftServer.f:Lgl;
   42:	aload_0
   43:	getfield	#150; //Field e:Leo;
   46:	invokevirtual	#198; //Method gl.c:(Leo;)V
   49:	aload_0
   50:	iconst_1
   51:	putfield	#148; //Field c:Z
   54:	return

public void a(im);
  Code:
   0:	getstatic	#146; //Field a:Ljava/util/logging/Logger;
   3:	new	#56; //class java/lang/StringBuilder
   6:	dup
   7:	invokespecial	#216; //Method java/lang/StringBuilder."<init>":()V
   10:	aload_0
   11:	invokevirtual	#205; //Method java/lang/Object.getClass:()Ljava/lang/Class;
   14:	invokevirtual	#218; //Method java/lang/StringBuilder.append:(Ljava/lang/Object;)Ljava/lang/StringBuilder;
   17:	ldc	#11; //String  wasn't prepared to deal with a 
   19:	invokevirtual	#219; //Method java/lang/StringBuilder.append:(Ljava/lang/String;)Ljava/lang/StringBuilder;
   22:	aload_1
   23:	invokevirtual	#205; //Method java/lang/Object.getClass:()Ljava/lang/Class;
   26:	invokevirtual	#218; //Method java/lang/StringBuilder.append:(Ljava/lang/Object;)Ljava/lang/StringBuilder;
   29:	invokevirtual	#220; //Method java/lang/StringBuilder.toString:()Ljava/lang/String;
   32:	invokevirtual	#223; //Method java/util/logging/Logger.warning:(Ljava/lang/String;)V
   35:	aload_0
   36:	ldc	#24; //String Protocol error, unexpected packet
   38:	invokevirtual	#226; //Method c:(Ljava/lang/String;)V
   41:	return

public void b(im);
  Code:
   0:	aload_0
   1:	getfield	#147; //Field b:Lbf;
   4:	aload_1
   5:	invokevirtual	#176; //Method bf.a:(Lim;)V
   8:	return

public void a(gn);
  Code:
   0:	aload_1
   1:	getfield	#123; //Field gn.b:I
   4:	istore_2
   5:	aload_0
   6:	getfield	#150; //Field e:Leo;
   9:	getfield	#97; //Field eo.ak:Lhe;
   12:	aload_0
   13:	getfield	#150; //Field e:Leo;
   16:	getfield	#97; //Field eo.ak:Lhe;
   19:	getfield	#133; //Field he.a:[Lhh;
   22:	arraylength
   23:	iconst_1
   24:	isub
   25:	putfield	#136; //Field he.d:I
   28:	iload_2
   29:	ifne	40
   32:	aload_0
   33:	aconst_null
   34:	putfield	#156; //Field k:Lhh;
   37:	goto	52
   40:	aload_0
   41:	new	#50; //class hh
   44:	dup
   45:	iload_2
   46:	invokespecial	#203; //Method hh."<init>":(I)V
   49:	putfield	#156; //Field k:Lhh;
   52:	aload_0
   53:	getfield	#150; //Field e:Leo;
   56:	getfield	#97; //Field eo.ak:Lhe;
   59:	getfield	#133; //Field he.a:[Lhh;
   62:	aload_0
   63:	getfield	#150; //Field e:Leo;
   66:	getfield	#97; //Field eo.ak:Lhe;
   69:	getfield	#136; //Field he.d:I
   72:	aload_0
   73:	getfield	#156; //Field k:Lhh;
   76:	aastore
   77:	aload_0
   78:	getfield	#149; //Field d:Lnet/minecraft/server/MinecraftServer;
   81:	getfield	#167; //Field net/minecraft/server/MinecraftServer.k:Lgp;
   84:	aload_0
   85:	getfield	#150; //Field e:Leo;
   88:	new	#45; //class gn
   91:	dup
   92:	aload_0
   93:	getfield	#150; //Field e:Leo;
   96:	getfield	#100; //Field eo.g:I
   99:	iload_2
   100:	invokespecial	#200; //Method gn."<init>":(II)V
   103:	invokevirtual	#201; //Method gp.a:(Ldv;Lim;)V
   106:	return

public void a(k);
  Code:
   0:	aload_1
   1:	getfield	#157; //Field k.b:I
   4:	i2d
   5:	ldc2_w	#86; //double 32.0d
   8:	ddiv
   9:	dstore_2
   10:	aload_1
   11:	getfield	#158; //Field k.c:I
   14:	i2d
   15:	ldc2_w	#86; //double 32.0d
   18:	ddiv
   19:	dstore	4
   21:	aload_1
   22:	getfield	#159; //Field k.d:I
   25:	i2d
   26:	ldc2_w	#86; //double 32.0d
   29:	ddiv
   30:	dstore	6
   32:	new	#42; //class gf
   35:	dup
   36:	aload_0
   37:	getfield	#149; //Field d:Lnet/minecraft/server/MinecraftServer;
   40:	getfield	#165; //Field net/minecraft/server/MinecraftServer.e:Les;
   43:	dload_2
   44:	dload	4
   46:	dload	6
   48:	new	#50; //class hh
   51:	dup
   52:	aload_1
   53:	getfield	#163; //Field k.h:I
   56:	aload_1
   57:	getfield	#164; //Field k.i:I
   60:	invokespecial	#204; //Method hh."<init>":(II)V
   63:	invokespecial	#194; //Method gf."<init>":(Lel;DDDLhh;)V
   66:	astore	8
   68:	aload	8
   70:	aload_1
   71:	getfield	#160; //Field k.e:B
   74:	i2d
   75:	ldc2_w	#88; //double 128.0d
   78:	ddiv
   79:	putfield	#116; //Field gf.s:D
   82:	aload	8
   84:	aload_1
   85:	getfield	#161; //Field k.f:B
   88:	i2d
   89:	ldc2_w	#88; //double 128.0d
   92:	ddiv
   93:	putfield	#117; //Field gf.t:D
   96:	aload	8
   98:	aload_1
   99:	getfield	#162; //Field k.g:B
   102:	i2d
   103:	ldc2_w	#88; //double 128.0d
   106:	ddiv
   107:	putfield	#118; //Field gf.u:D
   110:	aload	8
   112:	bipush	10
   114:	putfield	#115; //Field gf.c:I
   117:	aload_0
   118:	getfield	#149; //Field d:Lnet/minecraft/server/MinecraftServer;
   121:	getfield	#165; //Field net/minecraft/server/MinecraftServer.e:Les;
   124:	aload	8
   126:	invokevirtual	#188; //Method es.a:(Ldv;)Z
   129:	pop
   130:	return

public void a(be);
  Code:
   0:	aload_1
   1:	getfield	#92; //Field be.a:Ljava/lang/String;
   4:	astore_2
   5:	aload_2
   6:	invokevirtual	#210; //Method java/lang/String.length:()I
   9:	bipush	100
   11:	if_icmple	21
   14:	aload_0
   15:	ldc	#20; //String Chat message too long
   17:	invokevirtual	#226; //Method c:(Ljava/lang/String;)V
   20:	return
   21:	aload_2
   22:	invokevirtual	#215; //Method java/lang/String.trim:()Ljava/lang/String;
   25:	astore_2
   26:	iconst_0
   27:	istore_3
   28:	iload_3
   29:	aload_2
   30:	invokevirtual	#210; //Method java/lang/String.length:()I
   33:	if_icmpge	62
   36:	ldc	#3; //String  !\"#$%&'()*+,-./0123456789:;<=>?@ABCDEFGHIJKLMNOPQRSTUVWXYZ[\]^_'abcdefghijklmnopqrstuvwxyz{|}~⌂ÇüéâäàåçêëèïîìÄÅÉæÆôöòûùÿÖÜø£Ø×ƒáíóúñÑªº¿®¬½¼¡«»
   38:	aload_2
   39:	iload_3
   40:	invokevirtual	#206; //Method java/lang/String.charAt:(I)C
   43:	invokevirtual	#208; //Method java/lang/String.indexOf:(I)I
   46:	ifge	56
   49:	aload_0
   50:	ldc	#21; //String Illegal characters in chat
   52:	invokevirtual	#226; //Method c:(Ljava/lang/String;)V
   55:	return
   56:	iinc	3, 1
   59:	goto	28
   62:	aload_2
   63:	ldc	#14; //String /
   65:	invokevirtual	#212; //Method java/lang/String.startsWith:(Ljava/lang/String;)Z
   68:	ifeq	79
   71:	aload_0
   72:	aload_2
   73:	invokespecial	#227; //Method d:(Ljava/lang/String;)V
   76:	goto	139
   79:	new	#56; //class java/lang/StringBuilder
   82:	dup
   83:	invokespecial	#216; //Method java/lang/StringBuilder."<init>":()V
   86:	ldc	#18; //String <
   88:	invokevirtual	#219; //Method java/lang/StringBuilder.append:(Ljava/lang/String;)Ljava/lang/StringBuilder;
   91:	aload_0
   92:	getfield	#150; //Field e:Leo;
   95:	getfield	#98; //Field eo.ar:Ljava/lang/String;
   98:	invokevirtual	#219; //Method java/lang/StringBuilder.append:(Ljava/lang/String;)Ljava/lang/StringBuilder;
   101:	ldc	#19; //String > 
   103:	invokevirtual	#219; //Method java/lang/StringBuilder.append:(Ljava/lang/String;)Ljava/lang/StringBuilder;
   106:	aload_2
   107:	invokevirtual	#219; //Method java/lang/StringBuilder.append:(Ljava/lang/String;)Ljava/lang/StringBuilder;
   110:	invokevirtual	#220; //Method java/lang/StringBuilder.toString:()Ljava/lang/String;
   113:	astore_2
   114:	getstatic	#146; //Field a:Ljava/util/logging/Logger;
   117:	aload_2
   118:	invokevirtual	#222; //Method java/util/logging/Logger.info:(Ljava/lang/String;)V
   121:	aload_0
   122:	getfield	#149; //Field d:Lnet/minecraft/server/MinecraftServer;
   125:	getfield	#166; //Field net/minecraft/server/MinecraftServer.f:Lgl;
   128:	new	#32; //class be
   131:	dup
   132:	aload_2
   133:	invokespecial	#173; //Method be."<init>":(Ljava/lang/String;)V
   136:	invokevirtual	#195; //Method gl.a:(Lim;)V
   139:	return

public void a(p);
  Code:
   0:	aload_1
   1:	getfield	#168; //Field p.b:I
   4:	iconst_1
   5:	if_icmpne	15
   8:	aload_0
   9:	getfield	#150; //Field e:Leo;
   12:	invokevirtual	#183; //Method eo.E:()V
   15:	return

public void a(jp);
  Code:
   0:	aload_0
   1:	getfield	#147; //Field b:Lbf;
   4:	ldc	#25; //String Quitting
   6:	invokevirtual	#177; //Method bf.a:(Ljava/lang/String;)V
   9:	return

public int b();
  Code:
   0:	aload_0
   1:	getfield	#147; //Field b:Lbf;
   4:	invokevirtual	#179; //Method bf.d:()I
   7:	ireturn

public void b(java.lang.String);
  Code:
   0:	aload_0
   1:	new	#32; //class be
   4:	dup
   5:	new	#56; //class java/lang/StringBuilder
   8:	dup
   9:	invokespecial	#216; //Method java/lang/StringBuilder."<init>":()V
   12:	ldc	#29; //String §7
   14:	invokevirtual	#219; //Method java/lang/StringBuilder.append:(Ljava/lang/String;)Ljava/lang/StringBuilder;
   17:	aload_1
   18:	invokevirtual	#219; //Method java/lang/StringBuilder.append:(Ljava/lang/String;)Ljava/lang/StringBuilder;
   21:	invokevirtual	#220; //Method java/lang/StringBuilder.toString:()Ljava/lang/String;
   24:	invokespecial	#173; //Method be."<init>":(Ljava/lang/String;)V
   27:	invokevirtual	#225; //Method b:(Lim;)V
   30:	return

public java.lang.String c();
  Code:
   0:	aload_0
   1:	getfield	#150; //Field e:Leo;
   4:	getfield	#98; //Field eo.ar:Ljava/lang/String;
   7:	areturn

public void a(s);
  Code:
   0:	aload_1
   1:	getfield	#169; //Field s.a:I
   4:	iconst_m1
   5:	if_icmpne	22
   8:	aload_0
   9:	getfield	#150; //Field e:Leo;
   12:	getfield	#97; //Field eo.ak:Lhe;
   15:	aload_1
   16:	getfield	#170; //Field s.b:[Lhh;
   19:	putfield	#133; //Field he.a:[Lhh;
   22:	aload_1
   23:	getfield	#169; //Field s.a:I
   26:	bipush	-2
   28:	if_icmpne	45
   31:	aload_0
   32:	getfield	#150; //Field e:Leo;
   35:	getfield	#97; //Field eo.ak:Lhe;
   38:	aload_1
   39:	getfield	#170; //Field s.b:[Lhh;
   42:	putfield	#135; //Field he.c:[Lhh;
   45:	aload_1
   46:	getfield	#169; //Field s.a:I
   49:	bipush	-3
   51:	if_icmpne	68
   54:	aload_0
   55:	getfield	#150; //Field e:Leo;
   58:	getfield	#97; //Field eo.ak:Lhe;
   61:	aload_1
   62:	getfield	#170; //Field s.b:[Lhh;
   65:	putfield	#134; //Field he.b:[Lhh;
   68:	return

public void d();
  Code:
   0:	aload_0
   1:	getfield	#147; //Field b:Lbf;
   4:	new	#66; //class s
   7:	dup
   8:	iconst_m1
   9:	aload_0
   10:	getfield	#150; //Field e:Leo;
   13:	getfield	#97; //Field eo.ak:Lhe;
   16:	getfield	#133; //Field he.a:[Lhh;
   19:	invokespecial	#235; //Method s."<init>":(I[Lhh;)V
   22:	invokevirtual	#176; //Method bf.a:(Lim;)V
   25:	aload_0
   26:	getfield	#147; //Field b:Lbf;
   29:	new	#66; //class s
   32:	dup
   33:	bipush	-2
   35:	aload_0
   36:	getfield	#150; //Field e:Leo;
   39:	getfield	#97; //Field eo.ak:Lhe;
   42:	getfield	#135; //Field he.c:[Lhh;
   45:	invokespecial	#235; //Method s."<init>":(I[Lhh;)V
   48:	invokevirtual	#176; //Method bf.a:(Lim;)V
   51:	aload_0
   52:	getfield	#147; //Field b:Lbf;
   55:	new	#66; //class s
   58:	dup
   59:	bipush	-3
   61:	aload_0
   62:	getfield	#150; //Field e:Leo;
   65:	getfield	#97; //Field eo.ak:Lhe;
   68:	getfield	#134; //Field he.b:[Lhh;
   71:	invokespecial	#235; //Method s."<init>":(I[Lhh;)V
   74:	invokevirtual	#176; //Method bf.a:(Lim;)V
   77:	return

public void a(ja);
  Code:
   0:	aload_1
   1:	getfield	#145; //Field ja.e:Lt;
   4:	ldc	#26; //String x
   6:	invokevirtual	#236; //Method t.d:(Ljava/lang/String;)I
   9:	aload_1
   10:	getfield	#142; //Field ja.a:I
   13:	if_icmpeq	17
   16:	return
   17:	aload_1
   18:	getfield	#145; //Field ja.e:Lt;
   21:	ldc	#27; //String y
   23:	invokevirtual	#236; //Method t.d:(Ljava/lang/String;)I
   26:	aload_1
   27:	getfield	#143; //Field ja.b:I
   30:	if_icmpeq	34
   33:	return
   34:	aload_1
   35:	getfield	#145; //Field ja.e:Lt;
   38:	ldc	#28; //String z
   40:	invokevirtual	#236; //Method t.d:(Ljava/lang/String;)I
   43:	aload_1
   44:	getfield	#144; //Field ja.c:I
   47:	if_icmpeq	51
   50:	return
   51:	aload_0
   52:	getfield	#149; //Field d:Lnet/minecraft/server/MinecraftServer;
   55:	getfield	#165; //Field net/minecraft/server/MinecraftServer.e:Les;
   58:	aload_1
   59:	getfield	#142; //Field ja.a:I
   62:	aload_1
   63:	getfield	#143; //Field ja.b:I
   66:	aload_1
   67:	getfield	#144; //Field ja.c:I
   70:	invokevirtual	#191; //Method es.k:(III)Lav;
   73:	astore_2
   74:	aload_2
   75:	ifnull	94
   78:	aload_2
   79:	aload_1
   80:	getfield	#145; //Field ja.e:Lt;
   83:	invokevirtual	#171; //Method av.a:(Lt;)V
   86:	goto	90
   89:	astore_3
   90:	aload_2
   91:	invokevirtual	#172; //Method av.c:()V
   94:	return
  Exception table:
   from   to  target type
    78    86    89   Class java/lang/Exception


static {};
  Code:
   0:	ldc	#23; //String Minecraft
   2:	invokestatic	#221; //Method java/util/logging/Logger.getLogger:(Ljava/lang/String;)Ljava/util/logging/Logger;
   5:	putstatic	#146; //Field a:Ljava/util/logging/Logger;
   8:	return

}

